Workbook

Sheet 00_Instrucciones
A1: MASTER CONEXIÓN FORMULARIO → ORDEN DE TRABAJO IM
A2: Objetivo | B2: Recibir solicitudes de Microsoft Forms, normalizarlas y generar automáticamente una OT maestra con trazabilidad de Diseño, Preprensa, Producción, Calidad y Cierre.
A3: Paso | B3: Responsable | C3: Acción en el archivo | D3: Hoja | E3: Resultado esperado | F3: Observación
A4: 1 | B4: Cliente interno | C4: Diligencia Microsoft Forms | D4: Formulario externo | E4: Registro de solicitud | F4: Link en hoja Catalogos
A5: 2 | B5: Coordinador / Imprenta | C5: Pega o actualiza export de Forms en 01_Forms_Raw | D5: 01_Forms_Raw | E5: Datos crudos recibidos | F5: No editar fórmulas en hojas 02 y 03
A6: 3 | B6: Sistema Excel | C6: Normaliza campos, genera número OT y valida información | D6: 02_Base_Solicitudes | E6: Solicitud lista para OT | F6: Campos verdes = calculados
A7: 4 | B7: Diseño / Comunicaciones | C7: Completa arte, aprobación del cliente y proveedor de planchas | D7: 03_OT_Maestra | E7: Diseño aprobado o pendiente | F7: Campos amarillos = editar
A8: 5 | B8: Preprensa / Imprenta | C8: Completa especificación técnica, material, máquina, inventario y producción | D8: 03_OT_Maestra | E8: OT lista para producir | F8: Incluye input del Sr. Julio / operador
A9: 6 | B9: Calidad / Cierre | C9: Registra control de calidad, entrega, fecha cierre y estado | D9: 03_OT_Maestra | E9: Trazabilidad completa y KPIs | F9: Dashboard automático
A11: Convención de colores | B11: Azul = encabezados | C11: Amarillo = campos editables | D11: Verde = campos calculados | E11: Naranja = alertas / SLA
A13: A (concepto) | B13: B (regla)
A14: Regla de unidades | B14: Entrega Parcial y Cantidad producida miden cosas distintas. Nunca se suman entre sí.
A15: Entrega Parcial | B15: Acumulado entregado a la fecha. Se sobrescribe en cada entrega con el nuevo acumulado (ej. 146 → 288 → 500). Nunca se digita solo lo de esa entrega.
A16: Cantidad producida | B16: Total final de unidades terminadas. Se llena al cerrar la OT. No usar para avances parciales.
A17: Mientras la OT está abierta | B17: Solo se actualiza Entrega Parcial. El dashboard la toma como contador de unidades producidas.
A18: Al cerrar la OT | B18: Se digita Cantidad producida (valor final) y Fecha cierre. El parcial se deja como quedó. El KPI usa únicamente Cantidad producida.
A19: Producido ≠ entregado | B19: Si difieren (ej. 1.152 producidas, 1.000 entregadas), se deja así. La diferencia es inventario y debe quedar explicada en Observaciones cierre.
A20: Integridad Estado OT ↔ Fecha cierre | B20: Fecha cierre y Estado OT = Cerrada van siempre juntos. Primero se selecciona el Estado OT y luego se digita la fecha (Excel no deja digitar Fecha cierre si el estado no es Cerrada). La columna Integridad (AK) marca en rojo "⚠ Cerrada incompleta" (Cerrada sin Fecha entrega, Recibido por o Fecha cierre) o "⚠ Fecha cierre con estado abierto". Solo "OK" se considera válida; el dashboard muestra una alerta por cada inconsistencia.
A21: Fuentes internas del proyecto
A22: Solicitud Servicio_V1_Imprenta UM.xlsx | B22: Export de Microsoft Forms con campos del solicitante y solicitudes ejemplo
A23: OT_Maestra_V1_Imprenta_UM_Modelo.xlsx | B23: Base conceptual de OT Maestra con secciones de diseño, preprensa, producción y cierre
A24: Flujo Proceso_Imprenta_UM v1.2.pptx / Proyecto Reactivación PDF | B24: Proceso recomendado: Solicitud Digital → Diseño → Compras Planchas → Preprensa → Producción → Calidad → Entrega/KPIs
A26: Control de versiones
A27: v2 (2026-08-13) | B27: 03_OT_Maestra: "Estado OT" se reubica junto a "Fecha cierre"; se elimina "Versión diseño". Se actualizaron OTMaestraTable, 04_OT_Print001 y 06_Dashboard. Base preparada para automatización (Power Automate).
A29: v2.1 (2026-10-05) | B29: 03_OT_Maestra: se define la regla de unidades Entrega Parcial (acumulado entregado, se sobrescribe) vs. Cantidad producida (total final al cierre). El dashboard usa el parcial como contador en OTs abiertas y Cantidad producida en OTs cerradas. Sin cambios de columnas ni fórmulas.
A30: v2.2 (2026-10-07) | B30: 03_OT_Maestra: se agrega la columna AK "Integridad" (Estado OT vs. Fecha cierre) con formato condicional rojo/verde; Observaciones cierre pasa de AK a AL. Validación personalizada en Fecha cierre (AG): solo se digita si Estado OT = Cerrada. Regla documentada en 00_Instrucciones fila 20.

Sheet 01_Forms_Raw
A1: Id | B1: Start time | C1: Completion time | D1: Dependencia / Área solicitante | E1: Nombre del solicitante | F1: Cargo | G1: Correo institucional | H1: Fecha de solicitud | I1: Nombre del trabajo solicitado | J1: Tipo de pieza gráfica | K1: Cantidad requerida | L1: Fecha requerida de entrega | M1: Comentarios adicionales
A2: 1 | B2: 46164.682 | C2: 46164.686 | D2: Rectoria - Comunicaciones y Mercadeo | E2: Camilo Robledo | F2: Coordinador Contenido | G2: coordinadordecontenidos@unimetro.edu.co | H2: 46185 | I2: Miniblocks - Mercadeo / pieza promocional unimetro | J2: MiniBlocks | K2: 750 | L2: 46233 | M2: Mini Blocks pedido de Vicerrectoria. Se entregan 50 unidades a Julio Higgins para campaña mercadeo del Dpto de Diseño y Comunicaciones. El resto de la producción se entregará a Rectoría
A3: 2 | B3: 46164.686 | C3: 46164.688 | D3: Rectoria - Comunicaciones y Mercadeo | E3: Camilo Robledo | F3: Coordinador Comunicaciones | G3: coordinadordecontenidos@unimetro.edu.co | H3: 46185 | I3: Memos - pieza de mercadeo para el area de comunicaciones | J3: Memos | K3: 570 | L3: 46310 | M3: Mini Memos pedido de Vicerrectoria. Se entregan 50 unidades a Julio Higgins para campaña mercadeo del Dpto de Diseño y Comunicaciones
A4: 3 | B4: 46164.69 | C4: 46164.704 | D4: Vicerrectoria | E4: Jose Luis Castro Guerra | F4: Vicerrector | G4: vice-rectoria@unimetro.edu.co | H4: 46160 | I4: Agendas - Material interno y de distribución externa para segundo semestre 2026 | J4: Agendas | K4: 500 | L4: 46230 | M4: Material de la Agendas ya se adquirió. Al 11 de Junio la planchas están en proceso de elaboración por proveedor. Se requiere tecnico empastador para apoyar con el ensamble de las agendas
A5: 4 | B5: 46164.704 | C5: 46164.737 | D5: Vicerrectoria | E5: Jose Luis Castro | F5: Vicerrector | G5: vice-rectoria@unimetro.edu.co | H5: 46254 | I5: Abanicos - Material de promoción de la universidad | J5: Abanicos | K5: 1500 | L5: 46324 | M5: Los abanicos hacen parte de un material de promoción. Todavía no tiene aprobación de Rectoría
A6: 5 | B6: 46167.394 | C6: 46167.397 | D6: Vicerrectoria | E6: Indira Luz de la Rosa | F6: Asistente Vicerectoria | G6: idelarosa@unimetro.edu.co | H6: 46153 | I6: Actas de Grado | J6: Actas de grado | K6: 1000 | L6: 46184 | M6: Cotizar papel Opalina . Sr Julio Rivera consiguió la cotización de 150 pliegos en Dipaca - distribuidora papelera del caribe.
A7: 6 | B7: 46167.398 | C7: 46167.41 | D7: Vicerrectoria - Biblioteca | E7: Yarima Medrano Nazzer | F7: Directora Biblioteca | G7: directorabiblioteca@unimetro.edu.co | H7: 46121 | I7: Tarjetas de Prestamo | J7: Tarjetas Prestamo Biblioteca | K7: 5000 | L7: 46259 | M7: Esta solicitud tuvo una demora causada por el material que llego solo hasta el 4 de mayo.
A8: 7 | B8: 46167.41 | C8: 46167.413 | D8: Vicerrectoria - Biblioteca | E8: Yarima Medrano Nazzer | F8: Directora Biblioteca | G8: directorabiblioteca@unimetro.edu.co | H8: 46121 | I8: Bolsillos de tarjeta de préstamo | J8: Bolsillos de tarjeta de préstamo | K8: 2000 | L8: 46259 | M8: Material pedido en Febrero solo se recepcionó hasta inicios de Mayo.
A9: 8 | B9: 46167.413 | C9: 46167.419 | D9: Vicerrectoria - Biblioteca | E9: Yarima Medrano Nazzer | F9: Directora Biblioteca | G9: directorabiblioteca@unimetro.edu.co | H9: 46121 | I9: Adhesivos de Colores para categorizar grupos de Libros | J9: Adhesivos de Colores | K9: 1300 | L9: 46155 | M9: Se realizaran adhesivos tamaño carta Amarillo, verde, rosado, gris, azul - 500/200/200/200/200. Se entregaron el 11 de Mayo
A10: 9 | B10: 46177.929 | C10: 46177.93 | D10: Vicerrectoria - Direccion Administrativa | E10: Elio Ortiz | F10: Director Administrativo | G10: eortizg@unimetro.edu.co | H10: 46170 | I10: Hojas membretadas uso institucional para varias dependencias | J10: Hojas Membreteadas | K10: 5000 | L10: 46249 | M10: Se estima que para finalesde junio se debe tener la hojas membretadas para el uso en varias dependencias.
A11: 10 | B11: 46178.649 | C11: 46178.655 | D11: Rectoria - Alta consejeria | E11: Julian Ramirez | F11: Coordinador Imprenta UM | G11: jramirezo@unimetro.edu.co | H11: 46155 | I11: Individuales para bandejas de plazoleta de comidas | J11: Individuales para bandejas | K11: 3600 | L11: 46254 | M11: Este proyecto de los individuales para bandejas lo está impulsando la rectoria de la universidad como parte de ¨awarness¨ en lugares externos a UM. Todavia no se tiene claridad el número completo de ejemplares a realizar. Se ingresa el pedido para darle trazabilidad.
A12: 11 | B12: 46182.603 | C12: 46182.617 | D12: Rectoria - Comunicaciones y Mercadeo | E12: Camilo Robledo | F12: Coordinador Comunicaciones | G12: coordinadordecontenidos@unimetro.edu.co | H12: 46185 | I12: Volantes de programas académicos Pregado- Medicina - Nutrición y Dietética | J12: Volantes | K12: 3000 | L12: 46295 | M12: Los volantes de promoción de los programas académicos se imprimen con policromia completa. Por lo cual require por volante 4 planchas. El departamento de Diseño y Comunicaciones está en proceso de elaboración del diseño.
A13: 12 | B13: 46182.622 | C13: 46182.625 | D13: Rectoria - Comunicaciones y Mercadeo | E13: Camilo Robledo | F13: Coordinador Comunicaciones | G13: coordinadordecontenidos@unimetro.edu.co | H13: 46185 | I13: Volante progamas Pregrado - Bacteriología-Enfermeria-Fisioterapia- Trabajo Social | J13: Volantes | K13: 4000 | L13: 46295 | M13: De cada programa se requieren 1000 volantes aproximadamente en policromia
... A29: 28 | B29: 46297.648 | C29: 46297.649 | D29: Vicerrectoria - Direccion de bienestar universitario | E29: Katty Aguas Gamarra | F29: Coordinadora de Desarrollo Humano | G29: desarrollohumano@unimetro.edu.co | H29: 46300 | I29: Mini Agendas | J29: Mini Agendas o Libretas | K29: 60 | L29: 46314 | M29: 60 mini agendas color rosa con un diseño simple.

Sheet 02_Base_Solicitudes
A1: Id Forms | B1: Fecha recepción | C1: Fecha solicitud | D1: Dependencia | E1: Solicitante | F1: Cargo | G1: Correo | H1: Nombre trabajo | I1: Tipo trabajo | J1: Cantidad | K1: Fecha requerida | L1: Comentarios solicitud | M1: Prioridad | N1: Estado solicitud | O1: Info completa | P1: Días SLA | Q1: Alerta SLA | R1: Número OT | S1: Generar OT | T1: Observaciones validación
A2: =IF('01_Forms_Raw'!A2="","",'01_Forms_Raw'!A2) -> 1 | B2: =IF('01_Forms_Raw'!B2="","",'01_Forms_Raw'!B2) -> 46164.682 | C2: =IF('01_Forms_Raw'!H2="","",'01_Forms_Raw'!H2) -> 46185 | D2: =IF('01_Forms_Raw'!D2="","",'01_Forms_Raw'!D2) -> Rectoria - Comunicaciones y Mercadeo | E2: =IF('01_Forms_Raw'!E2="","",'01_Forms_Raw'!E2) -> Camilo Robledo | F2: =IF('01_Forms_Raw'!F2="","",'01_Forms_Raw'!F2) -> Coordinador Contenido | G2: =IF('01_Forms_Raw'!G2="","",'01_Forms_Raw'!G2) -> coordinadordecontenidos@unimetro.edu.co | H2: =IF('01_Forms_Raw'!I2="","",'01_Forms_Raw'!I2) -> Miniblocks - Mercadeo / pieza promocional unimetro | I2: =IF('01_Forms_Raw'!J2="","",'01_Forms_Raw'!J2) -> MiniBlocks | J2: =IF('01_Forms_Raw'!K2="","",VALUE('01_Forms_Raw'!K2)) -> 750 | K2: =IF('01_Forms_Raw'!L2="","",'01_Forms_Raw'!L2) -> 46233 | L2: =IF('01_Forms_Raw'!M2="","",'01_Forms_Raw'!M2) -> Mini Blocks pedido de Vicerrectoria. Se entregan 50 unidades a Julio Higgins para campaña mercadeo del Dpto de Diseño y Comunicaciones. El resto de la producción se entregará a Rectoría | M2: Normal | N2: Aprobada para OT | O2: =IF(A2="","",IF(AND(D2<>"",E2<>"",H2<>"",I2<>"",J2<>"",K2<>""),"Completa","Incompleta")) -> Completa | P2: =IF(A2="","",K2-C2) -> 48 | Q2: =IF(A2="","",IF(P2<3,"Riesgo SLA",IF(P2<7,"Corto","OK"))) -> OK | R2: =IF(A2="","","OT-UM-"&TEXT(C2,"yyyymm")&"-"&TEXT(A2,"000")) -> OT-UM-202606-001 | S2: =IF(A2="","",IF(O2="Completa","Sí","No")) -> Sí | T2: =IF(A2="","",IF(O2="Completa","Lista para OT","Completar brief antes de pasar a diseño")) -> Lista para OT
A3: =IF('01_Forms_Raw'!A3="","",'01_Forms_Raw'!A3) -> 2 | B3: =IF('01_Forms_Raw'!B3="","",'01_Forms_Raw'!B3) -> 46164.686 | C3: =IF('01_Forms_Raw'!H3="","",'01_Forms_Raw'!H3) -> 46185 | D3: =IF('01_Forms_Raw'!D3="","",'01_Forms_Raw'!D3) -> Rectoria - Comunicaciones y Mercadeo | E3: =IF('01_Forms_Raw'!E3="","",'01_Forms_Raw'!E3) -> Camilo Robledo | F3: =IF('01_Forms_Raw'!F3="","",'01_Forms_Raw'!F3) -> Coordinador Comunicaciones | G3: =IF('01_Forms_Raw'!G3="","",'01_Forms_Raw'!G3) -> coordinadordecontenidos@unimetro.edu.co | H3: =IF('01_Forms_Raw'!I3="","",'01_Forms_Raw'!I3) -> Memos - pieza de mercadeo para el area de comunicaciones | I3: =IF('01_Forms_Raw'!J3="","",'01_Forms_Raw'!J3) -> Memos | J3: =IF('01_Forms_Raw'!K3="","",VALUE('01_Forms_Raw'!K3)) -> 570 | K3: =IF('01_Forms_Raw'!L3="","",'01_Forms_Raw'!L3) -> 46310 | L3: =IF('01_Forms_Raw'!M3="","",'01_Forms_Raw'!M3) -> Mini Memos pedido de Vicerrectoria. Se entregan 50 unidades a Julio Higgins para campaña mercadeo del Dpto de Diseño y Comunicaciones | M3: Normal | N3: Aprobada para OT | O3: =IF(A3="","",IF(AND(D3<>"",E3<>"",H3<>"",I3<>"",J3<>"",K3<>""),"Completa","Incompleta")) -> Completa | P3: =IF(A3="","",K3-C3) -> 125 | Q3: =IF(A3="","",IF(P3<3,"Riesgo SLA",IF(P3<7,"Corto","OK"))) -> OK | R3: =IF(A3="","","OT-UM-"&TEXT(C3,"yyyymm")&"-"&TEXT(A3,"000")) -> OT-UM-202606-002 | S3: =IF(A3="","",IF(O3="Completa","Sí","No")) -> Sí | T3: =IF(A3="","",IF(O3="Completa","Lista para OT","Completar brief antes de pasar a diseño")) -> Lista para OT
A4: =IF('01_Forms_Raw'!A4="","",'01_Forms_Raw'!A4) -> 3 | B4: =IF('01_Forms_Raw'!B4="","",'01_Forms_Raw'!B4) -> 46164.69 | C4: =IF('01_Forms_Raw'!H4="","",'01_Forms_Raw'!H4) -> 46160 | D4: =IF('01_Forms_Raw'!D4="","",'01_Forms_Raw'!D4) -> Vicerrectoria | E4: =IF('01_Forms_Raw'!E4="","",'01_Forms_Raw'!E4) -> Jose Luis Castro Guerra | F4: =IF('01_Forms_Raw'!F4="","",'01_Forms_Raw'!F4) -> Vicerrector | G4: =IF('01_Forms_Raw'!G4="","",'01_Forms_Raw'!G4) -> vice-rectoria@unimetro.edu.co | H4: =IF('01_Forms_Raw'!I4="","",'01_Forms_Raw'!I4) -> Agendas - Material interno y de distribución externa para segundo semestre 2026 | I4: =IF('01_Forms_Raw'!J4="","",'01_Forms_Raw'!J4) -> Agendas | J4: =IF('01_Forms_Raw'!K4="","",VALUE('01_Forms_Raw'!K4)) -> 500 | K4: =IF('01_Forms_Raw'!L4="","",'01_Forms_Raw'!L4) -> 46230 | L4: =IF('01_Forms_Raw'!M4="","",'01_Forms_Raw'!M4) -> Material de la Agendas ya se adquirió. Al 11 de Junio la planchas están en proceso de elaboración por proveedor. Se requiere tecnico empastador para apoyar con el ensamble de las agendas | M4: Normal | N4: Aprobada para OT | O4: =IF(A4="","",IF(AND(D4<>"",E4<>"",H4<>"",I4<>"",J4<>"",K4<>""),"Completa","Incompleta")) -> Completa | P4: =IF(A4="","",K4-C4) -> 70 | Q4: =IF(A4="","",IF(P4<3,"Riesgo SLA",IF(P4<7,"Corto","OK"))) -> OK | R4: =IF(A4="","","OT-UM-"&TEXT(C4,"yyyymm")&"-"&TEXT(A4,"000")) -> OT-UM-202605-003 | S4: =IF(A4="","",IF(O4="Completa","Sí","No")) -> Sí | T4: =IF(A4="","",IF(O4="Completa","Lista para OT","Completar brief antes de pasar a diseño")) -> Lista para OT
A5: =IF('01_Forms_Raw'!A5="","",'01_Forms_Raw'!A5) -> 4 | B5: =IF('01_Forms_Raw'!B5="","",'01_Forms_Raw'!B5) -> 46164.704 | C5: =IF('01_Forms_Raw'!H5="","",'01_Forms_Raw'!H5) -> 46254 | D5: =IF('01_Forms_Raw'!D5="","",'01_Forms_Raw'!D5) -> Vicerrectoria | E5: =IF('01_Forms_Raw'!E5="","",'01_Forms_Raw'!E5) -> Jose Luis Castro | F5: =IF('01_Forms_Raw'!F5="","",'01_Forms_Raw'!F5) -> Vicerrector | G5: =IF('01_Forms_Raw'!G5="","",'01_Forms_Raw'!G5) -> vice-rectoria@unimetro.edu.co | H5: =IF('01_Forms_Raw'!I5="","",'01_Forms_Raw'!I5) -> Abanicos - Material de promoción de la universidad | I5: =IF('01_Forms_Raw'!J5="","",'01_Forms_Raw'!J5) -> Abanicos | J5: =IF('01_Forms_Raw'!K5="","",VALUE('01_Forms_Raw'!K5)) -> 1500 | K5: =IF('01_Forms_Raw'!L5="","",'01_Forms_Raw'!L5) -> 46324 | L5: =IF('01_Forms_Raw'!M5="","",'01_Forms_Raw'!M5) -> Los abanicos hacen parte de un material de promoción. Todavía no tiene aprobación de Rectoría | M5: Normal | N5: Recibida | O5: =IF(A5="","",IF(AND(D5<>"",E5<>"",H5<>"",I5<>"",J5<>"",K5<>""),"Completa","Incompleta")) -> Completa | P5: =IF(A5="","",K5-C5) -> 70 | Q5: =IF(A5="","",IF(P5<3,"Riesgo SLA",IF(P5<7,"Corto","OK"))) -> OK | R5: =IF(A5="","","OT-UM-"&TEXT(C5,"yyyymm")&"-"&TEXT(A5,"000")) -> OT-UM-202608-004 | S5: =IF(A5="","",IF(O5="Completa","Sí","No")) -> Sí | T5: =IF(A5="","",IF(O5="Completa","Lista para OT","Completar brief antes de pasar a diseño")) -> Lista para OT
A6: =IF('01_Forms_Raw'!A6="","",'01_Forms_Raw'!A6) -> 5 | B6: =IF('01_Forms_Raw'!B6="","",'01_Forms_Raw'!B6) -> 46167.394 | C6: =IF('01_Forms_Raw'!H6="","",'01_Forms_Raw'!H6) -> 46153 | D6: =IF('01_Forms_Raw'!D6="","",'01_Forms_Raw'!D6) -> Vicerrectoria | E6: =IF('01_Forms_Raw'!E6="","",'01_Forms_Raw'!E6) -> Indira Luz de la Rosa | F6: =IF('01_Forms_Raw'!F6="","",'01_Forms_Raw'!F6) -> Asistente Vicerectoria | G6: =IF('01_Forms_Raw'!G6="","",'01_Forms_Raw'!G6) -> idelarosa@unimetro.edu.co | H6: =IF('01_Forms_Raw'!I6="","",'01_Forms_Raw'!I6) -> Actas de Grado | I6: =IF('01_Forms_Raw'!J6="","",'01_Forms_Raw'!J6) -> Actas de grado | J6: =IF('01_Forms_Raw'!K6="","",VALUE('01_Forms_Raw'!K6)) -> 1000 | K6: =IF('01_Forms_Raw'!L6="","",'01_Forms_Raw'!L6) -> 46184 | L6: =IF('01_Forms_Raw'!M6="","",'01_Forms_Raw'!M6) -> Cotizar papel Opalina . Sr Julio Rivera consiguió la cotización de 150 pliegos en Dipaca - distribuidora papelera del caribe. | M6: Normal | N6: Aprobada para OT | O6: =IF(A6="","",IF(AND(D6<>"",E6<>"",H6<>"",I6<>"",J6<>"",K6<>""),"Completa","Incompleta")) -> Completa | P6: =IF(A6="","",K6-C6) -> 31 | Q6: =IF(A6="","",IF(P6<3,"Riesgo SLA",IF(P6<7,"Corto","OK"))) -> OK | R6: =IF(A6="","","OT-UM-"&TEXT(C6,"yyyymm")&"-"&TEXT(A6,"000")) -> OT-UM-202605-005 | S6: =IF(A6="","",IF(O6="Completa","Sí","No")) -> Sí | T6: =IF(A6="","",IF(O6="Completa","Lista para OT","Completar brief antes de pasar a diseño")) -> Lista para OT
A7: =IF('01_Forms_Raw'!A7="","",'01_Forms_Raw'!A7) -> 6 | B7: =IF('01_Forms_Raw'!B7="","",'01_Forms_Raw'!B7) -> 46167.398 | C7: =IF('01_Forms_Raw'!H7="","",'01_Forms_Raw'!H7) -> 46121 | D7: =IF('01_Forms_Raw'!D7="","",'01_Forms_Raw'!D7) -> Vicerrectoria - Biblioteca | E7: =IF('01_Forms_Raw'!E7="","",'01_Forms_Raw'!E7) -> Yarima Medrano Nazzer | F7: =IF('01_Forms_Raw'!F7="","",'01_Forms_Raw'!F7) -> Directora Biblioteca | G7: =IF('01_Forms_Raw'!G7="","",'01_Forms_Raw'!G7) -> directorabiblioteca@unimetro.edu.co | H7: =IF('01_Forms_Raw'!I7="","",'01_Forms_Raw'!I7) -> Tarjetas de Prestamo | I7: =IF('01_Forms_Raw'!J7="","",'01_Forms_Raw'!J7) -> Tarjetas Prestamo Biblioteca | J7: =IF('01_Forms_Raw'!K7="","",VALUE('01_Forms_Raw'!K7)) -> 5000 | K7: =IF('01_Forms_Raw'!L7="","",'01_Forms_Raw'!L7) -> 46259 | L7: =IF('01_Forms_Raw'!M7="","",'01_Forms_Raw'!M7) -> Esta solicitud tuvo una demora causada por el material que llego solo hasta el 4 de mayo. | M7: Normal | N7: Aprobada para OT | O7: =IF(A7="","",IF(AND(D7<>"",E7<>"",H7<>"",I7<>"",J7<>"",K7<>""),"Completa","Incompleta")) -> Completa | P7: =IF(A7="","",K7-C7) -> 138 | Q7: =IF(A7="","",IF(P7<3,"Riesgo SLA",IF(P7<7,"Corto","OK"))) -> OK | R7: =IF(A7="","","OT-UM-"&TEXT(C7,"yyyymm")&"-"&TEXT(A7,"000")) -> OT-UM-202604-006 | S7: =IF(A7="","",IF(O7="Completa","Sí","No")) -> Sí | T7: =IF(A7="","",IF(O7="Completa","Lista para OT","Completar brief antes de pasar a diseño")) -> Lista para OT
A8: =IF('01_Forms_Raw'!A8="","",'01_Forms_Raw'!A8) -> 7 | B8: =IF('01_Forms_Raw'!B8="","",'01_Forms_Raw'!B8) -> 46167.41 | C8: =IF('01_Forms_Raw'!H8="","",'01_Forms_Raw'!H8) -> 46121 | D8: =IF('01_Forms_Raw'!D8="","",'01_Forms_Raw'!D8) -> Vicerrectoria - Biblioteca | E8: =IF('01_Forms_Raw'!E8="","",'01_Forms_Raw'!E8) -> Yarima Medrano Nazzer | F8: =IF('01_Forms_Raw'!F8="","",'01_Forms_Raw'!F8) -> Directora Biblioteca | G8: =IF('01_Forms_Raw'!G8="","",'01_Forms_Raw'!G8) -> directorabiblioteca@unimetro.edu.co | H8: =IF('01_Forms_Raw'!I8="","",'01_Forms_Raw'!I8) -> Bolsillos de tarjeta de préstamo | I8: =IF('01_Forms_Raw'!J8="","",'01_Forms_Raw'!J8) -> Bolsillos de tarjeta de préstamo | J8: =IF('01_Forms_Raw'!K8="","",VALUE('01_Forms_Raw'!K8)) -> 2000 | K8: =IF('01_Forms_Raw'!L8="","",'01_Forms_Raw'!L8) -> 46259 | L8: =IF('01_Forms_Raw'!M8="","",'01_Forms_Raw'!M8) -> Material pedido en Febrero solo se recepcionó hasta inicios de Mayo. | M8: Normal | N8: Aprobada para OT | O8: =IF(A8="","",IF(AND(D8<>"",E8<>"",H8<>"",I8<>"",J8<>"",K8<>""),"Completa","Incompleta")) -> Completa | P8: =IF(A8="","",K8-C8) -> 138 | Q8: =IF(A8="","",IF(P8<3,"Riesgo SLA",IF(P8<7,"Corto","OK"))) -> OK | R8: =IF(A8="","","OT-UM-"&TEXT(C8,"yyyymm")&"-"&TEXT(A8,"000")) -> OT-UM-202604-007 | S8: =IF(A8="","",IF(O8="Completa","Sí","No")) -> Sí | T8: =IF(A8="","",IF(O8="Completa","Lista para OT","Completar brief antes de pasar a diseño")) -> Lista para OT
A9: =IF('01_Forms_Raw'!A9="","",'01_Forms_Raw'!A9) -> 8 | B9: =IF('01_Forms_Raw'!B9="","",'01_Forms_Raw'!B9) -> 46167.413 | C9: =IF('01_Forms_Raw'!H9="","",'01_Forms_Raw'!H9) -> 46121 | D9: =IF('01_Forms_Raw'!D9="","",'01_Forms_Raw'!D9) -> Vicerrectoria - Biblioteca | E9: =IF('01_Forms_Raw'!E9="","",'01_Forms_Raw'!E9) -> Yarima Medrano Nazzer | F9: =IF('01_Forms_Raw'!F9="","",'01_Forms_Raw'!F9) -> Directora Biblioteca | G9: =IF('01_Forms_Raw'!G9="","",'01_Forms_Raw'!G9) -> directorabiblioteca@unimetro.edu.co | H9: =IF('01_Forms_Raw'!I9="","",'01_Forms_Raw'!I9) -> Adhesivos de Colores para categorizar grupos de Libros | I9: =IF('01_Forms_Raw'!J9="","",'01_Forms_Raw'!J9) -> Adhesivos de Colores | J9: =IF('01_Forms_Raw'!K9="","",VALUE('01_Forms_Raw'!K9)) -> 1300 | K9: =IF('01_Forms_Raw'!L9="","",'01_Forms_Raw'!L9) -> 46155 | L9: =IF('01_Forms_Raw'!M9="","",'01_Forms_Raw'!M9) -> Se realizaran adhesivos tamaño carta Amarillo, verde, rosado, gris, azul - 500/200/200/200/200. Se entregaron el 11 de Mayo | M9: Normal | N9: Aprobada para OT | O9: =IF(A9="","",IF(AND(D9<>"",E9<>"",H9<>"",I9<>"",J9<>"",K9<>""),"Completa","Incompleta")) -> Completa | P9: =IF(A9="","",K9-C9) -> 34 | Q9: =IF(A9="","",IF(P9<3,"Riesgo SLA",IF(P9<7,"Corto","OK"))) -> OK | R9: =IF(A9="","","OT-UM-"&TEXT(C9,"yyyymm")&"-"&TEXT(A9,"000")) -> OT-UM-202604-008 | S9: =IF(A9="","",IF(O9="Completa","Sí","No")) -> Sí | T9: =IF(A9="","",IF(O9="Completa","Lista para OT","Completar brief antes de pasar a diseño")) -> Lista para OT
A10: =IF('01_Forms_Raw'!A10="","",'01_Forms_Raw'!A10) -> 9 | B10: =IF('01_Forms_Raw'!B10="","",'01_Forms_Raw'!B10) -> 46177.929 | C10: =IF('01_Forms_Raw'!H10="","",'01_Forms_Raw'!H10) -> 46170 | D10: =IF('01_Forms_Raw'!D10="","",'01_Forms_Raw'!D10) -> Vicerrectoria - Direccion Administrativa | E10: =IF('01_Forms_Raw'!E10="","",'01_Forms_Raw'!E10) -> Elio Ortiz | F10: =IF('01_Forms_Raw'!F10="","",'01_Forms_Raw'!F10) -> Director Administrativo | G10: =IF('01_Forms_Raw'!G10="","",'01_Forms_Raw'!G10) -> eortizg@unimetro.edu.co | H10: Hojas membretadas uso institucional para varias dependencias | I10: =IF('01_Forms_Raw'!J10="","",'01_Forms_Raw'!J10) -> Hojas Membreteadas | J10: =IF('01_Forms_Raw'!K10="","",VALUE('01_Forms_Raw'!K10)) -> 5000 | K10: =IF('01_Forms_Raw'!L10="","",'01_Forms_Raw'!L10) -> 46249 | L10: =IF('01_Forms_Raw'!M10="","",'01_Forms_Raw'!M10) -> Se estima que para finalesde junio se debe tener la hojas membretadas para el uso en varias dependencias. | M10: Normal | N10: Aprobada para OT | O10: =IF(A10="","",IF(AND(D10<>"",E10<>"",H10<>"",I10<>"",J10<>"",K10<>""),"Completa","Incompleta")) -> Completa | P10: =IF(A10="","",K10-C10) -> 79 | Q10: =IF(A10="","",IF(P10<3,"Riesgo SLA",IF(P10<7,"Corto","OK"))) -> OK | R10: =IF(A10="","","OT-UM-"&TEXT(C10,"yyyymm")&"-"&TEXT(A10,"000")) -> OT-UM-202605-009 | S10: =IF(A10="","",IF(O10="Completa","Sí","No")) -> Sí | T10: =IF(A10="","",IF(O10="Completa","Lista para OT","Completar brief antes de pasar a diseño")) -> Lista para OT
A11: =IF('01_Forms_Raw'!A11="","",'01_Forms_Raw'!A11) -> 10 | B11: =IF('01_Forms_Raw'!B11="","",'01_Forms_Raw'!B11) -> 46178.649 | C11: =IF('01_Forms_Raw'!H11="","",'01_Forms_Raw'!H11) -> 46155 | D11: =IF('01_Forms_Raw'!D11="","",'01_Forms_Raw'!D11) -> Rectoria - Alta consejeria | E11: =IF('01_Forms_Raw'!E11="","",'01_Forms_Raw'!E11) -> Julian Ramirez | F11: =IF('01_Forms_Raw'!F11="","",'01_Forms_Raw'!F11) -> Coordinador Imprenta UM | G11: =IF('01_Forms_Raw'!G11="","",'01_Forms_Raw'!G11) -> jramirezo@unimetro.edu.co | H11: =IF('01_Forms_Raw'!I11="","",'01_Forms_Raw'!I11) -> Individuales para bandejas de plazoleta de comidas | I11: =IF('01_Forms_Raw'!J11="","",'01_Forms_Raw'!J11) -> Individuales para bandejas | J11: =IF('01_Forms_Raw'!K11="","",VALUE('01_Forms_Raw'!K11)) -> 3600 | K11: =IF('01_Forms_Raw'!L11="","",'01_Forms_Raw'!L11) -> 46254 | L11: =IF('01_Forms_Raw'!M11="","",'01_Forms_Raw'!M11) -> Este proyecto de los individuales para bandejas lo está impulsando la rectoria de la universidad como parte de ¨awarness¨ en lugares externos a UM. Todavia no se tiene claridad el número completo de ejemplares a realizar. Se ingresa el pedido para darle trazabilidad. | M11: Normal | N11: Aprobada para OT | O11: =IF(A11="","",IF(AND(D11<>"",E11<>"",H11<>"",I11<>"",J11<>"",K11<>""),"Completa","Incompleta")) -> Completa | P11: =IF(A11="","",K11-C11) -> 99 | Q11: =IF(A11="","",IF(P11<3,"Riesgo SLA",IF(P11<7,"Corto","OK"))) -> OK | R11: =IF(A11="","","OT-UM-"&TEXT(C11,"yyyymm")&"-"&TEXT(A11,"000")) -> OT-UM-202605-010 | S11: =IF(A11="","",IF(O11="Completa","Sí","No")) -> Sí | T11: =IF(A11="","",IF(O11="Completa","Lista para OT","Completar brief antes de pasar a diseño")) -> Lista para OT
A12: =IF('01_Forms_Raw'!A12="","",'01_Forms_Raw'!A12) -> 11 | B12: =IF('01_Forms_Raw'!B12="","",'01_Forms_Raw'!B12) -> 46182.603 | C12: =IF('01_Forms_Raw'!H12="","",'01_Forms_Raw'!H12) -> 46185 | D12: =IF('01_Forms_Raw'!D12="","",'01_Forms_Raw'!D12) -> Rectoria - Comunicaciones y Mercadeo | E12: =IF('01_Forms_Raw'!E12="","",'01_Forms_Raw'!E12) -> Camilo Robledo | F12: =IF('01_Forms_Raw'!F12="","",'01_Forms_Raw'!F12) -> Coordinador Comunicaciones | G12: =IF('01_Forms_Raw'!G12="","",'01_Forms_Raw'!G12) -> coordinadordecontenidos@unimetro.edu.co | H12: =IF('01_Forms_Raw'!I12="","",'01_Forms_Raw'!I12) -> Volantes de programas académicos Pregado- Medicina - Nutrición y Dietética | I12: =IF('01_Forms_Raw'!J12="","",'01_Forms_Raw'!J12) -> Volantes | J12: =IF('01_Forms_Raw'!K12="","",VALUE('01_Forms_Raw'!K12)) -> 3000 | K12: =IF('01_Forms_Raw'!L12="","",'01_Forms_Raw'!L12) -> 46295 | L12: =IF('01_Forms_Raw'!M12="","",'01_Forms_Raw'!M12) -> Los volantes de promoción de los programas académicos se imprimen con policromia completa. Por lo cual require por volante 4 planchas. El departamento de Diseño y Comunicaciones está en proceso de elaboración del diseño. | M12: Normal | N12: Recibida | O12: =IF(A12="","",IF(AND(D12<>"",E12<>"",H12<>"",I12<>"",J12<>"",K12<>""),"Completa","Incompleta")) -> Completa | P12: =IF(A12="","",K12-C12) -> 110 | Q12: =IF(A12="","",IF(P12<3,"Riesgo SLA",IF(P12<7,"Corto","OK"))) -> OK | R12: =IF(A12="","","OT-UM-"&TEXT(C12,"yyyymm")&"-"&TEXT(A12,"000")) -> OT-UM-202606-011 | S12: =IF(A12="","",IF(O12="Completa","Sí","No")) -> Sí | T12: =IF(A12="","",IF(O12="Completa","Lista para OT","Completar brief antes de pasar a diseño")) -> Lista para OT
A13: =IF('01_Forms_Raw'!A13="","",'01_Forms_Raw'!A13) -> 12 | B13: =IF('01_Forms_Raw'!B13="","",'01_Forms_Raw'!B13) -> 46182.622 | C13: =IF('01_Forms_Raw'!H13="","",'01_Forms_Raw'!H13) -> 46185 | D13: =IF('01_Forms_Raw'!D13="","",'01_Forms_Raw'!D13) -> Rectoria - Comunicaciones y Mercadeo | E13: =IF('01_Forms_Raw'!E13="","",'01_Forms_Raw'!E13) -> Camilo Robledo | F13: =IF('01_Forms_Raw'!F13="","",'01_Forms_Raw'!F13) -> Coordinador Comunicaciones | G13: =IF('01_Forms_Raw'!G13="","",'01_Forms_Raw'!G13) -> coordinadordecontenidos@unimetro.edu.co | H13: =IF('01_Forms_Raw'!I13="","",'01_Forms_Raw'!I13) -> Volante progamas Pregrado - Bacteriología-Enfermeria-Fisioterapia- Trabajo Social | I13: =IF('01_Forms_Raw'!J13="","",'01_Forms_Raw'!J13) -> Volantes | J13: =IF('01_Forms_Raw'!K13="","",VALUE('01_Forms_Raw'!K13)) -> 4000 | K13: =IF('01_Forms_Raw'!L13="","",'01_Forms_Raw'!L13) -> 46295 | L13: =IF('01_Forms_Raw'!M13="","",'01_Forms_Raw'!M13) -> De cada programa se requieren 1000 volantes aproximadamente en policromia | M13: Normal | N13: Recibida | O13: =IF(A13="","",IF(AND(D13<>"",E13<>"",H13<>"",I13<>"",J13<>"",K13<>""),"Completa","Incompleta")) -> Completa | P13: =IF(A13="","",K13-C13) -> 110 | Q13: =IF(A13="","",IF(P13<3,"Riesgo SLA",IF(P13<7,"Corto","OK"))) -> OK | R13: =IF(A13="","","OT-UM-"&TEXT(C13,"yyyymm")&"-"&TEXT(A13,"000")) -> OT-UM-202606-012 | S13: =IF(A13="","",IF(O13="Completa","Sí","No")) -> Sí | T13: =IF(A13="","",IF(O13="Completa","Lista para OT","Completar brief antes de pasar a diseño")) -> Lista para OT
A14: =IF('01_Forms_Raw'!A14="","",'01_Forms_Raw'!A14) -> 13 | B14: =IF('01_Forms_Raw'!B14="","",'01_Forms_Raw'!B14) -> 46184.735 | C14: =IF('01_Forms_Raw'!H14="","",'01_Forms_Raw'!H14) -> 46185 | D14: =IF('01_Forms_Raw'!D14="","",'01_Forms_Raw'!D14) -> Rectoria - Comunicaciones y Mercadeo | E14: =IF('01_Forms_Raw'!E14="","",'01_Forms_Raw'!E14) -> Camilo Robledo | F14: =IF('01_Forms_Raw'!F14="","",'01_Forms_Raw'!F14) -> Coordinador Comunicaciones | G14: =IF('01_Forms_Raw'!G14="","",'01_Forms_Raw'!G14) -> coordinadordecontenidos@unimetro.edu.co | H14: =IF('01_Forms_Raw'!I14="","",'01_Forms_Raw'!I14) -> Volante programas pregrado - Odontología - Optometría - Psicología - Terapia Ocupacional | I14: =IF('01_Forms_Raw'!J14="","",'01_Forms_Raw'!J14) -> Volantes | J14: =IF('01_Forms_Raw'!K14="","",VALUE('01_Forms_Raw'!K14)) -> 4000 | K14: =IF('01_Forms_Raw'!L14="","",'01_Forms_Raw'!L14) -> 46295 | L14: =IF('01_Forms_Raw'!M14="","",'01_Forms_Raw'!M14) -> De cada programa se requieren 1000 volantes aproximadamente en policromia | M14: Normal | N14: Recibida | O14: =IF(A14="","",IF(AND(D14<>"",E14<>"",H14<>"",I14<>"",J14<>"",K14<>""),"Completa","Incompleta")) -> Completa | P14: =IF(A14="","",K14-C14) -> 110 | Q14: =IF(A14="","",IF(P14<3,"Riesgo SLA",IF(P14<7,"Corto","OK"))) -> OK | R14: =IF(A14="","","OT-UM-"&TEXT(C14,"yyyymm")&"-"&TEXT(A14,"000")) -> OT-UM-202606-013 | S14: =IF(A14="","",IF(O14="Completa","Sí","No")) -> Sí | T14: =IF(A14="","",IF(O14="Completa","Lista para OT","Completar brief antes de pasar a diseño")) -> Lista para OT
A15: =IF('01_Forms_Raw'!A15="","",'01_Forms_Raw'!A15) -> 14 | B15: =IF('01_Forms_Raw'!B15="","",'01_Forms_Raw'!B15) -> 46164.69 | C15: =IF('01_Forms_Raw'!H15="","",'01_Forms_Raw'!H15) -> 46200 | D15: =IF('01_Forms_Raw'!D15="","",'01_Forms_Raw'!D15) -> Vicerrectoria | E15: =IF('01_Forms_Raw'!E15="","",'01_Forms_Raw'!E15) -> Jose Luis Castro Guerra | F15: =IF('01_Forms_Raw'!F15="","",'01_Forms_Raw'!F15) -> Vicerrector | G15: =IF('01_Forms_Raw'!G15="","",'01_Forms_Raw'!G15) -> vice-rectoria@unimetro.edu.co | H15: =IF('01_Forms_Raw'!I15="","",'01_Forms_Raw'!I15) -> Agendas - 2ndo lote de 500 unidades para 30Sep | I15: =IF('01_Forms_Raw'!J15="","",'01_Forms_Raw'!J15) -> Agendas | J15: =IF('01_Forms_Raw'!K15="","",VALUE('01_Forms_Raw'!K15)) -> 500 | K15: =IF('01_Forms_Raw'!L15="","",'01_Forms_Raw'!L15) -> 46310 | L15: =IF('01_Forms_Raw'!M15="","",'01_Forms_Raw'!M15) -> Se divide el pedido inicial de1000 agendas en 2 etapas. 500 para inicio 2nd semestre de 2026 y las otras 500 para finales de Noviembre para suplir la necesidad de 1er semestre de 2027 | M15: Programado | N15: Aprobada para OT | O15: =IF(A15="","",IF(AND(D15<>"",E15<>"",H15<>"",I15<>"",J15<>"",K15<>""),"Completa","Incompleta")) -> Completa | P15: =IF(A15="","",K15-C15) -> 110 | Q15: =IF(A15="","",IF(P15<3,"Riesgo SLA",IF(P15<7,"Corto","OK"))) -> OK | R15: =IF(A15="","","OT-UM-"&TEXT(C15,"yyyymm")&"-"&TEXT(A15,"000")) -> OT-UM-202606-014 | S15: =IF(A15="","",IF(O15="Completa","Sí","No")) -> Sí | T15: =IF(A15="","",IF(O15="Completa","Lista para OT","Completar brief antes de pasar a diseño")) -> Lista para OT
A16: =IF('01_Forms_Raw'!A16="","",'01_Forms_Raw'!A16) -> 15 | B16: =IF('01_Forms_Raw'!B16="","",'01_Forms_Raw'!B16) -> 46233.622 | C16: =IF('01_Forms_Raw'!H16="","",'01_Forms_Raw'!H16) -> 46267 | D16: =IF('01_Forms_Raw'!D16="","",'01_Forms_Raw'!D16) -> Rectoria - Alta consejeria | E16: =IF('01_Forms_Raw'!E16="","",'01_Forms_Raw'!E16) -> Camilo Robledo | F16: =IF('01_Forms_Raw'!F16="","",'01_Forms_Raw'!F16) -> Coordinador Comunicaciones | G16: =IF('01_Forms_Raw'!G16="","",'01_Forms_Raw'!G16) -> coordinadordecontenidos@unimetro.edu.co | H16: =IF('01_Forms_Raw'!I16="","",'01_Forms_Raw'!I16) -> Calendario 2027 | I16: =IF('01_Forms_Raw'!J16="","",'01_Forms_Raw'!J16) -> Calendarios | J16: =IF('01_Forms_Raw'!K16="","",VALUE('01_Forms_Raw'!K16)) -> 4000 | K16: =IF('01_Forms_Raw'!L16="","",'01_Forms_Raw'!L16) -> 46326 | L16: =IF('01_Forms_Raw'!M16="","",'01_Forms_Raw'!M16) -> Los Calendarios hacen parte la marca instutucional de la universidad. El diseño debe iniciarse desde 1ero de Agosto para que la Imprenta inicie la impresión a mas tardar el 1ero de Octubre. | M16: Programado | N16: Recibida | O16: =IF(A16="","",IF(AND(D16<>"",E16<>"",H16<>"",I16<>"",J16<>"",K16<>""),"Completa","Incompleta")) -> Completa | P16: =IF(A16="","",K16-C16) -> 59 | Q16: =IF(A16="","",IF(P16<3,"Riesgo SLA",IF(P16<7,"Corto","OK"))) -> OK | R16: =IF(A16="","","OT-UM-"&TEXT(C16,"yyyymm")&"-"&TEXT(A16,"000")) -> OT-UM-202609-015 | S16: =IF(A16="","",IF(O16="Completa","Sí","No")) -> Sí | T16: =IF(A16="","",IF(O16="Completa","Lista para OT","Completar brief antes de pasar a diseño")) -> Lista para OT
A17: =IF('01_Forms_Raw'!A17="","",'01_Forms_Raw'!A17) -> 16 | B17: =IF('01_Forms_Raw'!B17="","",'01_Forms_Raw'!B17) -> 46238 | C17: =IF('01_Forms_Raw'!H17="","",'01_Forms_Raw'!H17) -> 46238 | D17: =IF('01_Forms_Raw'!D17="","",'01_Forms_Raw'!D17) -> Vicerrectoria - Direccion de bienestar universitario | E17: =IF('01_Forms_Raw'!E17="","",'01_Forms_Raw'!E17) -> Katty Aguas Gamarra | F17: =IF('01_Forms_Raw'!F17="","",'01_Forms_Raw'!F17) -> Coordinadora de Desarrollo Humano | G17: =IF('01_Forms_Raw'!G17="","",'01_Forms_Raw'!G17) -> desarrollohumano@unimetro.edu.co | H17: =IF('01_Forms_Raw'!I17="","",'01_Forms_Raw'!I17) -> ACTUALIZACION DE FOLLETO DE SALUD MENTAL | I17: =IF('01_Forms_Raw'!J17="","",'01_Forms_Raw'!J17) -> Folletos | J17: =IF('01_Forms_Raw'!K17="","",VALUE('01_Forms_Raw'!K17)) -> 2000 | K17: =IF('01_Forms_Raw'!L17="","",'01_Forms_Raw'!L17) -> 46275 | L17: =IF('01_Forms_Raw'!M17="","",'01_Forms_Raw'!M17) -> El diseño fue enviado a su correo institucional. | M17: Programado | N17: Validada | O17: =IF(A17="","",IF(AND(D17<>"",E17<>"",H17<>"",I17<>"",J17<>"",K17<>""),"Completa","Incompleta")) -> Completa | P17: =IF(A17="","",K17-C17) -> 37 | Q17: =IF(A17="","",IF(P17<3,"Riesgo SLA",IF(P17<7,"Corto","OK"))) -> OK | R17: =IF(A17="","","OT-UM-"&TEXT(C17,"yyyymm")&"-"&TEXT(A17,"000")) -> OT-UM-202608-016 | S17: =IF(A17="","",IF(O17="Completa","Sí","No")) -> Sí | T17: =IF(A17="","",IF(O17="Completa","Lista para OT","Completar brief antes de pasar a diseño")) -> Lista para OT
A18: =IF('01_Forms_Raw'!A18="","",'01_Forms_Raw'!A18) -> 17 | B18: =IF('01_Forms_Raw'!B18="","",'01_Forms_Raw'!B18) -> 46238 | C18: =IF('01_Forms_Raw'!H18="","",'01_Forms_Raw'!H18) -> 46238 | D18: =IF('01_Forms_Raw'!D18="","",'01_Forms_Raw'!D18) -> Rectoria - Comunicaciones y Mercadeo | E18: =IF('01_Forms_Raw'!E18="","",'01_Forms_Raw'!E18) -> Julio Higgins | F18: =IF('01_Forms_Raw'!F18="","",'01_Forms_Raw'!F18) -> Relaciones Publicas | G18: =IF('01_Forms_Raw'!G18="","",'01_Forms_Raw'!G18) -> relacionespublicas@unimetro.edu.co | H18: =IF('01_Forms_Raw'!I18="","",'01_Forms_Raw'!I18) -> Volantes Pregrado y Postgrado Unimetro | I18: =IF('01_Forms_Raw'!J18="","",'01_Forms_Raw'!J18) -> Volantes | J18: =IF('01_Forms_Raw'!K18="","",VALUE('01_Forms_Raw'!K18)) -> 500 | K18: =IF('01_Forms_Raw'!L18="","",'01_Forms_Raw'!L18) -> 46239 | L18: =IF('01_Forms_Raw'!M18="","",'01_Forms_Raw'!M18) -> Se utilizará el diseño anterior que contaba con 10 programas de pre y post grado. Se recomienda al departamento de comunicaciones y mercadeo realizar un nuevo diseño para el próximo batch | M18: Urgente | N18: Aprobada para OT | O18: =IF(A18="","",IF(AND(D18<>"",E18<>"",H18<>"",I18<>"",J18<>"",K18<>""),"Completa","Incompleta")) -> Completa | P18: =IF(A18="","",K18-C18) -> 1 | Q18: =IF(A18="","",IF(P18<3,"Riesgo SLA",IF(P18<7,"Corto","OK"))) -> Riesgo SLA | R18: =IF(A18="","","OT-UM-"&TEXT(C18,"yyyymm")&"-"&TEXT(A18,"000")) -> OT-UM-202608-017 | S18: =IF(A18="","",IF(O18="Completa","Sí","No")) -> Sí | T18: =IF(A18="","",IF(O18="Completa","Lista para OT","Completar brief antes de pasar a diseño")) -> Lista para OT
A19: =IF('01_Forms_Raw'!A19="","",'01_Forms_Raw'!A19) -> 18 | B19: =IF('01_Forms_Raw'!B19="","",'01_Forms_Raw'!B19) -> 46238 | C19: =IF('01_Forms_Raw'!H19="","",'01_Forms_Raw'!H19) -> 46238 | D19: =IF('01_Forms_Raw'!D19="","",'01_Forms_Raw'!D19) -> Vicerrectoria - Direccion de bienestar universitario | E19: =IF('01_Forms_Raw'!E19="","",'01_Forms_Raw'!E19) -> Katty Aguas Gamarra | F19: =IF('01_Forms_Raw'!F19="","",'01_Forms_Raw'!F19) -> Coordinadora de Desarrollo Humano | G19: =IF('01_Forms_Raw'!G19="","",'01_Forms_Raw'!G19) -> desarrollohumano@unimetro.edu.co | H19: =IF('01_Forms_Raw'!I19="","",'01_Forms_Raw'!I19) -> ACTUALIZACION DE FOLLETO DE LOS SERVICIOS DE BIENESTAR UNIVERSITARIO | I19: =IF('01_Forms_Raw'!J19="","",'01_Forms_Raw'!J19) -> Folletos | J19: =IF('01_Forms_Raw'!K19="","",VALUE('01_Forms_Raw'!K19)) -> 2000 | K19: =IF('01_Forms_Raw'!L19="","",'01_Forms_Raw'!L19) -> 46296 | L19: =IF('01_Forms_Raw'!M19="","",'01_Forms_Raw'!M19) -> El diseño fue enviado a su correo institucional. | M19: Programado | N19: Validada | O19: =IF(A19="","",IF(AND(D19<>"",E19<>"",H19<>"",I19<>"",J19<>"",K19<>""),"Completa","Incompleta")) -> Completa | P19: =IF(A19="","",K19-C19) -> 58 | Q19: =IF(A19="","",IF(P19<3,"Riesgo SLA",IF(P19<7,"Corto","OK"))) -> OK | R19: =IF(A19="","","OT-UM-"&TEXT(C19,"yyyymm")&"-"&TEXT(A19,"000")) -> OT-UM-202608-018 | S19: =IF(A19="","",IF(O19="Completa","Sí","No")) -> Sí | T19: =IF(A19="","",IF(O19="Completa","Lista para OT","Completar brief antes de pasar a diseño")) -> Lista para OT
A20: =IF('01_Forms_Raw'!A20="","",'01_Forms_Raw'!A20) -> 19 | B20: =IF('01_Forms_Raw'!B20="","",'01_Forms_Raw'!B20) -> 46245 | C20: =IF('01_Forms_Raw'!H20="","",'01_Forms_Raw'!H20) -> 46245 | D20: =IF('01_Forms_Raw'!D20="","",'01_Forms_Raw'!D20) -> Rectoria - Comunicaciones y Mercadeo | E20: =IF('01_Forms_Raw'!E20="","",'01_Forms_Raw'!E20) -> Julio Higgins | F20: =IF('01_Forms_Raw'!F20="","",'01_Forms_Raw'!F20) -> Relaciones Publicas | G20: =IF('01_Forms_Raw'!G20="","",'01_Forms_Raw'!G20) -> relacionespublicas@unimetro.edu.co | H20: =IF('01_Forms_Raw'!I20="","",'01_Forms_Raw'!I20) -> Volantes QR Pregrado y Postgrado Actualizado Unimetro | I20: =IF('01_Forms_Raw'!J20="","",'01_Forms_Raw'!J20) -> Volantes | J20: =IF('01_Forms_Raw'!K20="","",VALUE('01_Forms_Raw'!K20)) -> 2000 | K20: =IF('01_Forms_Raw'!L20="","",'01_Forms_Raw'!L20) -> 46295 | L20: =IF('01_Forms_Raw'!M20="","",'01_Forms_Raw'!M20) -> Se aprobó una nueva versión del volante infomativo de las carreras, Este volante informativo se requiere para todo el año, es decir, una buena cantidad de ejemplares se requieren. Para H2 se harán 3000 y se esperan complementar con los dedicados a cada programa | M20: Programado | N20: Aprobada para OT | O20: =IF(A20="","",IF(AND(D20<>"",E20<>"",H20<>"",I20<>"",J20<>"",K20<>""),"Completa","Incompleta")) -> Completa | P20: =IF(A20="","",K20-C20) -> 50 | Q20: =IF(A20="","",IF(P20<3,"Riesgo SLA",IF(P20<7,"Corto","OK"))) -> OK | R20: =IF(A20="","","OT-UM-"&TEXT(C20,"yyyymm")&"-"&TEXT(A20,"000")) -> OT-UM-202608-019 | S20: =IF(A20="","",IF(O20="Completa","Sí","No")) -> Sí | T20: =IF(A20="","",IF(O20="Completa","Lista para OT","Completar brief antes de pasar a diseño")) -> Lista para OT
A21: =IF('01_Forms_Raw'!A21="","",'01_Forms_Raw'!A21) -> 20 | B21: =IF('01_Forms_Raw'!B21="","",'01_Forms_Raw'!B21) -> 46259 | C21: =IF('01_Forms_Raw'!H21="","",'01_Forms_Raw'!H21) -> 46259 | D21: =IF('01_Forms_Raw'!D21="","",'01_Forms_Raw'!D21) -> Rectoria | E21: =IF('01_Forms_Raw'!E21="","",'01_Forms_Raw'!E21) -> Lidia Cala | F21: =IF('01_Forms_Raw'!F21="","",'01_Forms_Raw'!F21) -> Secretaria | G21: =IF('01_Forms_Raw'!G21="","",'01_Forms_Raw'!G21) -> rectoriaunimetro@unimetro.edu.co | H21: =IF('01_Forms_Raw'!I21="","",'01_Forms_Raw'!I21) -> Miniblocks - pieza uso interno unimetro | I21: =IF('01_Forms_Raw'!J21="","",'01_Forms_Raw'!J21) -> MiniBlocks | J21: =IF('01_Forms_Raw'!K21="","",VALUE('01_Forms_Raw'!K21)) -> 1000 | K21: =IF('01_Forms_Raw'!L21="","",'01_Forms_Raw'!L21) -> 46295 | L21: =IF('01_Forms_Raw'!M21="","",'01_Forms_Raw'!M21) -> Se requieren 1000 unidades de miniblocks.Se utizará material del inventario de la Imprenta UM que se replazará con material del pedido#016 | M21: Programado | N21: Aprobada para OT | O21: =IF(A21="","",IF(AND(D21<>"",E21<>"",H21<>"",I21<>"",J21<>"",K21<>""),"Completa","Incompleta")) -> Completa | P21: =IF(A21="","",K21-C21) -> 36 | Q21: =IF(A21="","",IF(P21<3,"Riesgo SLA",IF(P21<7,"Corto","OK"))) -> OK | R21: =IF(A21="","","OT-UM-"&TEXT(C21,"yyyymm")&"-"&TEXT(A21,"000")) -> OT-UM-202608-020 | S21: =IF(A21="","",IF(O21="Completa","Sí","No")) -> Sí | T21: =IF(A21="","",IF(O21="Completa","Lista para OT","Completar brief antes de pasar a diseño")) -> Lista para OT
A22: =IF('01_Forms_Raw'!A22="","",'01_Forms_Raw'!A22) -> 21 | B22: =IF('01_Forms_Raw'!B22="","",'01_Forms_Raw'!B22) -> 46260 | C22: =IF('01_Forms_Raw'!H22="","",'01_Forms_Raw'!H22) -> 46260 | D22: =IF('01_Forms_Raw'!D22="","",'01_Forms_Raw'!D22) -> Vicerrectoria - Direccion de bienestar universitario | E22: =IF('01_Forms_Raw'!E22="","",'01_Forms_Raw'!E22) -> Katty Aguas Gamarra | F22: =IF('01_Forms_Raw'!F22="","",'01_Forms_Raw'!F22) -> Coordinadora de Desarrollo Humano | G22: =IF('01_Forms_Raw'!G22="","",'01_Forms_Raw'!G22) -> desarrollohumano@unimetro.edu.co | H22: =IF('01_Forms_Raw'!I22="","",'01_Forms_Raw'!I22) -> Separadores de libros sobre salud mental | I22: =IF('01_Forms_Raw'!J22="","",'01_Forms_Raw'!J22) -> Separadores de libros | J22: =IF('01_Forms_Raw'!K22="","",VALUE('01_Forms_Raw'!K22)) -> 1000 | K22: =IF('01_Forms_Raw'!L22="","",'01_Forms_Raw'!L22) -> 46274 | L22: =IF('01_Forms_Raw'!M22="","",'01_Forms_Raw'!M22) -> Estos separadores se entregarán el dia 10 de septiembre en actividad masiva sobre prevención del suicidio. | M22: Programado | N22: Aprobada para OT | O22: =IF(A22="","",IF(AND(D22<>"",E22<>"",H22<>"",I22<>"",J22<>"",K22<>""),"Completa","Incompleta")) -> Completa | P22: =IF(A22="","",K22-C22) -> 14 | Q22: =IF(A22="","",IF(P22<3,"Riesgo SLA",IF(P22<7,"Corto","OK"))) -> OK | R22: =IF(A22="","","OT-UM-"&TEXT(C22,"yyyymm")&"-"&TEXT(A22,"000")) -> OT-UM-202608-021 | S22: =IF(A22="","",IF(O22="Completa","Sí","No")) -> Sí | T22: =IF(A22="","",IF(O22="Completa","Lista para OT","Completar brief antes de pasar a diseño")) -> Lista para OT
... A29: =IF('01_Forms_Raw'!A29="","",'01_Forms_Raw'!A29) -> 28 | B29: =IF('01_Forms_Raw'!B29="","",'01_Forms_Raw'!B29) -> 46297.648 | C29: =IF('01_Forms_Raw'!H29="","",'01_Forms_Raw'!H29) -> 46300 | D29: =IF('01_Forms_Raw'!D29="","",'01_Forms_Raw'!D29) -> Vicerrectoria - Direccion de bienestar universitario | E29: =IF('01_Forms_Raw'!E29="","",'01_Forms_Raw'!E29) -> Katty Aguas Gamarra | F29: =IF('01_Forms_Raw'!F29="","",'01_Forms_Raw'!F29) -> Coordinadora de Desarrollo Humano | G29: =IF('01_Forms_Raw'!G29="","",'01_Forms_Raw'!G29) -> desarrollohumano@unimetro.edu.co | H29: =IF('01_Forms_Raw'!I29="","",'01_Forms_Raw'!I29) -> Mini Agendas | I29: =IF('01_Forms_Raw'!J29="","",'01_Forms_Raw'!J29) -> Mini Agendas o Libretas | J29: =IF('01_Forms_Raw'!K29="","",VALUE('01_Forms_Raw'!K29)) -> 60 | K29: =IF('01_Forms_Raw'!L29="","",'01_Forms_Raw'!L29) -> 46314 | L29: =IF('01_Forms_Raw'!M29="","",'01_Forms_Raw'!M29) -> 60 mini agendas color rosa con un diseño simple. | M29: Urgente | N29: Validada | O29: =IF(A29="","",IF(AND(D29<>"",E29<>"",H29<>"",I29<>"",J29<>"",K29<>""),"Completa","Incompleta")) -> Completa | P29: =IF(A29="","",K29-C29) -> 14 | Q29: =IF(A29="","",IF(P29<3,"Riesgo SLA",IF(P29<7,"Corto","OK"))) -> OK | R29: =IF(A29="","","OT-UM-"&TEXT(C29,"yyyymm")&"-"&TEXT(A29,"000")) -> OT-UM-202610-028 | S29: =IF(A29="","",IF(O29="Completa","Sí","No")) -> Sí | T29: =IF(A29="","",IF(O29="Completa","Lista para OT","Completar brief antes de pasar a diseño")) -> Lista para OT
A30: =IF('01_Forms_Raw'!A30="","",'01_Forms_Raw'!A30) | B30: =IF('01_Forms_Raw'!B30="","",'01_Forms_Raw'!B30) | C30: =IF('01_Forms_Raw'!H30="","",'01_Forms_Raw'!H30) | D30: =IF('01_Forms_Raw'!D30="","",'01_Forms_Raw'!D30) | E30: =IF('01_Forms_Raw'!E30="","",'01_Forms_Raw'!E30) | F30: =IF('01_Forms_Raw'!F30="","",'01_Forms_Raw'!F30) | G30: =IF('01_Forms_Raw'!G30="","",'01_Forms_Raw'!G30) | H30: =IF('01_Forms_Raw'!I30="","",'01_Forms_Raw'!I30) | I30: =IF('01_Forms_Raw'!J30="","",'01_Forms_Raw'!J30) | J30: =IF('01_Forms_Raw'!K30="","",VALUE('01_Forms_Raw'!K30)) | K30: =IF('01_Forms_Raw'!L30="","",'01_Forms_Raw'!L30) | L30: =IF('01_Forms_Raw'!M30="","",'01_Forms_Raw'!M30) | O30: =IF(A30="","",IF(AND(D30<>"",E30<>"",H30<>"",I30<>"",J30<>"",K30<>""),"Completa","Incompleta")) | P30: =IF(A30="","",K30-C30) | Q30: =IF(A30="","",IF(P30<3,"Riesgo SLA",IF(P30<7,"Corto","OK"))) | R30: =IF(A30="","","OT-UM-"&TEXT(C30,"yyyymm")&"-"&TEXT(A30,"000")) | S30: =IF(A30="","",IF(O30="Completa","Sí","No")) | T30: =IF(A30="","",IF(O30="Completa","Lista para OT","Completar brief antes de pasar a diseño"))
A31: =IF('01_Forms_Raw'!A31="","",'01_Forms_Raw'!A31) | B31: =IF('01_Forms_Raw'!B31="","",'01_Forms_Raw'!B31) | C31: =IF('01_Forms_Raw'!H31="","",'01_Forms_Raw'!H31) | D31: =IF('01_Forms_Raw'!D31="","",'01_Forms_Raw'!D31) | E31: =IF('01_Forms_Raw'!E31="","",'01_Forms_Raw'!E31) | F31: =IF('01_Forms_Raw'!F31="","",'01_Forms_Raw'!F31) | G31: =IF('01_Forms_Raw'!G31="","",'01_Forms_Raw'!G31) | H31: =IF('01_Forms_Raw'!I31="","",'01_Forms_Raw'!I31) | I31: =IF('01_Forms_Raw'!J31="","",'01_Forms_Raw'!J31) | J31: =IF('01_Forms_Raw'!K31="","",VALUE('01_Forms_Raw'!K31)) | K31: =IF('01_Forms_Raw'!L31="","",'01_Forms_Raw'!L31) | L31: =IF('01_Forms_Raw'!M31="","",'01_Forms_Raw'!M31) | O31: =IF(A31="","",IF(AND(D31<>"",E31<>"",H31<>"",I31<>"",J31<>"",K31<>""),"Completa","Incompleta")) | P31: =IF(A31="","",K31-C31) | Q31: =IF(A31="","",IF(P31<3,"Riesgo SLA",IF(P31<7,"Corto","OK"))) | R31: =IF(A31="","","OT-UM-"&TEXT(C31,"yyyymm")&"-"&TEXT(A31,"000")) | S31: =IF(A31="","",IF(O31="Completa","Sí","No")) | T31: =IF(A31="","",IF(O31="Completa","Lista para OT","Completar brief antes de pasar a diseño"))
A32: =IF('01_Forms_Raw'!A32="","",'01_Forms_Raw'!A32) | B32: =IF('01_Forms_Raw'!B32="","",'01_Forms_Raw'!B32) | C32: =IF('01_Forms_Raw'!H32="","",'01_Forms_Raw'!H32) | D32: =IF('01_Forms_Raw'!D32="","",'01_Forms_Raw'!D32) | E32: =IF('01_Forms_Raw'!E32="","",'01_Forms_Raw'!E32) | F32: =IF('01_Forms_Raw'!F32="","",'01_Forms_Raw'!F32) | G32: =IF('01_Forms_Raw'!G32="","",'01_Forms_Raw'!G32) | H32: =IF('01_Forms_Raw'!I32="","",'01_Forms_Raw'!I32) | I32: =IF('01_Forms_Raw'!J32="","",'01_Forms_Raw'!J32) | J32: =IF('01_Forms_Raw'!K32="","",VALUE('01_Forms_Raw'!K32)) | K32: =IF('01_Forms_Raw'!L32="","",'01_Forms_Raw'!L32) | L32: =IF('01_Forms_Raw'!M32="","",'01_Forms_Raw'!M32) | O32: =IF(A32="","",IF(AND(D32<>"",E32<>"",H32<>"",I32<>"",J32<>"",K32<>""),"Completa","Incompleta")) | P32: =IF(A32="","",K32-C32) | Q32: =IF(A32="","",IF(P32<3,"Riesgo SLA",IF(P32<7,"Corto","OK"))) | R32: =IF(A32="","","OT-UM-"&TEXT(C32,"yyyymm")&"-"&TEXT(A32,"000")) | S32: =IF(A32="","",IF(O32="Completa","Sí","No")) | T32: =IF(A32="","",IF(O32="Completa","Lista para OT","Completar brief antes de pasar a diseño"))
A33: =IF('01_Forms_Raw'!A33="","",'01_Forms_Raw'!A33) | B33: =IF('01_Forms_Raw'!B33="","",'01_Forms_Raw'!B33) | C33: =IF('01_Forms_Raw'!H33="","",'01_Forms_Raw'!H33) | D33: =IF('01_Forms_Raw'!D33="","",'01_Forms_Raw'!D33) | E33: =IF('01_Forms_Raw'!E33="","",'01_Forms_Raw'!E33) | F33: =IF('01_Forms_Raw'!F33="","",'01_Forms_Raw'!F33) | G33: =IF('01_Forms_Raw'!G33="","",'01_Forms_Raw'!G33) | H33: =IF('01_Forms_Raw'!I33="","",'01_Forms_Raw'!I33) | I33: =IF('01_Forms_Raw'!J33="","",'01_Forms_Raw'!J33) | J33: =IF('01_Forms_Raw'!K33="","",VALUE('01_Forms_Raw'!K33)) | K33: =IF('01_Forms_Raw'!L33="","",'01_Forms_Raw'!L33) | L33: =IF('01_Forms_Raw'!M33="","",'01_Forms_Raw'!M33) | O33: =IF(A33="","",IF(AND(D33<>"",E33<>"",H33<>"",I33<>"",J33<>"",K33<>""),"Completa","Incompleta")) | P33: =IF(A33="","",K33-C33) | Q33: =IF(A33="","",IF(P33<3,"Riesgo SLA",IF(P33<7,"Corto","OK"))) | R33: =IF(A33="","","OT-UM-"&TEXT(C33,"yyyymm")&"-"&TEXT(A33,"000")) | S33: =IF(A33="","",IF(O33="Completa","Sí","No")) | T33: =IF(A33="","",IF(O33="Completa","Lista para OT","Completar brief antes de pasar a diseño"))
A34: =IF('01_Forms_Raw'!A34="","",'01_Forms_Raw'!A34) | B34: =IF('01_Forms_Raw'!B34="","",'01_Forms_Raw'!B34) | C34: =IF('01_Forms_Raw'!H34="","",'01_Forms_Raw'!H34) | D34: =IF('01_Forms_Raw'!D34="","",'01_Forms_Raw'!D34) | E34: =IF('01_Forms_Raw'!E34="","",'01_Forms_Raw'!E34) | F34: =IF('01_Forms_Raw'!F34="","",'01_Forms_Raw'!F34) | G34: =IF('01_Forms_Raw'!G34="","",'01_Forms_Raw'!G34) | H34: =IF('01_Forms_Raw'!I34="","",'01_Forms_Raw'!I34) | I34: =IF('01_Forms_Raw'!J34="","",'01_Forms_Raw'!J34) | J34: =IF('01_Forms_Raw'!K34="","",VALUE('01_Forms_Raw'!K34)) | K34: =IF('01_Forms_Raw'!L34="","",'01_Forms_Raw'!L34) | L34: =IF('01_Forms_Raw'!M34="","",'01_Forms_Raw'!M34) | O34: =IF(A34="","",IF(AND(D34<>"",E34<>"",H34<>"",I34<>"",J34<>"",K34<>""),"Completa","Incompleta")) | P34: =IF(A34="","",K34-C34) | Q34: =IF(A34="","",IF(P34<3,"Riesgo SLA",IF(P34<7,"Corto","OK"))) | R34: =IF(A34="","","OT-UM-"&TEXT(C34,"yyyymm")&"-"&TEXT(A34,"000")) | S34: =IF(A34="","",IF(O34="Completa","Sí","No")) | T34: =IF(A34="","",IF(O34="Completa","Lista para OT","Completar brief antes de pasar a diseño"))
A35: =IF('01_Forms_Raw'!A35="","",'01_Forms_Raw'!A35) | B35: =IF('01_Forms_Raw'!B35="","",'01_Forms_Raw'!B35) | C35: =IF('01_Forms_Raw'!H35="","",'01_Forms_Raw'!H35) | D35: =IF('01_Forms_Raw'!D35="","",'01_Forms_Raw'!D35) | E35: =IF('01_Forms_Raw'!E35="","",'01_Forms_Raw'!E35) | F35: =IF('01_Forms_Raw'!F35="","",'01_Forms_Raw'!F35) | G35: =IF('01_Forms_Raw'!G35="","",'01_Forms_Raw'!G35) | H35: =IF('01_Forms_Raw'!I35="","",'01_Forms_Raw'!I35) | I35: =IF('01_Forms_Raw'!J35="","",'01_Forms_Raw'!J35) | J35: =IF('01_Forms_Raw'!K35="","",VALUE('01_Forms_Raw'!K35)) | K35: =IF('01_Forms_Raw'!L35="","",'01_Forms_Raw'!L35) | L35: =IF('01_Forms_Raw'!M35="","",'01_Forms_Raw'!M35) | O35: =IF(A35="","",IF(AND(D35<>"",E35<>"",H35<>"",I35<>"",J35<>"",K35<>""),"Completa","Incompleta")) | P35: =IF(A35="","",K35-C35) | Q35: =IF(A35="","",IF(P35<3,"Riesgo SLA",IF(P35<7,"Corto","OK"))) | R35: =IF(A35="","","OT-UM-"&TEXT(C35,"yyyymm")&"-"&TEXT(A35,"000")) | S35: =IF(A35="","",IF(O35="Completa","Sí","No")) | T35: =IF(A35="","",IF(O35="Completa","Lista para OT","Completar brief antes de pasar a diseño"))
A36: =IF('01_Forms_Raw'!A36="","",'01_Forms_Raw'!A36) | B36: =IF('01_Forms_Raw'!B36="","",'01_Forms_Raw'!B36) | C36: =IF('01_Forms_Raw'!H36="","",'01_Forms_Raw'!H36) | D36: =IF('01_Forms_Raw'!D36="","",'01_Forms_Raw'!D36) | E36: =IF('01_Forms_Raw'!E36="","",'01_Forms_Raw'!E36) | F36: =IF('01_Forms_Raw'!F36="","",'01_Forms_Raw'!F36) | G36: =IF('01_Forms_Raw'!G36="","",'01_Forms_Raw'!G36) | H36: =IF('01_Forms_Raw'!I36="","",'01_Forms_Raw'!I36) | I36: =IF('01_Forms_Raw'!J36="","",'01_Forms_Raw'!J36) | J36: =IF('01_Forms_Raw'!K36="","",VALUE('01_Forms_Raw'!K36)) | K36: =IF('01_Forms_Raw'!L36="","",'01_Forms_Raw'!L36) | L36: =IF('01_Forms_Raw'!M36="","",'01_Forms_Raw'!M36) | O36: =IF(A36="","",IF(AND(D36<>"",E36<>"",H36<>"",I36<>"",J36<>"",K36<>""),"Completa","Incompleta")) | P36: =IF(A36="","",K36-C36) | Q36: =IF(A36="","",IF(P36<3,"Riesgo SLA",IF(P36<7,"Corto","OK"))) | R36: =IF(A36="","","OT-UM-"&TEXT(C36,"yyyymm")&"-"&TEXT(A36,"000")) | S36: =IF(A36="","",IF(O36="Completa","Sí","No")) | T36: =IF(A36="","",IF(O36="Completa","Lista para OT","Completar brief antes de pasar a diseño"))
A37: =IF('01_Forms_Raw'!A37="","",'01_Forms_Raw'!A37) | B37: =IF('01_Forms_Raw'!B37="","",'01_Forms_Raw'!B37) | C37: =IF('01_Forms_Raw'!H37="","",'01_Forms_Raw'!H37) | D37: =IF('01_Forms_Raw'!D37="","",'01_Forms_Raw'!D37) | E37: =IF('01_Forms_Raw'!E37="","",'01_Forms_Raw'!E37) | F37: =IF('01_Forms_Raw'!F37="","",'01_Forms_Raw'!F37) | G37: =IF('01_Forms_Raw'!G37="","",'01_Forms_Raw'!G37) | H37: =IF('01_Forms_Raw'!I37="","",'01_Forms_Raw'!I37) | I37: =IF('01_Forms_Raw'!J37="","",'01_Forms_Raw'!J37) | J37: =IF('01_Forms_Raw'!K37="","",VALUE('01_Forms_Raw'!K37)) | K37: =IF('01_Forms_Raw'!L37="","",'01_Forms_Raw'!L37) | L37: =IF('01_Forms_Raw'!M37="","",'01_Forms_Raw'!M37) | O37: =IF(A37="","",IF(AND(D37<>"",E37<>"",H37<>"",I37<>"",J37<>"",K37<>""),"Completa","Incompleta")) | P37: =IF(A37="","",K37-C37) | Q37: =IF(A37="","",IF(P37<3,"Riesgo SLA",IF(P37<7,"Corto","OK"))) | R37: =IF(A37="","","OT-UM-"&TEXT(C37,"yyyymm")&"-"&TEXT(A37,"000")) | S37: =IF(A37="","",IF(O37="Completa","Sí","No")) | T37: =IF(A37="","",IF(O37="Completa","Lista para OT","Completar brief antes de pasar a diseño"))
A38: =IF('01_Forms_Raw'!A38="","",'01_Forms_Raw'!A38) | B38: =IF('01_Forms_Raw'!B38="","",'01_Forms_Raw'!B38) | C38: =IF('01_Forms_Raw'!H38="","",'01_Forms_Raw'!H38) | D38: =IF('01_Forms_Raw'!D38="","",'01_Forms_Raw'!D38) | E38: =IF('01_Forms_Raw'!E38="","",'01_Forms_Raw'!E38) | F38: =IF('01_Forms_Raw'!F38="","",'01_Forms_Raw'!F38) | G38: =IF('01_Forms_Raw'!G38="","",'01_Forms_Raw'!G38) | H38: =IF('01_Forms_Raw'!I38="","",'01_Forms_Raw'!I38) | I38: =IF('01_Forms_Raw'!J38="","",'01_Forms_Raw'!J38) | J38: =IF('01_Forms_Raw'!K38="","",VALUE('01_Forms_Raw'!K38)) | K38: =IF('01_Forms_Raw'!L38="","",'01_Forms_Raw'!L38) | L38: =IF('01_Forms_Raw'!M38="","",'01_Forms_Raw'!M38) | O38: =IF(A38="","",IF(AND(D38<>"",E38<>"",H38<>"",I38<>"",J38<>"",K38<>""),"Completa","Incompleta")) | P38: =IF(A38="","",K38-C38) | Q38: =IF(A38="","",IF(P38<3,"Riesgo SLA",IF(P38<7,"Corto","OK"))) | R38: =IF(A38="","","OT-UM-"&TEXT(C38,"yyyymm")&"-"&TEXT(A38,"000")) | S38: =IF(A38="","",IF(O38="Completa","Sí","No")) | T38: =IF(A38="","",IF(O38="Completa","Lista para OT","Completar brief antes de pasar a diseño"))
A39: =IF('01_Forms_Raw'!A39="","",'01_Forms_Raw'!A39) | B39: =IF('01_Forms_Raw'!B39="","",'01_Forms_Raw'!B39) | C39: =IF('01_Forms_Raw'!H39="","",'01_Forms_Raw'!H39) | D39: =IF('01_Forms_Raw'!D39="","",'01_Forms_Raw'!D39) | E39: =IF('01_Forms_Raw'!E39="","",'01_Forms_Raw'!E39) | F39: =IF('01_Forms_Raw'!F39="","",'01_Forms_Raw'!F39) | G39: =IF('01_Forms_Raw'!G39="","",'01_Forms_Raw'!G39) | H39: =IF('01_Forms_Raw'!I39="","",'01_Forms_Raw'!I39) | I39: =IF('01_Forms_Raw'!J39="","",'01_Forms_Raw'!J39) | J39: =IF('01_Forms_Raw'!K39="","",VALUE('01_Forms_Raw'!K39)) | K39: =IF('01_Forms_Raw'!L39="","",'01_Forms_Raw'!L39) | L39: =IF('01_Forms_Raw'!M39="","",'01_Forms_Raw'!M39) | O39: =IF(A39="","",IF(AND(D39<>"",E39<>"",H39<>"",I39<>"",J39<>"",K39<>""),"Completa","Incompleta")) | P39: =IF(A39="","",K39-C39) | Q39: =IF(A39="","",IF(P39<3,"Riesgo SLA",IF(P39<7,"Corto","OK"))) | R39: =IF(A39="","","OT-UM-"&TEXT(C39,"yyyymm")&"-"&TEXT(A39,"000")) | S39: =IF(A39="","",IF(O39="Completa","Sí","No")) | T39: =IF(A39="","",IF(O39="Completa","Lista para OT","Completar brief antes de pasar a diseño"))
A40: =IF('01_Forms_Raw'!A40="","",'01_Forms_Raw'!A40) | B40: =IF('01_Forms_Raw'!B40="","",'01_Forms_Raw'!B40) | C40: =IF('01_Forms_Raw'!H40="","",'01_Forms_Raw'!H40) | D40: =IF('01_Forms_Raw'!D40="","",'01_Forms_Raw'!D40) | E40: =IF('01_Forms_Raw'!E40="","",'01_Forms_Raw'!E40) | F40: =IF('01_Forms_Raw'!F40="","",'01_Forms_Raw'!F40) | G40: =IF('01_Forms_Raw'!G40="","",'01_Forms_Raw'!G40) | H40: =IF('01_Forms_Raw'!I40="","",'01_Forms_Raw'!I40) | I40: =IF('01_Forms_Raw'!J40="","",'01_Forms_Raw'!J40) | J40: =IF('01_Forms_Raw'!K40="","",VALUE('01_Forms_Raw'!K40)) | K40: =IF('01_Forms_Raw'!L40="","",'01_Forms_Raw'!L40) | L40: =IF('01_Forms_Raw'!M40="","",'01_Forms_Raw'!M40) | O40: =IF(A40="","",IF(AND(D40<>"",E40<>"",H40<>"",I40<>"",J40<>"",K40<>""),"Completa","Incompleta")) | P40: =IF(A40="","",K40-C40) | Q40: =IF(A40="","",IF(P40<3,"Riesgo SLA",IF(P40<7,"Corto","OK"))) | R40: =IF(A40="","","OT-UM-"&TEXT(C40,"yyyymm")&"-"&TEXT(A40,"000")) | S40: =IF(A40="","",IF(O40="Completa","Sí","No")) | T40: =IF(A40="","",IF(O40="Completa","Lista para OT","Completar brief antes de pasar a diseño"))
A41: =IF('01_Forms_Raw'!A41="","",'01_Forms_Raw'!A41) | B41: =IF('01_Forms_Raw'!B41="","",'01_Forms_Raw'!B41) | C41: =IF('01_Forms_Raw'!H41="","",'01_Forms_Raw'!H41) | D41: =IF('01_Forms_Raw'!D41="","",'01_Forms_Raw'!D41) | E41: =IF('01_Forms_Raw'!E41="","",'01_Forms_Raw'!E41) | F41: =IF('01_Forms_Raw'!F41="","",'01_Forms_Raw'!F41) | G41: =IF('01_Forms_Raw'!G41="","",'01_Forms_Raw'!G41) | H41: =IF('01_Forms_Raw'!I41="","",'01_Forms_Raw'!I41) | I41: =IF('01_Forms_Raw'!J41="","",'01_Forms_Raw'!J41) | J41: =IF('01_Forms_Raw'!K41="","",VALUE('01_Forms_Raw'!K41)) | K41: =IF('01_Forms_Raw'!L41="","",'01_Forms_Raw'!L41) | L41: =IF('01_Forms_Raw'!M41="","",'01_Forms_Raw'!M41) | O41: =IF(A41="","",IF(AND(D41<>"",E41<>"",H41<>"",I41<>"",J41<>"",K41<>""),"Completa","Incompleta")) | P41: =IF(A41="","",K41-C41) | Q41: =IF(A41="","",IF(P41<3,"Riesgo SLA",IF(P41<7,"Corto","OK"))) | R41: =IF(A41="","","OT-UM-"&TEXT(C41,"yyyymm")&"-"&TEXT(A41,"000")) | S41: =IF(A41="","",IF(O41="Completa","Sí","No")) | T41: =IF(A41="","",IF(O41="Completa","Lista para OT","Completar brief antes de pasar a diseño"))
... A201: =IF('01_Forms_Raw'!A201="","",'01_Forms_Raw'!A201) | B201: =IF('01_Forms_Raw'!B201="","",'01_Forms_Raw'!B201) | C201: =IF('01_Forms_Raw'!H201="","",'01_Forms_Raw'!H201) | D201: =IF('01_Forms_Raw'!D201="","",'01_Forms_Raw'!D201) | E201: =IF('01_Forms_Raw'!E201="","",'01_Forms_Raw'!E201) | F201: =IF('01_Forms_Raw'!F201="","",'01_Forms_Raw'!F201) | G201: =IF('01_Forms_Raw'!G201="","",'01_Forms_Raw'!G201) | H201: =IF('01_Forms_Raw'!I201="","",'01_Forms_Raw'!I201) | I201: =IF('01_Forms_Raw'!J201="","",'01_Forms_Raw'!J201) | J201: =IF('01_Forms_Raw'!K201="","",VALUE('01_Forms_Raw'!K201)) | K201: =IF('01_Forms_Raw'!L201="","",'01_Forms_Raw'!L201) | L201: =IF('01_Forms_Raw'!M201="","",'01_Forms_Raw'!M201) | O201: =IF(A201="","",IF(AND(D201<>"",E201<>"",H201<>"",I201<>"",J201<>"",K201<>""),"Completa","Incompleta")) | P201: =IF(A201="","",K201-C201) | Q201: =IF(A201="","",IF(P201<3,"Riesgo SLA",IF(P201<7,"Corto","OK"))) | R201: =IF(A201="","","OT-UM-"&TEXT(C201,"yyyymm")&"-"&TEXT(A201,"000")) | S201: =IF(A201="","",IF(O201="Completa","Sí","No")) | T201: =IF(A201="","",IF(O201="Completa","Lista para OT","Completar brief antes de pasar a diseño"))

Sheet 03_OT_Maestra
A1: OT Maestra V1 - Integrada Formulario + Diseño + Preprensa + Producción
A2: Campos verdes = extraídos del formulario / Campos amarillos = input Diseño, Preprensa, Producción y Cierre
A3: Número OT | B3: Id Forms | C3: Fecha solicitud | D3: Dependencia | E3: Solicitante | F3: Correo | G3: Nombre trabajo | H3: Tipo trabajo | I3: Cantidad | J3: Prioridad | K3: Fecha requerida | L3: Responsable OT | M3: Diseñador | N3: Cliente aprobó | O3: Fecha aprobación diseño | P3: Observaciones diseño | Q3: Planchas Listas | R3: Preprensa: formato/tamaño (cm) | S3: Preprensa: color/tintas | T3: Preprensa: material | U3: Preprensa: acabado | V3: Preprensa: máquina sugerida | W3: ¿Hay stock? | X3: Requiere compra | Y3: Fecha inicio producción | Z3: Fecha fin producción | AA3: Cantidad producida | AB3: Entrega Parcial | AC3: Control calidad | AD3: Observaciones calidad | AE3: Fecha entrega | AF3: Recibido por | AG3: Fecha cierre | AH3: Estado OT | AI3: Tiempo ciclo días | AJ3: SLA cumplido | AK3: Integridad | AL3: Observaciones cierre
A4: =IF('02_Base_Solicitudes'!A2="","",'02_Base_Solicitudes'!R2) -> OT-UM-202606-001 | B4: =IF('02_Base_Solicitudes'!A2="","",'02_Base_Solicitudes'!A2) -> 1 | C4: =IF('02_Base_Solicitudes'!A2="","",'02_Base_Solicitudes'!C2) -> 46185 | D4: =IF('02_Base_Solicitudes'!A2="","",'02_Base_Solicitudes'!D2) -> Rectoria - Comunicaciones y Mercadeo | E4: =IF('02_Base_Solicitudes'!A2="","",'02_Base_Solicitudes'!E2) -> Camilo Robledo | F4: =IF('02_Base_Solicitudes'!A2="","",'02_Base_Solicitudes'!G2) -> coordinadordecontenidos@unimetro.edu.co | G4: =IF('02_Base_Solicitudes'!A2="","",'02_Base_Solicitudes'!H2) -> Miniblocks - Mercadeo / pieza promocional unimetro | H4: =IF('02_Base_Solicitudes'!A2="","",'02_Base_Solicitudes'!I2) -> MiniBlocks | I4: =IF('02_Base_Solicitudes'!A2="","",'02_Base_Solicitudes'!J2) -> 750 | J4: =IF('02_Base_Solicitudes'!A2="","",'02_Base_Solicitudes'!M2) -> Normal | K4: =IF('02_Base_Solicitudes'!A2="","",'02_Base_Solicitudes'!K2) -> 46233 | L4: =IF($A4="","","Julio Rivera") -> Julio Rivera | M4: Diseño / Comunicaciones | N4: Sí | O4: 46167 | P4: Dejar 1/2 cm de sangrado para corte y refilo | Q4: Sí | R4: 20 x 13 | S4: Dos tintas | T4: Bond 75 g | U4: Plastificado brillante | V4: Shinohara 52 Bicolor | W4: Sí | X4: No | Y4: 46161 | Z4: 46233 | AA4: =40+270+270+170 -> 750 | AB4: =OTMaestraTable[[#This Row],[Cantidad producida]] -> 750 | AC4: Sí | AD4: Entrega Parcial 40 miniblocks al Dpto de Comunicaciones y Diseño para evento. 270 unidades se entregan a Sec. Rectoria el 25 de Junio. Se envián a grafar 644 portadas en el centro.Valor de $25k por el millar. 270uni entregadas el 21 de Julio. Se entregan un total de 750 unidades de miniblocks cada uno de 40 hojas. | AE4: 46234 | AF4: =OTMaestraTable[[#This Row],[Solicitante]] -> Camilo Robledo | AG4: 46233 | AH4: Cerrada | AI4: =IF(AND(C4<>"",AG4<>""),AG4-C4,"") -> 48 | AJ4: =IF(A4="","",IF(AND(AG4<>"",K4<>""),IF(AG4<=K4,"Sí","No"),"Pendiente")) -> Sí | AK4: =IF(A4="","",IF(AND($AH4="Cerrada",OR($AE4="",$AF4="",$AG4="")),"⚠ Cerrada incompleta",IF(AND($AH4<>"Cerrada",$AG4<>""),"⚠ Fecha cierre con estado abierto","OK"))) -> OK | AL4: Se entregan 760 unidades en esta primera etapa de miniblocks . Se utilizan los nuevos diseños con 40 hojas en lugar de 30 Por lo cual se disminuyó la cantidad final entregada de 950 a 760.. Se le entregan a secretaria de Rectoria para su distribución. Recibe Lidia Cala.
A5: =IF('02_Base_Solicitudes'!A3="","",'02_Base_Solicitudes'!R3) -> OT-UM-202606-002 | B5: =IF('02_Base_Solicitudes'!A3="","",'02_Base_Solicitudes'!A3) -> 2 | C5: =IF('02_Base_Solicitudes'!A3="","",'02_Base_Solicitudes'!C3) -> 46185 | D5: =IF('02_Base_Solicitudes'!A3="","",'02_Base_Solicitudes'!D3) -> Rectoria - Comunicaciones y Mercadeo | E5: =IF('02_Base_Solicitudes'!A3="","",'02_Base_Solicitudes'!E3) -> Camilo Robledo | F5: =IF('02_Base_Solicitudes'!A3="","",'02_Base_Solicitudes'!G3) -> coordinadordecontenidos@unimetro.edu.co | G5: =IF('02_Base_Solicitudes'!A3="","",'02_Base_Solicitudes'!H3) -> Memos - pieza de mercadeo para el area de comunicaciones | H5: =IF('02_Base_Solicitudes'!A3="","",'02_Base_Solicitudes'!I3) -> Memos | I5: =IF('02_Base_Solicitudes'!A3="","",'02_Base_Solicitudes'!J3) -> 570 | J5: =IF('02_Base_Solicitudes'!A3="","",'02_Base_Solicitudes'!M3) -> Normal | K5: =IF('02_Base_Solicitudes'!A3="","",'02_Base_Solicitudes'!K3) -> 46310 | L5: =IF($A5="","","Julio Rivera") -> Julio Rivera | M5: Diseño / Comunicaciones | N5: Sí | O5: 46167 | P5: Dejar 1/2 cm de sangrado para corte y refilo | Q5: Sí | R5: 9 x 9 | S5: Dos tintas | T5: Bond 75 g | U5: Plastificado brillante | V5: Shinohara 52 Bicolor | W5: Sí | X5: No | Y5: 46255 | AA5: 50 | AB5: 50 | AC5: Sí | AD5: Entrega Parcial 50 Memos al Dpto de Comunicaciones y Diseño para evento. Se tiene un mes de retraso de entrega por causa de la falla de la plastificadora. Pedido se envió el 6 de Julio. La portada se termina de imprimir el 12 de Agosto y se debe plastificar. El técnico debe intervenir la máquina una vez se libere el anticipo para la compra de los repuestos. Al dia 14 de Ago en espera de Aprobación y liberación de recurso. Se termina la intervención de la máquina plastificadora el 1ero de Septiembre. El 2 de Sep se termina de platificar las 300+ portadas. En espera para ensamble 1 a 1. | AF5: =OTMaestraTable[[#This Row],[Solicitante]] -> Camilo Robledo | AH5: Producción | AI5: =IF(AND(C5<>"",AG5<>""),AG5-C5,"") | AJ5: =IF(A5="","",IF(AND(AG5<>"",K5<>""),IF(AG5<=K5,"Sí","No"),"Pendiente")) -> Pendiente | AK5: =IF(A5="","",IF(AND($AH5="Cerrada",OR($AE5="",$AF5="",$AG5="")),"⚠ Cerrada incompleta",IF(AND($AH5<>"Cerrada",$AG5<>""),"⚠ Fecha cierre con estado abierto","OK"))) -> OK
A6: =IF('02_Base_Solicitudes'!A4="","",'02_Base_Solicitudes'!R4) -> OT-UM-202605-003 | B6: =IF('02_Base_Solicitudes'!A4="","",'02_Base_Solicitudes'!A4) -> 3 | C6: =IF('02_Base_Solicitudes'!A4="","",'02_Base_Solicitudes'!C4) -> 46160 | D6: =IF('02_Base_Solicitudes'!A4="","",'02_Base_Solicitudes'!D4) -> Vicerrectoria | E6: =IF('02_Base_Solicitudes'!A4="","",'02_Base_Solicitudes'!E4) -> Jose Luis Castro Guerra | F6: =IF('02_Base_Solicitudes'!A4="","",'02_Base_Solicitudes'!G4) -> vice-rectoria@unimetro.edu.co | G6: =IF('02_Base_Solicitudes'!A4="","",'02_Base_Solicitudes'!H4) -> Agendas - Material interno y de distribución externa para segundo semestre 2026 | H6: =IF('02_Base_Solicitudes'!A4="","",'02_Base_Solicitudes'!I4) -> Agendas | I6: =IF('02_Base_Solicitudes'!A4="","",'02_Base_Solicitudes'!J4) -> 500 | J6: Urgente | K6: =IF('02_Base_Solicitudes'!A4="","",'02_Base_Solicitudes'!K4) -> 46230 | L6: =IF($A6="","","Julio Rivera") -> Julio Rivera | M6: Diseño / Comunicaciones | N6: Sí | O6: 46175 | P6: Se hicieron las correcciones del calendario, Planchas corregidas llegarón el 12 de Junio. | Q6: Sí | R6: 16x22 | S6: Full color | T6: Bond 75 g | U6: Anillado | V6: Shinohara 52 Bicolor | W6: Sí | X6: No | Y6: 46198 | Z6: 46228 | AA6: 500 | AB6: =OTMaestraTable[[#This Row],[Cantidad producida]] -> 500 | AC6: Sí | AD6: Inicio de producción 25 Junio. Entrega esperada el 24 de Julio de 500 ejemplares minimo. Se ha utilizado el apoyo del personal de centro de copiado para la plastificación de las portadas. Le plastificadora se recalentó, faltaron 340 contraportadas. Maquina shinohara continua con problemas de perdida de presión. Contratista entregó el 14Jul26 portadas para 200 agendas. Se inicia la impresión de las hojas internas de la agentas. 15Jul26 se terminan los orificios de las tapas. 16jul26 se debe finalizar impresión frente y reverso de hojas. 17jul26 inicio de corte. Se emite OC anillos 17Jul26.Se continua corte de hojas internas. Se abren orificios de portadas.el 21Jul26. Orificios en hojas e incertos se hará el 22jul y se inicia ensamble el 23jul.Se entregan 250 a Bienestar el dia 24 y 200 unidades el sábado 25 a las 2pm. 50 a Rectoria el 27 de Julio. Se planea entregar las 500 faltantes de las 1000 inicialmente pedidas antes de finalizar el mes de Septiembre | AE6: 46228 | AF6: =OTMaestraTable[[#This Row],[Solicitante]] -> Jose Luis Castro Guerra | AG6: 46230 | AH6: Cerrada | AI6: =IF(AND(C6<>"",AG6<>""),AG6-C6,"") -> 70 | AJ6: =IF(A6="","",IF(AND(AG6<>"",K6<>""),IF(AG6<=K6,"Sí","No"),"Pendiente")) -> Sí | AK6: =IF(A6="","",IF(AND($AH6="Cerrada",OR($AE6="",$AF6="",$AG6="")),"⚠ Cerrada incompleta",IF(AND($AH6<>"Cerrada",$AG6<>""),"⚠ Fecha cierre con estado abierto","OK"))) -> OK | AL6: Se entregaran 250 ejemplares inicialmente el 24 de Julio. 200 se entregaron el sabado 25. 55 unidades se entregaron el dia 27. Se utilizan 6.5 resmas o 3250 pliegos. Esto implica hacer 104mil impresiones en 52mil hojas. Notas para Mejora - Se debe pedir una maquina perforadora y anilladora Nueva. Se tienen 2 antiguas en muy mal estado. Se debe buscar el servicio técnico de ellas
A7: =IF('02_Base_Solicitudes'!A5="","",'02_Base_Solicitudes'!R5) -> OT-UM-202608-004 | B7: =IF('02_Base_Solicitudes'!A5="","",'02_Base_Solicitudes'!A5) -> 4 | C7: =IF('02_Base_Solicitudes'!A5="","",'02_Base_Solicitudes'!C5) -> 46254 | D7: =IF('02_Base_Solicitudes'!A5="","",'02_Base_Solicitudes'!D5) -> Vicerrectoria | E7: =IF('02_Base_Solicitudes'!A5="","",'02_Base_Solicitudes'!E5) -> Jose Luis Castro | F7: =IF('02_Base_Solicitudes'!A5="","",'02_Base_Solicitudes'!G5) -> vice-rectoria@unimetro.edu.co | G7: =IF('02_Base_Solicitudes'!A5="","",'02_Base_Solicitudes'!H5) -> Abanicos - Material de promoción de la universidad | H7: =IF('02_Base_Solicitudes'!A5="","",'02_Base_Solicitudes'!I5) -> Abanicos | I7: =IF('02_Base_Solicitudes'!A5="","",'02_Base_Solicitudes'!J5) -> 1500 | J7: =IF('02_Base_Solicitudes'!A5="","",'02_Base_Solicitudes'!M5) -> Normal | K7: =IF('02_Base_Solicitudes'!A5="","",'02_Base_Solicitudes'!K5) -> 46324 | L7: =IF($A7="","","Julio Rivera") -> Julio Rivera | M7: Diseño / Comunicaciones | N7: No | P7: Idea en maduración , sin diseño, sin embargo ya está la OC del material, que se puede usar para Abanico o para volantes, llegado el caso | Q7: No | S7: Dos tintas | T7: Propalcote | U7: Plastificado brillante | V7: Shinohara 52 Bicolor | W7: Sí | X7: No | AC7: Pendiente | AF7: =OTMaestraTable[[#This Row],[Solicitante]] -> Jose Luis Castro | AH7: Abierta | AI7: =IF(AND(C7<>"",AG7<>""),AG7-C7,"") | AJ7: =IF(A7="","",IF(AND(AG7<>"",K7<>""),IF(AG7<=K7,"Sí","No"),"Pendiente")) -> Pendiente | AK7: =IF(A7="","",IF(AND($AH7="Cerrada",OR($AE7="",$AF7="",$AG7="")),"⚠ Cerrada incompleta",IF(AND($AH7<>"Cerrada",$AG7<>""),"⚠ Fecha cierre con estado abierto","OK"))) -> OK
A8: =IF('02_Base_Solicitudes'!A6="","",'02_Base_Solicitudes'!R6) -> OT-UM-202605-005 | B8: =IF('02_Base_Solicitudes'!A6="","",'02_Base_Solicitudes'!A6) -> 5 | C8: =IF('02_Base_Solicitudes'!A6="","",'02_Base_Solicitudes'!C6) -> 46153 | D8: =IF('02_Base_Solicitudes'!A6="","",'02_Base_Solicitudes'!D6) -> Vicerrectoria | E8: =IF('02_Base_Solicitudes'!A6="","",'02_Base_Solicitudes'!E6) -> Indira Luz de la Rosa | F8: =IF('02_Base_Solicitudes'!A6="","",'02_Base_Solicitudes'!G6) -> idelarosa@unimetro.edu.co | G8: =IF('02_Base_Solicitudes'!A6="","",'02_Base_Solicitudes'!H6) -> Actas de Grado | H8: =IF('02_Base_Solicitudes'!A6="","",'02_Base_Solicitudes'!I6) -> Actas de grado | I8: =IF('02_Base_Solicitudes'!A6="","",'02_Base_Solicitudes'!J6) -> 1000 | J8: =IF('02_Base_Solicitudes'!A6="","",'02_Base_Solicitudes'!M6) -> Normal | K8: =IF('02_Base_Solicitudes'!A6="","",'02_Base_Solicitudes'!K6) -> 46184 | L8: =IF($A8="","","Julio Rivera") -> Julio Rivera | M8: Diseño / Comunicaciones | N8: Sí | O8: 46002 | P8: Diseño y Plancha existente tamaño carta. | Q8: Sí | R8: 28 x 22 | S8: Dos tintas | T8: Opalina | U8: Tinta Seguridad | V8: Shinohara 52 Bicolor | W8: Sí | X8: No | Y8: 46175 | Z8: 46177 | AA8: 1250 | AB8: 0 | AC8: Sí | AD8: Se agregan pequeños visos de seguridad | AE8: 46184 | AF8: =OTMaestraTable[[#This Row],[Solicitante]] -> Indira Luz de la Rosa | AG8: 46184 | AH8: Cerrada | AI8: =IF(AND(C8<>"",AG8<>""),AG8-C8,"") -> 31 | AJ8: =IF(A8="","",IF(AND(AG8<>"",K8<>""),IF(AG8<=K8,"Sí","No"),"Pendiente")) -> Sí | AK8: =IF(A8="","",IF(AND($AH8="Cerrada",OR($AE8="",$AF8="",$AG8="")),"⚠ Cerrada incompleta",IF(AND($AH8<>"Cerrada",$AG8<>""),"⚠ Fecha cierre con estado abierto","OK"))) -> OK | AL8: Se aplica barniz al logo de UM resaltar el nombre . Se entregan más de las 1000 inicialmente pactadas.
A9: =IF('02_Base_Solicitudes'!A7="","",'02_Base_Solicitudes'!R7) -> OT-UM-202604-006 | B9: =IF('02_Base_Solicitudes'!A7="","",'02_Base_Solicitudes'!A7) -> 6 | C9: =IF('02_Base_Solicitudes'!A7="","",'02_Base_Solicitudes'!C7) -> 46121 | D9: =IF('02_Base_Solicitudes'!A7="","",'02_Base_Solicitudes'!D7) -> Vicerrectoria - Biblioteca | E9: =IF('02_Base_Solicitudes'!A7="","",'02_Base_Solicitudes'!E7) -> Yarima Medrano Nazzer | F9: =IF('02_Base_Solicitudes'!A7="","",'02_Base_Solicitudes'!G7) -> directorabiblioteca@unimetro.edu.co | G9: =IF('02_Base_Solicitudes'!A7="","",'02_Base_Solicitudes'!H7) -> Tarjetas de Prestamo | H9: =IF('02_Base_Solicitudes'!A7="","",'02_Base_Solicitudes'!I7) -> Tarjetas Prestamo Biblioteca | I9: =IF('02_Base_Solicitudes'!A7="","",'02_Base_Solicitudes'!J7) -> 5000 | J9: =IF('02_Base_Solicitudes'!A7="","",'02_Base_Solicitudes'!M7) -> Normal | K9: =IF('02_Base_Solicitudes'!A7="","",'02_Base_Solicitudes'!K7) -> 46259 | L9: =IF($A9="","","Julio Rivera") -> Julio Rivera | M9: Diseño / Comunicaciones | N9: Sí | O9: 46147 | P9: Diseño, Plancha y Material ya listos, | Q9: Sí | R9: 18.5 x 10.5 | S9: Una tinta | T9: Cartulina | U9: Corte | V9: Shinohara 52 Bicolor | W9: Sí | X9: No | Y9: 46232 | Z9: 46237 | AA9: 5000 | AB9: 0 | AC9: Sí | AD9: Tartjetas de préstamo en cartulina bristol azul. La impresión se realiza por frente y reverso de acuerdo al estándar d e la biblioteca. Se pueden entregar las tarjetas a esta dependencia el dia 3 de Agosto. | AE9: 46248 | AF9: =OTMaestraTable[[#This Row],[Solicitante]] -> Yarima Medrano Nazzer | AG9: 46248 | AH9: Cerrada | AI9: =IF(AND(C9<>"",AG9<>""),AG9-C9,"") -> 127 | AJ9: =IF(A9="","",IF(AND(AG9<>"",K9<>""),IF(AG9<=K9,"Sí","No"),"Pendiente")) -> Sí | AK9: =IF(A9="","",IF(AND($AH9="Cerrada",OR($AE9="",$AF9="",$AG9="")),"⚠ Cerrada incompleta",IF(AND($AH9<>"Cerrada",$AG9<>""),"⚠ Fecha cierre con estado abierto","OK"))) -> OK | AL9: Se entregan las tarjetas sin los bolsillos, pues todavia no se aprueba el servicio externo de troquelado. Esta espera en aprobación en Dir. Administrativa atrasa la entrega y cierre de la OT para las tarjetas.
A10: =IF('02_Base_Solicitudes'!A8="","",'02_Base_Solicitudes'!R8) -> OT-UM-202604-007 | B10: =IF('02_Base_Solicitudes'!A8="","",'02_Base_Solicitudes'!A8) -> 7 | C10: =IF('02_Base_Solicitudes'!A8="","",'02_Base_Solicitudes'!C8) -> 46121 | D10: =IF('02_Base_Solicitudes'!A8="","",'02_Base_Solicitudes'!D8) -> Vicerrectoria - Biblioteca | E10: =IF('02_Base_Solicitudes'!A8="","",'02_Base_Solicitudes'!E8) -> Yarima Medrano Nazzer | F10: =IF('02_Base_Solicitudes'!A8="","",'02_Base_Solicitudes'!G8) -> directorabiblioteca@unimetro.edu.co | G10: =IF('02_Base_Solicitudes'!A8="","",'02_Base_Solicitudes'!H8) -> Bolsillos de tarjeta de préstamo | H10: =IF('02_Base_Solicitudes'!A8="","",'02_Base_Solicitudes'!I8) -> Bolsillos de tarjeta de préstamo | I10: =IF('02_Base_Solicitudes'!A8="","",'02_Base_Solicitudes'!J8) -> 2000 | J10: =IF('02_Base_Solicitudes'!A8="","",'02_Base_Solicitudes'!M8) -> Normal | K10: =IF('02_Base_Solicitudes'!A8="","",'02_Base_Solicitudes'!K8) -> 46259 | L10: =IF($A10="","","Julio Rivera") -> Julio Rivera | M10: Diseño / Comunicaciones | N10: Sí | O10: 46147 | P10: Diseño, Plancha y Material ya listos. Sin embargo para la creación de los Bolsillos se requiere: Creación de Troquel, grafado y ensamble o pegado del bolsillo. Se requerirá soporte externo para creación de troquel y troquelado del bolsillo, así como del grafado. Se planea pedir el apoyo del personal de biblioteca, una vez teniendo el bolsillo, ellos mismos podrán pegarlo en culquier momento libre. Así optimizamos el recurso y tiempo del personal de imprenta | Q10: Sí | R10: 17 x 10.5 | S10: Una tinta | T10: Bond 75 g | U10: Doblado | V10: Shinohara 52 Bicolor | W10: Sí | X10: No | Y10: 46232 | Z10: 46234 | AA10: 2000 | AB10: 0 | AC10: Sí | AD10: Los bolsillos impresos deben proseguir a un trabajo externo de troquelado y grafado que permitan en corte y doblado de los bolsillos. Posteriormente se le entregarán a la biblioteca para que con apoyo del personal se puedan hacer los pegues correspondientes de los bolsillos. Para la entrega de Bolsillos se requiere un pedido de trabajo externo de torquelado y pegado. Este servicio se pide el 3 de agosto. Solo se aprueba a comienzos de Septiembre y el proveedor entrega el bolsillo el 9 de Septiembre | AE10: 46274 | AF10: =OTMaestraTable[[#This Row],[Solicitante]] -> Yarima Medrano Nazzer | AG10: 46274 | AH10: Cerrada | AI10: =IF(AND(C10<>"",AG10<>""),AG10-C10,"") -> 153 | AJ10: =IF(A10="","",IF(AND(AG10<>"",K10<>""),IF(AG10<=K10,"Sí","No"),"Pendiente")) -> No | AK10: =IF(A10="","",IF(AND($AH10="Cerrada",OR($AE10="",$AF10="",$AG10="")),"⚠ Cerrada incompleta",IF(AND($AH10<>"Cerrada",$AG10<>""),"⚠ Fecha cierre con estado abierto","OK"))) -> OK | AL10: No se cumple el SLA -Service level Agreement o con el dia de entrega por la demora en aprobación del sevicio externo. Sin embargo se recibe a satisfacci´pn por parte de Biblioteca
A11: =IF('02_Base_Solicitudes'!A9="","",'02_Base_Solicitudes'!R9) -> OT-UM-202604-008 | B11: =IF('02_Base_Solicitudes'!A9="","",'02_Base_Solicitudes'!A9) -> 8 | C11: =IF('02_Base_Solicitudes'!A9="","",'02_Base_Solicitudes'!C9) -> 46121 | D11: =IF('02_Base_Solicitudes'!A9="","",'02_Base_Solicitudes'!D9) -> Vicerrectoria - Biblioteca | E11: =IF('02_Base_Solicitudes'!A9="","",'02_Base_Solicitudes'!E9) -> Yarima Medrano Nazzer | F11: =IF('02_Base_Solicitudes'!A9="","",'02_Base_Solicitudes'!G9) -> directorabiblioteca@unimetro.edu.co | G11: =IF('02_Base_Solicitudes'!A9="","",'02_Base_Solicitudes'!H9) -> Adhesivos de Colores para categorizar grupos de Libros | H11: =IF('02_Base_Solicitudes'!A9="","",'02_Base_Solicitudes'!I9) -> Adhesivos de Colores | I11: =IF('02_Base_Solicitudes'!A9="","",'02_Base_Solicitudes'!J9) -> 1300 | J11: =IF('02_Base_Solicitudes'!A9="","",'02_Base_Solicitudes'!M9) -> Normal | K11: =IF('02_Base_Solicitudes'!A9="","",'02_Base_Solicitudes'!K9) -> 46155 | L11: =IF($A11="","","Julio Rivera") -> Julio Rivera | M11: Diseño / Comunicaciones | N11: Sí | O11: 46148 | P11: No requirió diseño, planca tampoco. Si material adhesivo que se utilizó | Q11: Sí | R11: 28 x 22 | S11: Una tinta | T11: Adhesivo | U11: Sin acabado | V11: Shinohara 52 Bicolor | W11: Sí | X11: No | Y11: 46149 | Z11: 46153 | AA11: =OTMaestraTable[[#This Row],[Cantidad]] -> 1300 | AC11: Sí | AD11: Se entregaron por paquetes en Biblioteca según pedido | AE11: 46154 | AF11: =OTMaestraTable[[#This Row],[Solicitante]] -> Yarima Medrano Nazzer | AG11: 46155 | AH11: Cerrada | AI11: =IF(AND(C11<>"",AG11<>""),AG11-C11,"") -> 34 | AJ11: =IF(A11="","",IF(AND(AG11<>"",K11<>""),IF(AG11<=K11,"Sí","No"),"Pendiente")) -> Sí | AK11: =IF(A11="","",IF(AND($AH11="Cerrada",OR($AE11="",$AF11="",$AG11="")),"⚠ Cerrada incompleta",IF(AND($AH11<>"Cerrada",$AG11<>""),"⚠ Fecha cierre con estado abierto","OK"))) -> OK | AL11: Se entregan conforme a los colores solicitados por biblioteca
A12: =IF('02_Base_Solicitudes'!A10="","",'02_Base_Solicitudes'!R10) -> OT-UM-202605-009 | B12: =IF('02_Base_Solicitudes'!A10="","",'02_Base_Solicitudes'!A10) -> 9 | C12: =IF('02_Base_Solicitudes'!A10="","",'02_Base_Solicitudes'!C10) -> 46170 | D12: =IF('02_Base_Solicitudes'!A10="","",'02_Base_Solicitudes'!D10) -> Vicerrectoria - Direccion Administrativa | E12: =IF('02_Base_Solicitudes'!A10="","",'02_Base_Solicitudes'!E10) -> Elio Ortiz | F12: =IF('02_Base_Solicitudes'!A10="","",'02_Base_Solicitudes'!G10) -> eortizg@unimetro.edu.co | G12: =IF('02_Base_Solicitudes'!A10="","",'02_Base_Solicitudes'!H10) -> Hojas membretadas uso institucional para varias dependencias | H12: =IF('02_Base_Solicitudes'!A10="","",'02_Base_Solicitudes'!I10) -> Hojas Membreteadas | I12: =IF('02_Base_Solicitudes'!A10="","",'02_Base_Solicitudes'!J10) -> 5000 | J12: =IF('02_Base_Solicitudes'!A10="","",'02_Base_Solicitudes'!M10) -> Normal | K12: =IF('02_Base_Solicitudes'!A10="","",'02_Base_Solicitudes'!K10) -> 46249 | L12: =IF($A12="","","Julio Rivera") -> Julio Rivera | M12: Diseño / Comunicaciones | N12: Sí | O12: 46206 | P12: Existe Diseño, este es enviado el 3de julio de 2026. El pedido de caja de 10 resmas para prueba piloto, llega el 4 de Julio. Planchas llegan el 8 de Julio. Se aplaza el inicio por el trabajo de las agendas. El 30 deJulio se requiere por parte de gerente administrativo de las hojas membrete. | Q12: Sí | R12: 28 x 22 | S12: Dos tintas | T12: Bond 75 g | U12: Sin acabado | V12: Shinohara 52 Bicolor | W12: Sí | X12: No | Y12: 46237 | Z12: 46238 | AA12: =4850 -> 4850 | AB12: 0 | AC12: Sí | AD12: De las 500 por resma, se entregan 485. Se tuvo un 3% de merma pues no pasó el control de calidad. Tuvimos problema con el sistema de pinzas,que ocacionó el movimiento de la hoja de torre a torre, por lo cual la tinta negra tuvo un pequeño desplazamiento en una hojas | AE12: 46239 | AF12: =OTMaestraTable[[#This Row],[Solicitante]] -> Elio Ortiz | AG12: 46239 | AH12: Cerrada | AI12: =IF(AND(C12<>"",AG12<>""),AG12-C12,"") -> 69 | AJ12: =IF(A12="","",IF(AND(AG12<>"",K12<>""),IF(AG12<=K12,"Sí","No"),"Pendiente")) -> Sí | AK12: =IF(A12="","",IF(AND($AH12="Cerrada",OR($AE12="",$AF12="",$AG12="")),"⚠ Cerrada incompleta",IF(AND($AH12<>"Cerrada",$AG12<>""),"⚠ Fecha cierre con estado abierto","OK"))) -> OK | AL12: Se entregan 9 resmas a Almacén para su custodía y distribución a las dependencias que lo soliciten. 1 resma queda para el servicio de la gerencia administrativa
A13: =IF('02_Base_Solicitudes'!A11="","",'02_Base_Solicitudes'!R11) -> OT-UM-202605-010 | B13: =IF('02_Base_Solicitudes'!A11="","",'02_Base_Solicitudes'!A11) -> 10 | C13: =IF('02_Base_Solicitudes'!A11="","",'02_Base_Solicitudes'!C11) -> 46155 | D13: =IF('02_Base_Solicitudes'!A11="","",'02_Base_Solicitudes'!D11) -> Rectoria - Alta consejeria | E13: =IF('02_Base_Solicitudes'!A11="","",'02_Base_Solicitudes'!E11) -> Julian Ramirez | F13: =IF('02_Base_Solicitudes'!A11="","",'02_Base_Solicitudes'!G11) -> jramirezo@unimetro.edu.co | G13: =IF('02_Base_Solicitudes'!A11="","",'02_Base_Solicitudes'!H11) -> Individuales para bandejas de plazoleta de comidas | H13: =IF('02_Base_Solicitudes'!A11="","",'02_Base_Solicitudes'!I11) -> Individuales para bandejas | I13: =IF('02_Base_Solicitudes'!A11="","",'02_Base_Solicitudes'!J11) -> 3600 | J13: =IF('02_Base_Solicitudes'!A11="","",'02_Base_Solicitudes'!M11) -> Normal | K13: =IF('02_Base_Solicitudes'!A11="","",'02_Base_Solicitudes'!K11) -> 46254 | L13: =IF($A13="","","Julio Rivera") -> Julio Rivera | M13: Diseño / Comunicaciones | N13: Sí | O13: 46155 | P13: Se realizó una prueba con diseño v1. Segundo diseño aprobado por parte de rectoria. Se envía diseño para planchas el 3 de julio. Planchas llegan el 8 de Julio. Pedido del Papel llegó 31 de Julio 2026. Se inicia corte del material el dia 5 de Agosto. | Q13: Sí | R13: 45x 25 | S13: Dos tintas | T13: Otro | U13: Sin acabado | V13: Shinohara 52 Bicolor | W13: Sí | X13: No | Y13: 46241 | Z13: 46244 | AA13: 3660 | AB13: 0 | AC13: Sí | AD13: Se imprimió el dia 5 de Agosto la 2nd plancha, sin embargo despues de imprimir una muestras, se encontró un discrepancia con el fondo negro y el tono azul. Otros detalles como + futuro no era claro y legible. Se explicó al diseñador y se hicieron los cambios respectivos Plancha se recibió el 10 de Ago y se imprimueron las 3.6k piezas. Se lleva a rectoria para decidir corte o no de margen. | AE13: 46245 | AF13: =OTMaestraTable[[#This Row],[Solicitante]] -> Julian Ramirez | AG13: 46245 | AH13: Cerrada | AI13: =IF(AND(C13<>"",AG13<>""),AG13-C13,"") -> 90 | AJ13: =IF(A13="","",IF(AND(AG13<>"",K13<>""),IF(AG13<=K13,"Sí","No"),"Pendiente")) -> Sí | AK13: =IF(A13="","",IF(AND($AH13="Cerrada",OR($AE13="",$AF13="",$AG13="")),"⚠ Cerrada incompleta",IF(AND($AH13<>"Cerrada",$AG13<>""),"⚠ Fecha cierre con estado abierto","OK"))) -> OK
A14: =IF('02_Base_Solicitudes'!A12="","",'02_Base_Solicitudes'!R12) -> OT-UM-202606-011 | B14: =IF('02_Base_Solicitudes'!A12="","",'02_Base_Solicitudes'!A12) -> 11 | C14: =IF('02_Base_Solicitudes'!A12="","",'02_Base_Solicitudes'!C12) -> 46185 | D14: =IF('02_Base_Solicitudes'!A12="","",'02_Base_Solicitudes'!D12) -> Rectoria - Comunicaciones y Mercadeo | E14: =IF('02_Base_Solicitudes'!A12="","",'02_Base_Solicitudes'!E12) -> Camilo Robledo | F14: =IF('02_Base_Solicitudes'!A12="","",'02_Base_Solicitudes'!G12) -> coordinadordecontenidos@unimetro.edu.co | G14: =IF('02_Base_Solicitudes'!A12="","",'02_Base_Solicitudes'!H12) -> Volantes de programas académicos Pregado- Medicina - Nutrición y Dietética | H14: =IF('02_Base_Solicitudes'!A12="","",'02_Base_Solicitudes'!I12) -> Volantes | I14: =IF('02_Base_Solicitudes'!A12="","",'02_Base_Solicitudes'!J12) -> 3000 | J14: =IF('02_Base_Solicitudes'!A12="","",'02_Base_Solicitudes'!M12) -> Normal | K14: =IF('02_Base_Solicitudes'!A12="","",'02_Base_Solicitudes'!K12) -> 46295 | L14: =IF($A14="","","Julio Rivera") -> Julio Rivera | M14: Diseño / Comunicaciones | N14: Sí | O14: 46261 | P14: Se diseñan en policromia en el tiro y el retiro en 2 tintas con la información pertinente a cada disciplina | Q14: Sí | R14: 24x16 | S14: Full color | T14: Propalcote200 | U14: Corte | V14: Shinohara 52 Bicolor | W14: Sí | X14: No | Y14: 46273 | Z14: 46283 | AA14: =4000+OTMaestraTable[[#This Row],[Entrega Parcial]] -> 4100 | AB14: 100 | AC14: Sí | AD14: Se imprime inicialmente el retiro de los programas en dia 10 de Septiembre. Se termina impresión Lunes 14 de Septiembre. Sin embargo se nota que el azul del tiro no es trama, es via punto de color, lo que deja el color palido. Se decide pasar de nuevo por la impresora agregando barniz con color C y M para destacar más el color. Se entregan 50 unidades de cada disciplina a Rectoria. 17/09/26 Se prosigue con el corte definitivo de todos los volantes para entrega definitiva el 18/09/26 | AE14: 46286 | AF14: =OTMaestraTable[[#This Row],[Solicitante]] -> Camilo Robledo | AG14: 46286 | AH14: Cerrada | AI14: =IF(AND(C14<>"",AG14<>""),AG14-C14,"") -> 101 | AJ14: =IF(A14="","",IF(AND(AG14<>"",K14<>""),IF(AG14<=K14,"Sí","No"),"Pendiente")) -> Sí | AK14: =IF(A14="","",IF(AND($AH14="Cerrada",OR($AE14="",$AF14="",$AG14="")),"⚠ Cerrada incompleta",IF(AND($AH14<>"Cerrada",$AG14<>""),"⚠ Fecha cierre con estado abierto","OK"))) -> OK | AL14: Se recomienda al dpto de comunicaciones mejorar el diseño para dejar el fondo en fondo completo o parche y no trama o pixelado pues el fondo no se ve vivo y con fuerza. Se intentó mejorar el producto aplicando barniz en una segunda pasada a todos los volantes, mejoró pero no como se ve en digital
A15: =IF('02_Base_Solicitudes'!A13="","",'02_Base_Solicitudes'!R13) -> OT-UM-202606-012 | B15: =IF('02_Base_Solicitudes'!A13="","",'02_Base_Solicitudes'!A13) -> 12 | C15: =IF('02_Base_Solicitudes'!A13="","",'02_Base_Solicitudes'!C13) -> 46185 | D15: =IF('02_Base_Solicitudes'!A13="","",'02_Base_Solicitudes'!D13) -> Rectoria - Comunicaciones y Mercadeo | E15: =IF('02_Base_Solicitudes'!A13="","",'02_Base_Solicitudes'!E13) -> Camilo Robledo | F15: =IF('02_Base_Solicitudes'!A13="","",'02_Base_Solicitudes'!G13) -> coordinadordecontenidos@unimetro.edu.co | G15: =IF('02_Base_Solicitudes'!A13="","",'02_Base_Solicitudes'!H13) -> Volante progamas Pregrado - Bacteriología-Enfermeria-Fisioterapia- Trabajo Social | H15: =IF('02_Base_Solicitudes'!A13="","",'02_Base_Solicitudes'!I13) -> Volantes | I15: =IF('02_Base_Solicitudes'!A13="","",'02_Base_Solicitudes'!J13) -> 4000 | J15: =IF('02_Base_Solicitudes'!A13="","",'02_Base_Solicitudes'!M13) -> Normal | K15: =IF('02_Base_Solicitudes'!A13="","",'02_Base_Solicitudes'!K13) -> 46295 | L15: =IF($A15="","","Julio Rivera") -> Julio Rivera | M15: Diseño / Comunicaciones | N15: Sí | O15: 46261 | P15: Se diseñan en policromia en el tiro y el retiro en 2 tintas con la información pertinente a cada disciplina | Q15: Sí | R15: 24x16 | S15: Full color | T15: Propalcote200 | U15: Corte | V15: Shinohara 52 Bicolor | W15: Sí | X15: No | Y15: 46273 | AA15: =4000+OTMaestraTable[[#This Row],[Entrega Parcial]] -> 4200 | AB15: 200 | AC15: Sí | AD15: Se imprime inicialmente el retiro de los programas en dia 10 de Septiembre. Se termina impresión Lunes 14 de Septiembre. Sin embargo se nota que el azul del tiro no es trama, es via punto de color, lo que deja el color palido. Se decide pasar de nuevo por la impresora agregando barniz con color C y M para destacar más el color | AE15: 46286 | AF15: =OTMaestraTable[[#This Row],[Solicitante]] -> Camilo Robledo | AG15: 46286 | AH15: Cerrada | AI15: =IF(AND(C15<>"",AG15<>""),AG15-C15,"") -> 101 | AJ15: =IF(A15="","",IF(AND(AG15<>"",K15<>""),IF(AG15<=K15,"Sí","No"),"Pendiente")) -> Sí | AK15: =IF(A15="","",IF(AND($AH15="Cerrada",OR($AE15="",$AF15="",$AG15="")),"⚠ Cerrada incompleta",IF(AND($AH15<>"Cerrada",$AG15<>""),"⚠ Fecha cierre con estado abierto","OK"))) -> OK | AL15: Se recomienda al dpto de comunicaciones mejorar el diseño para dejar el fondo en fondo completo o parche y no trama o pixelado pues el fondo no se ve vivo y con fuerza. Se intentó mejorar el producto aplicando barniz en una segunda pasada a todos los volantes, mejoró pero no como se ve en digital
A16: =IF('02_Base_Solicitudes'!A14="","",'02_Base_Solicitudes'!R14) -> OT-UM-202606-013 | B16: =IF('02_Base_Solicitudes'!A14="","",'02_Base_Solicitudes'!A14) -> 13 | C16: =IF('02_Base_Solicitudes'!A14="","",'02_Base_Solicitudes'!C14) -> 46185 | D16: =IF('02_Base_Solicitudes'!A14="","",'02_Base_Solicitudes'!D14) -> Rectoria - Comunicaciones y Mercadeo | E16: =IF('02_Base_Solicitudes'!A14="","",'02_Base_Solicitudes'!E14) -> Camilo Robledo | F16: =IF('02_Base_Solicitudes'!A14="","",'02_Base_Solicitudes'!G14) -> coordinadordecontenidos@unimetro.edu.co | G16: =IF('02_Base_Solicitudes'!A14="","",'02_Base_Solicitudes'!H14) -> Volante programas pregrado - Odontología - Optometría - Psicología - Terapia Ocupacional | H16: =IF('02_Base_Solicitudes'!A14="","",'02_Base_Solicitudes'!I14) -> Volantes | I16: =IF('02_Base_Solicitudes'!A14="","",'02_Base_Solicitudes'!J14) -> 4000 | J16: =IF('02_Base_Solicitudes'!A14="","",'02_Base_Solicitudes'!M14) -> Normal | K16: =IF('02_Base_Solicitudes'!A14="","",'02_Base_Solicitudes'!K14) -> 46295 | L16: =IF($A16="","","Julio Rivera") -> Julio Rivera | M16: Diseño / Comunicaciones | N16: Sí | O16: 46261 | P16: Se diseñan en policromia en el tiro y el retiro en 2 tintas con la información pertinente a cada disciplina | Q16: Sí | R16: 24x16 | S16: Full color | T16: Propalcote200 | U16: Corte | V16: Shinohara 52 Bicolor | W16: Sí | X16: No | Y16: 46273 | AA16: =4000+OTMaestraTable[[#This Row],[Entrega Parcial]] -> 4200 | AB16: 200 | AC16: Sí | AD16: Se imprime inicialmente el retiro de los programas en dia 10 de Septiembre. Se encuentra un error de impresión en plancha por faltante del ejemplar Yellow. Se comunica con el proveedor para subsanar el inconveniente | AE16: 46286 | AF16: =OTMaestraTable[[#This Row],[Solicitante]] -> Camilo Robledo | AG16: 46286 | AH16: Cerrada | AI16: =IF(AND(C16<>"",AG16<>""),AG16-C16,"") -> 101 | AJ16: =IF(A16="","",IF(AND(AG16<>"",K16<>""),IF(AG16<=K16,"Sí","No"),"Pendiente")) -> Sí | AK16: =IF(A16="","",IF(AND($AH16="Cerrada",OR($AE16="",$AF16="",$AG16="")),"⚠ Cerrada incompleta",IF(AND($AH16<>"Cerrada",$AG16<>""),"⚠ Fecha cierre con estado abierto","OK"))) -> OK | AL16: Se recomienda al dpto de comunicaciones mejorar el diseño para dejar el fondo en fondo completo o parche y no trama o pixelado pues el fondo no se ve vivo y con fuerza. Se intentó mejorar el producto aplicando barniz en una segunda pasada a todos los volantes, mejoró pero no como se ve en digital
A17: =IF('02_Base_Solicitudes'!A15="","",'02_Base_Solicitudes'!R15) -> OT-UM-202606-014 | B17: =IF('02_Base_Solicitudes'!A15="","",'02_Base_Solicitudes'!A15) -> 14 | C17: =IF('02_Base_Solicitudes'!A15="","",'02_Base_Solicitudes'!C15) -> 46200 | D17: =IF('02_Base_Solicitudes'!A15="","",'02_Base_Solicitudes'!D15) -> Vicerrectoria | E17: =IF('02_Base_Solicitudes'!A15="","",'02_Base_Solicitudes'!E15) -> Jose Luis Castro Guerra | F17: =IF('02_Base_Solicitudes'!A15="","",'02_Base_Solicitudes'!G15) -> vice-rectoria@unimetro.edu.co | G17: =IF('02_Base_Solicitudes'!A15="","",'02_Base_Solicitudes'!H15) -> Agendas - 2ndo lote de 500 unidades para 30Sep | H17: =IF('02_Base_Solicitudes'!A15="","",'02_Base_Solicitudes'!I15) -> Agendas | I17: =IF('02_Base_Solicitudes'!A15="","",'02_Base_Solicitudes'!J15) -> 500 | J17: =IF('02_Base_Solicitudes'!A15="","",'02_Base_Solicitudes'!M15) -> Programado | K17: =IF('02_Base_Solicitudes'!A15="","",'02_Base_Solicitudes'!K15) -> 46310 | L17: =IF($A17="","","Julio Rivera") -> Julio Rivera | M17: Diseño / Comunicaciones | N17: Sí | O17: 46175 | P17: Se requiere que la portada sea la imagen del hospital y la contraportada, la imagen de las carreras de fondo azul | Q17: Sí | R17: 16x22 | S17: Full color | T17: Bond 75 g | U17: Anillado | V17: Shinohara 52 Bicolor | W17: Sí | X17: No | Y17: 46280 | AA17: 500 | AB17: =50+40+50+6+10+2+130+212 -> 500 | AC17: Sí | AD17: Se ensamblan 50 agendas con extra de papel del primer lote, pero portadas del 2ndo lote. En entregan 50 a Rectoria el 3 de Agosto.Se inicia el corte de las resmas el 13 de Agosto. Se inicia la impresión el 21 de Agosto. Se finaliza impresión 26 de Agosto. Inicio de corte de paginas agendas este mismo dia. En espera de reparacion de plastificadora para que se puedan ensamblar las tapas que estan con el proveedor . 28 de Agosto se entregan 40 para evento de Voluntariado en Medellin. Se entregan 56 a Rectoria el 15 y 16 de Septiembre. | AE17: 46297 | AF17: =OTMaestraTable[[#This Row],[Solicitante]] -> Jose Luis Castro Guerra | AG17: 46297 | AH17: Cerrada | AI17: =IF(AND(C17<>"",AG17<>""),AG17-C17,"") -> 97 | AJ17: =IF(A17="","",IF(AND(AG17<>"",K17<>""),IF(AG17<=K17,"Sí","No"),"Pendiente")) -> Sí | AK17: =IF(A17="","",IF(AND($AH17="Cerrada",OR($AE17="",$AF17="",$AG17="")),"⚠ Cerrada incompleta",IF(AND($AH17<>"Cerrada",$AG17<>""),"⚠ Fecha cierre con estado abierto","OK"))) -> OK | AL17: Se han producido 93 en total de este nuevo lote. 50 Se entregaron a Rectoria y 40 a voluntariado para evento en Medellin el 28 de Agosto. Ver Email de aprobación. !0 perdido recotira 23 Sep + 2 x unidades visita del Dr.130 emtregadas el 29 de Sep. Se termina de ensamblar las últimas 212 agendas para completar las 500 del mes de septiembre.Se Iban a entregar el 2 de Octubre pero Rectoria decidió dejarlas en Imprenta por espacio. Se cierra la Orden el mismo dia de la entrega telefonica. En espera que las reciban en Rectoria
A18: =IF('02_Base_Solicitudes'!A16="","",'02_Base_Solicitudes'!R16) -> OT-UM-202609-015 | B18: =IF('02_Base_Solicitudes'!A16="","",'02_Base_Solicitudes'!A16) -> 15 | C18: =IF('02_Base_Solicitudes'!A16="","",'02_Base_Solicitudes'!C16) -> 46267 | D18: =IF('02_Base_Solicitudes'!A16="","",'02_Base_Solicitudes'!D16) -> Rectoria - Alta consejeria | E18: =IF('02_Base_Solicitudes'!A16="","",'02_Base_Solicitudes'!E16) -> Camilo Robledo | F18: =IF('02_Base_Solicitudes'!A16="","",'02_Base_Solicitudes'!G16) -> coordinadordecontenidos@unimetro.edu.co | G18: =IF('02_Base_Solicitudes'!A16="","",'02_Base_Solicitudes'!H16) -> Calendario 2027 | H18: =IF('02_Base_Solicitudes'!A16="","",'02_Base_Solicitudes'!I16) -> Calendarios | I18: =IF('02_Base_Solicitudes'!A16="","",'02_Base_Solicitudes'!J16) -> 4000 | J18: =IF('02_Base_Solicitudes'!A16="","",'02_Base_Solicitudes'!M16) -> Programado | K18: =IF('02_Base_Solicitudes'!A16="","",'02_Base_Solicitudes'!K16) -> 46326 | L18: =IF($A18="","","Julio Rivera") -> Julio Rivera | M18: Diseño / Comunicaciones | N18: =IF($A18="","","No") -> No | P18: En proceso de diseño. 1 sola virgen.Opciones deben ser presentadas a Rectoria para aprobación | Q18: No | R18: 16x22 | S18: Full color | T18: Propalcote320 | U18: Plastificado brillante | V18: Shinohara 52 Bicolor | W18: Sí | X18: Sí | Y18: 46296 | AC18: =IF($A18="","","Pendiente") -> Pendiente | AF18: =OTMaestraTable[[#This Row],[Solicitante]] -> Camilo Robledo | AH18: Diseño | AI18: =IF(AND(C18<>"",AG18<>""),AG18-C18,"") | AJ18: =IF(A18="","",IF(AND(AG18<>"",K18<>""),IF(AG18<=K18,"Sí","No"),"Pendiente")) -> Pendiente | AK18: =IF(A18="","",IF(AND($AH18="Cerrada",OR($AE18="",$AF18="",$AG18="")),"⚠ Cerrada incompleta",IF(AND($AH18<>"Cerrada",$AG18<>""),"⚠ Fecha cierre con estado abierto","OK"))) -> OK
A19: =IF('02_Base_Solicitudes'!A17="","",'02_Base_Solicitudes'!R17) -> OT-UM-202608-016 | B19: =IF('02_Base_Solicitudes'!A17="","",'02_Base_Solicitudes'!A17) -> 16 | C19: =IF('02_Base_Solicitudes'!A17="","",'02_Base_Solicitudes'!C17) -> 46238 | D19: =IF('02_Base_Solicitudes'!A17="","",'02_Base_Solicitudes'!D17) -> Vicerrectoria - Direccion de bienestar universitario | E19: =IF('02_Base_Solicitudes'!A17="","",'02_Base_Solicitudes'!E17) -> Katty Aguas Gamarra | F19: =IF('02_Base_Solicitudes'!A17="","",'02_Base_Solicitudes'!G17) -> desarrollohumano@unimetro.edu.co | G19: =IF('02_Base_Solicitudes'!A17="","",'02_Base_Solicitudes'!H17) -> ACTUALIZACION DE FOLLETO DE SALUD MENTAL | H19: =IF('02_Base_Solicitudes'!A17="","",'02_Base_Solicitudes'!I17) -> Folletos | I19: =IF('02_Base_Solicitudes'!A17="","",'02_Base_Solicitudes'!J17) -> 2000 | J19: =IF('02_Base_Solicitudes'!A17="","",'02_Base_Solicitudes'!M17) -> Programado | K19: =IF('02_Base_Solicitudes'!A17="","",'02_Base_Solicitudes'!K17) -> 46275 | L19: =IF($A19="","","Julio Rivera") -> Julio Rivera | M19: Diseño / Comunicaciones | N19: Sí | O19: 46240 | P19: El diseño fue enviado por Katty de las Aguas de desarrollo humano. Debe ser validado por ComyMercadeo. Igual que la aprobación. Se recibe aprobación del diseño el 6 de Agosto. Se hae pedido de planchas y envio de diseño el 11 de Agosto. | Q19: Sí | R19: 33x23 | S19: Full color | T19: Propalcote200 | U19: Corte | V19: Shinohara 52 Bicolor | W19: Sí | X19: Sí | Y19: 46252 | Z19: 46254 | AA19: 2000 | AB19: 0 | AC19: Sí | AD19: Se inicia con el corte de las formatos a imprimir en policromia a partir del 18 de Agosto. A pesar que el pedido es para el 10 de Septiembre, se está agilizando de tal manera que se pueda entregar el proyecto el 19 del mes de Agosto. | AE19: 46255 | AF19: =OTMaestraTable[[#This Row],[Solicitante]] -> Katty Aguas Gamarra | AG19: 46255 | AH19: Cerrada | AI19: =IF(AND(C19<>"",AG19<>""),AG19-C19,"") -> 17 | AJ19: =IF(A19="","",IF(AND(AG19<>"",K19<>""),IF(AG19<=K19,"Sí","No"),"Pendiente")) -> Sí | AK19: =IF(A19="","",IF(AND($AH19="Cerrada",OR($AE19="",$AF19="",$AG19="")),"⚠ Cerrada incompleta",IF(AND($AH19<>"Cerrada",$AG19<>""),"⚠ Fecha cierre con estado abierto","OK"))) -> OK | AL19: Se entregan los 2000 ejemplares requeridos por Bienestar universitario. Se le comenta a Comunicaciones algunos detalles para mejorar en cuestión del diseño que permitan un corte sin comprometer el tamaño y diseño de la pieza. Se deja la notificación de requerir compra, pues se usó material que tenia otra finalidad. Se debe enviar a compra con cargo a Bienestar. Total invertido 1 resma de Propalcote200
A20: =IF('02_Base_Solicitudes'!A18="","",'02_Base_Solicitudes'!R18) -> OT-UM-202608-017 | B20: =IF('02_Base_Solicitudes'!A18="","",'02_Base_Solicitudes'!A18) -> 17 | C20: =IF('02_Base_Solicitudes'!A18="","",'02_Base_Solicitudes'!C18) -> 46238 | D20: =IF('02_Base_Solicitudes'!A18="","",'02_Base_Solicitudes'!D18) -> Rectoria - Comunicaciones y Mercadeo | E20: =IF('02_Base_Solicitudes'!A18="","",'02_Base_Solicitudes'!E18) -> Julio Higgins | F20: =IF('02_Base_Solicitudes'!A18="","",'02_Base_Solicitudes'!G18) -> relacionespublicas@unimetro.edu.co | G20: =IF('02_Base_Solicitudes'!A18="","",'02_Base_Solicitudes'!H18) -> Volantes Pregrado y Postgrado Unimetro | H20: =IF('02_Base_Solicitudes'!A18="","",'02_Base_Solicitudes'!I18) -> Volantes | I20: =IF('02_Base_Solicitudes'!A18="","",'02_Base_Solicitudes'!J18) -> 500 | J20: =IF('02_Base_Solicitudes'!A18="","",'02_Base_Solicitudes'!M18) -> Urgente | K20: =IF('02_Base_Solicitudes'!A18="","",'02_Base_Solicitudes'!K18) -> 46239 | L20: =IF($A20="","","Julio Rivera") -> Julio Rivera | M20: Diseño / Comunicaciones | N20: Sí | O20: 46238 | P20: Se utilizará el diseño anterior que contaba con 10 programas de pre y post grado. Se recomienda al departamento de comunicaciones y mercadeo realizar un nuevo diseño para el próximo batch | Q20: Sí | R20: 21x15 | S20: Dos tintas | T20: Propalcote200 | U20: Corte | V20: Shinohara 52 Bicolor | W20: Sí | X20: Sí | Y20: 46238 | Z20: 46238 | AA20: 900 | AB20: 0 | AC20: Sí | AD20: Se entregan a Rectoria los volantes informativos con QR. QR carga correctamente. No se plastifican. Se imprimen en alta calidad en propalcote200. | AE20: 46239 | AF20: =OTMaestraTable[[#This Row],[Solicitante]] -> Julio Higgins | AG20: 46239 | AH20: Cerrada | AI20: =IF(AND(C20<>"",AG20<>""),AG20-C20,"") -> 1 | AJ20: =IF(A20="","",IF(AND(AG20<>"",K20<>""),IF(AG20<=K20,"Sí","No"),"Pendiente")) -> Sí | AK20: =IF(A20="","",IF(AND($AH20="Cerrada",OR($AE20="",$AF20="",$AG20="")),"⚠ Cerrada incompleta",IF(AND($AH20<>"Cerrada",$AG20<>""),"⚠ Fecha cierre con estado abierto","OK"))) -> OK | AL20: Se entrega a Rectoria las 900 unidades para el evento que tiene relaciones públicas el 6 de Agosto
A21: =IF('02_Base_Solicitudes'!A19="","",'02_Base_Solicitudes'!R19) -> OT-UM-202608-018 | B21: =IF('02_Base_Solicitudes'!A19="","",'02_Base_Solicitudes'!A19) -> 18 | C21: =IF('02_Base_Solicitudes'!A19="","",'02_Base_Solicitudes'!C19) -> 46238 | D21: =IF('02_Base_Solicitudes'!A19="","",'02_Base_Solicitudes'!D19) -> Vicerrectoria - Direccion de bienestar universitario | E21: =IF('02_Base_Solicitudes'!A19="","",'02_Base_Solicitudes'!E19) -> Katty Aguas Gamarra | F21: =IF('02_Base_Solicitudes'!A19="","",'02_Base_Solicitudes'!G19) -> desarrollohumano@unimetro.edu.co | G21: =IF('02_Base_Solicitudes'!A19="","",'02_Base_Solicitudes'!H19) -> ACTUALIZACION DE FOLLETO DE LOS SERVICIOS DE BIENESTAR UNIVERSITARIO | H21: =IF('02_Base_Solicitudes'!A19="","",'02_Base_Solicitudes'!I19) -> Folletos | I21: =IF('02_Base_Solicitudes'!A19="","",'02_Base_Solicitudes'!J19) -> 2000 | J21: =IF('02_Base_Solicitudes'!A19="","",'02_Base_Solicitudes'!M19) -> Programado | K21: =IF('02_Base_Solicitudes'!A19="","",'02_Base_Solicitudes'!K19) -> 46296 | L21: =IF($A21="","","Julio Rivera") -> Julio Rivera | M21: Diseño / Comunicaciones | N21: Sí | O21: 46240 | P21: Se recibe aprobación del diseño el 6 de Agosto. Se hae pedido de planchas y envio de diseño el 11 de Agosto. | Q21: Sí | R21: 48x33 | S21: Full color | T21: Propalcote200 | U21: Corte | V21: Shinohara 52 Bicolor | W21: Sí | X21: Sí | Y21: 46252 | Z21: 46254 | AA21: 2000 | AB21: 0 | AC21: Sí | AD21: Se inicia con el corte de las formatos a imprimir en policromia a partir del 18 de Agosto. En paralelo se esta trabajando en la entrega lo antes posible, 22 20 o 21 de Agosto de los servicios de bienestar, 1 mes y 1o dias antes del dia requerido por la cliente interno.Se identificaron detalles en el diseño por mejorar, en cuanto al color, alieanción de textos, etc | AE21: 46255 | AF21: =OTMaestraTable[[#This Row],[Solicitante]] -> Katty Aguas Gamarra | AG21: 46255 | AH21: Cerrada | AI21: =IF(AND(C21<>"",AG21<>""),AG21-C21,"") -> 17 | AJ21: =IF(A21="","",IF(AND(AG21<>"",K21<>""),IF(AG21<=K21,"Sí","No"),"Pendiente")) -> Sí | AK21: =IF(A21="","",IF(AND($AH21="Cerrada",OR($AE21="",$AF21="",$AG21="")),"⚠ Cerrada incompleta",IF(AND($AH21<>"Cerrada",$AG21<>""),"⚠ Fecha cierre con estado abierto","OK"))) -> OK | AL21: Se entregaron parcialmente el dia 19 de Agosto 370 unidades. El dia 21 dia de cierre de la orden se entregaron las unidades pendientes para alcanzar un total de 2000. Se deja la notificación de requerir compra, pues se usó material que tenia otra finalidad. Se debe enviar a compra con cargo a Bienestar. Total invertidas 2 resmas de Propalcote 200
A22: =IF('02_Base_Solicitudes'!A20="","",'02_Base_Solicitudes'!R20) -> OT-UM-202608-019 | B22: =IF('02_Base_Solicitudes'!A20="","",'02_Base_Solicitudes'!A20) -> 19 | C22: =IF('02_Base_Solicitudes'!A20="","",'02_Base_Solicitudes'!C20) -> 46245 | D22: =IF('02_Base_Solicitudes'!A20="","",'02_Base_Solicitudes'!D20) -> Rectoria - Comunicaciones y Mercadeo | E22: =IF('02_Base_Solicitudes'!A20="","",'02_Base_Solicitudes'!E20) -> Julio Higgins | F22: =IF('02_Base_Solicitudes'!A20="","",'02_Base_Solicitudes'!G20) -> relacionespublicas@unimetro.edu.co | G22: =IF('02_Base_Solicitudes'!A20="","",'02_Base_Solicitudes'!H20) -> Volantes QR Pregrado y Postgrado Actualizado Unimetro | H22: =IF('02_Base_Solicitudes'!A20="","",'02_Base_Solicitudes'!I20) -> Volantes | I22: =IF('02_Base_Solicitudes'!A20="","",'02_Base_Solicitudes'!J20) -> 2000 | J22: Programado | K22: =IF('02_Base_Solicitudes'!A20="","",'02_Base_Solicitudes'!K20) -> 46295 | L22: =IF($A22="","","Julio Rivera") -> Julio Rivera | M22: Diseño / Comunicaciones | N22: Sí | O22: 46245 | P22: Se aprobó una nueva versión del volante infomativo de las carreras, Este volante informativo se requiere para todo el año, es decir, una buena cantidad de ejemplares se requieren. Para H2 se harán 3000 y se esperan complementar con los dedicados a cada programa | Q22: Sí | R22: 33x23 | S22: Dos tintas | T22: Propalcote200 | U22: Corte | V22: Shinohara 52 Bicolor | W22: Sí | X22: Sí | Y22: 46260 | Z22: 46261 | AA22: 2000 | AB22: 0 | AC22: Sí | AD22: Se debio repetir el planchas pues hubno un error en las primeras planchas desde el diseño,se ajusto el color azul y negro. Se emplean 120 pliegos, casi la resma completa de propalcote 200. . Se refila y corta según tamaño estandar Se aprovecha la empresión anterior que tiene azul y negro (hojas de agendas) para darle continuidad e a la impresión de los volantes | AE22: 46262 | AF22: =OTMaestraTable[[#This Row],[Solicitante]] -> Julio Higgins | AG22: 46262 | AH22: Cerrada | AI22: =IF(AND(C22<>"",AG22<>""),AG22-C22,"") -> 17 | AJ22: =IF(A22="","",IF(AND(AG22<>"",K22<>""),IF(AG22<=K22,"Sí","No"),"Pendiente")) -> Sí | AK22: =IF(A22="","",IF(AND($AH22="Cerrada",OR($AE22="",$AF22="",$AG22="")),"⚠ Cerrada incompleta",IF(AND($AH22<>"Cerrada",$AG22<>""),"⚠ Fecha cierre con estado abierto","OK"))) -> OK | AL22: Se entregan en Rectoria el dia 28 de Agosto.
A23: =IF('02_Base_Solicitudes'!A21="","",'02_Base_Solicitudes'!R21) -> OT-UM-202608-020 | B23: =IF('02_Base_Solicitudes'!A21="","",'02_Base_Solicitudes'!A21) -> 20 | C23: =IF('02_Base_Solicitudes'!A21="","",'02_Base_Solicitudes'!C21) -> 46259 | D23: =IF('02_Base_Solicitudes'!A21="","",'02_Base_Solicitudes'!D21) -> Rectoria | E23: =IF('02_Base_Solicitudes'!A21="","",'02_Base_Solicitudes'!E21) -> Lidia Cala | F23: =IF('02_Base_Solicitudes'!A21="","",'02_Base_Solicitudes'!G21) -> rectoriaunimetro@unimetro.edu.co | G23: =IF('02_Base_Solicitudes'!A21="","",'02_Base_Solicitudes'!H21) -> Miniblocks - pieza uso interno unimetro | H23: =IF('02_Base_Solicitudes'!A21="","",'02_Base_Solicitudes'!I21) -> MiniBlocks | I23: 1000 | J23: Programado | K23: =IF('02_Base_Solicitudes'!A21="","",'02_Base_Solicitudes'!K21) -> 46295 | L23: =IF($A23="","","Julio Rivera") -> Julio Rivera | M23: Comunicaciones | N23: Sí | O23: 46259 | P23: Se utilizará el mismo diseño con que se realizaron los primeros miniblocks que se entregaron iniciando esta administración en OT-UM-202605-001. Se realizarán en propalcote 300, un material mas delgado que el previamente usado para las portadas | Q23: Sí | R23: 42x28 | S23: Dos tintas | T23: Propalcote300 | U23: Plastificado mate | V23: Shinohara 52 Bicolor | W23: Sí | X23: Sí | Y23: 46261 | Z23: 46293 | AA23: 1152 | AB23: =50+110+220+340+280 -> 1000 | AC23: Sí | AD23: Se Inició el proceso de impresión de las hojas para las 1000 libretas o miniblocks el dia 27 ago con el corte e inicio de impresion. Rectoria aprueba 50 unidades para entrega a Camilo Robledo para evento en Medellin. Se hace el ensamble el 29 de Agosto. Se entregan 100 el dia 9 de Septiembre a Rectoria. Se entregan a Rectoria 110 ejemplares el 4 de Sept. Pedido Vicerectoria de 220 unidades de un dia para otro, sin plastificar por falta de plastico. Las 620 unidades restantes se harán con media plastificación en contraportada azul. Pedido pendiente por parte de compras del rollo de plástico. | AE23: 46294 | AF23: =OTMaestraTable[[#This Row],[Solicitante]] -> Lidia Cala | AG23: 46294 | AH23: Cerrada | AI23: =IF(AND(C23<>"",AG23<>""),AG23-C23,"") -> 35 | AJ23: =IF(A23="","",IF(AND(AG23<>"",K23<>""),IF(AG23<=K23,"Sí","No"),"Pendiente")) -> Sí | AK23: =IF(A23="","",IF(AND($AH23="Cerrada",OR($AE23="",$AF23="",$AG23="")),"⚠ Cerrada incompleta",IF(AND($AH23<>"Cerrada",$AG23<>""),"⚠ Fecha cierre con estado abierto","OK"))) -> OK | AL23: Se han producido 50 Se entregaron a Rectoria y a voluntariado para evento en Medellin el 28 de Agosto. Ver Email de aprobación.220 unidades se entegaron en modo urgente a vicerrectoria para evento en Colegio Colón y otro colegio el 22 de Sept 2026. Se entregan 340 el 28 de Sep y 280 el 29 de Sept para completar 1000 unidades acordadas con Rectoria. Se dejan 152 unidades para cubrir el intervalo de tiempo mientras se inicia la nueva produccion para Oct y Nov.
A24: =IF('02_Base_Solicitudes'!A22="","",'02_Base_Solicitudes'!R22) -> OT-UM-202608-021 | B24: =IF('02_Base_Solicitudes'!A22="","",'02_Base_Solicitudes'!A22) -> 21 | C24: =IF('02_Base_Solicitudes'!A22="","",'02_Base_Solicitudes'!C22) -> 46260 | D24: =IF('02_Base_Solicitudes'!A22="","",'02_Base_Solicitudes'!D22) -> Vicerrectoria - Direccion de bienestar universitario | E24: =IF('02_Base_Solicitudes'!A22="","",'02_Base_Solicitudes'!E22) -> Katty Aguas Gamarra | F24: =IF('02_Base_Solicitudes'!A22="","",'02_Base_Solicitudes'!G22) -> desarrollohumano@unimetro.edu.co | G24: =IF('02_Base_Solicitudes'!A22="","",'02_Base_Solicitudes'!H22) -> Separadores de libros sobre salud mental | H24: =IF('02_Base_Solicitudes'!A22="","",'02_Base_Solicitudes'!I22) -> Separadores de libros | I24: =IF('02_Base_Solicitudes'!A22="","",'02_Base_Solicitudes'!J22) -> 1000 | J24: Programado | K24: =IF('02_Base_Solicitudes'!A22="","",'02_Base_Solicitudes'!K22) -> 46274 | L24: =IF($A24="","","Julio Rivera") -> Julio Rivera | M24: Diseño / Comunicaciones | N24: Sí | O24: 46261 | P24: Se recomienda al Dpto de Com y Mercadeo el ajuste del diseño tal que aparezca completa la regla. Se dejan los vertices cuadrados de la regla/separador. Llegada de planchas el 2 de Sept. En espera de finalizacion Mto de Shonohara y limpieza para inicio de impresion el 4 de sept y plastificación el 7. Entrega esperada el 9 de Sep. | Q24: Sí | R24: 33x23 | S24: Full color | T24: Propalcote300 | U24: Corte | V24: Shinohara 52 Bicolor | W24: Sí | X24: Sí | Y24: 46269 | Z24: 46272 | AA24: 1000 | AB24: 0 | AC24: Sí | AD24: Se plastificaron los separadores con plástico mate , tal cual era la muestra proporcionada por comunicaciones. Se cortan en angulo recto en guillotina de la Imprenta | AE24: 46273 | AF24: =OTMaestraTable[[#This Row],[Solicitante]] -> Katty Aguas Gamarra | AG24: 46273 | AH24: Cerrada | AI24: =IF(AND(C24<>"",AG24<>""),AG24-C24,"") -> 13 | AJ24: =IF(A24="","",IF(AND(AG24<>"",K24<>""),IF(AG24<=K24,"Sí","No"),"Pendiente")) -> Sí | AK24: =IF(A24="","",IF(AND($AH24="Cerrada",OR($AE24="",$AF24="",$AG24="")),"⚠ Cerrada incompleta",IF(AND($AH24<>"Cerrada",$AG24<>""),"⚠ Fecha cierre con estado abierto","OK"))) -> OK | AL24: Se entregan los separadores a Katty de las Aguas ocn el conocimiento y OK de Rectoria.
A25: =IF('02_Base_Solicitudes'!A23="","",'02_Base_Solicitudes'!R23) -> OT-UM-202609-022 | B25: =IF('02_Base_Solicitudes'!A23="","",'02_Base_Solicitudes'!A23) -> 22 | C25: =IF('02_Base_Solicitudes'!A23="","",'02_Base_Solicitudes'!C23) -> 46272 | D25: =IF('02_Base_Solicitudes'!A23="","",'02_Base_Solicitudes'!D23) -> Rectoria | E25: =IF('02_Base_Solicitudes'!A23="","",'02_Base_Solicitudes'!E23) -> Lidia Cala | F25: =IF('02_Base_Solicitudes'!A23="","",'02_Base_Solicitudes'!G23) -> rectoriaunimetro@unimetro.edu.co | G25: =IF('02_Base_Solicitudes'!A23="","",'02_Base_Solicitudes'!H23) -> Agendas- 3er lote de 500 agendas para 30 Oct | H25: =IF('02_Base_Solicitudes'!A23="","",'02_Base_Solicitudes'!I23) -> Agendas | I25: =IF('02_Base_Solicitudes'!A23="","",'02_Base_Solicitudes'!J23) -> 500 | J25: =IF('02_Base_Solicitudes'!A23="","",'02_Base_Solicitudes'!M23) -> Programado | K25: =IF('02_Base_Solicitudes'!A23="","",'02_Base_Solicitudes'!K23) -> 46325 | L25: =IF($A25="","","Julio Rivera") -> Julio Rivera | M25: Diseño / Comunicaciones | N25: Sí | O25: 46272 | P25: Se cuenta con 7.5 resmas de Bond75g y propalcore. Pero requiere compra de carton para portadas. | Q25: No | R25: 16x22 | S25: Full color | T25: Bond 75 g | U25: Anillado | V25: Shinohara 52 Bicolor | W25: Sí | X25: Sí | Y25: 46310 | AC25: =IF($A25="","","Pendiente") -> Pendiente | AD25: Se enviaron los diseños de las planchas al proveedor el dia 5 de Oct. Deben llegar esta semana para inicio de impresión mas tardar el 15 de Oct. 300 pliegos se disponen para cortar para 1500 portadas de agendas. 500 extra pues el lote 1 y 2 se produjeron justo las 1000 y quedamos cortos con el exceso. Inclusive quedaron 200 bloques de hojas internas sin armar | AF25: =OTMaestraTable[[#This Row],[Solicitante]] -> Lidia Cala | AH25: Diseño | AI25: =IF(AND(C25<>"",AG25<>""),AG25-C25,"") | AJ25: =IF(A25="","",IF(AND(AG25<>"",K25<>""),IF(AG25<=K25,"Sí","No"),"Pendiente")) -> Pendiente | AK25: =IF(A25="","",IF(AND($AH25="Cerrada",OR($AE25="",$AF25="",$AG25="")),"⚠ Cerrada incompleta",IF(AND($AH25<>"Cerrada",$AG25<>""),"⚠ Fecha cierre con estado abierto","OK"))) -> OK
A26: =IF('02_Base_Solicitudes'!A24="","",'02_Base_Solicitudes'!R24) -> OT-UM-202609-023 | B26: =IF('02_Base_Solicitudes'!A24="","",'02_Base_Solicitudes'!A24) -> 23 | C26: =IF('02_Base_Solicitudes'!A24="","",'02_Base_Solicitudes'!C24) -> 46272 | D26: =IF('02_Base_Solicitudes'!A24="","",'02_Base_Solicitudes'!D24) -> Rectoria | E26: =IF('02_Base_Solicitudes'!A24="","",'02_Base_Solicitudes'!E24) -> Lidia Cala | F26: =IF('02_Base_Solicitudes'!A24="","",'02_Base_Solicitudes'!G24) -> rectoriaunimetro@unimetro.edu.co | G26: =IF('02_Base_Solicitudes'!A24="","",'02_Base_Solicitudes'!H24) -> Agendas- 4to lote de 500 agendas para 30 Nov | H26: =IF('02_Base_Solicitudes'!A24="","",'02_Base_Solicitudes'!I24) -> Agendas | I26: =IF('02_Base_Solicitudes'!A24="","",'02_Base_Solicitudes'!J24) -> 500 | J26: =IF('02_Base_Solicitudes'!A24="","",'02_Base_Solicitudes'!M24) -> Programado | K26: =IF('02_Base_Solicitudes'!A24="","",'02_Base_Solicitudes'!K24) -> 46356 | L26: =IF($A26="","","Julio Rivera") -> Julio Rivera | M26: Diseño / Comunicaciones | N26: Sí | O26: 46272 | P26: Requiere compra de Material completo. Se hace el pedido para que lo compra llegue a inicios de Oct | Q26: No | R26: 16x22 | S26: Full color | T26: Bond 75 g | U26: Anillado | V26: Shinohara 52 Bicolor | W26: =IF($A26="","","Pendiente") -> Pendiente | X26: Sí | Y26: 46331 | AC26: =IF($A26="","","Pendiente") -> Pendiente | AF26: =OTMaestraTable[[#This Row],[Solicitante]] -> Lidia Cala | AH26: Diseño | AI26: =IF(AND(C26<>"",AG26<>""),AG26-C26,"") | AJ26: =IF(A26="","",IF(AND(AG26<>"",K26<>""),IF(AG26<=K26,"Sí","No"),"Pendiente")) -> Pendiente | AK26: =IF(A26="","",IF(AND($AH26="Cerrada",OR($AE26="",$AF26="",$AG26="")),"⚠ Cerrada incompleta",IF(AND($AH26<>"Cerrada",$AG26<>""),"⚠ Fecha cierre con estado abierto","OK"))) -> OK
A27: =IF('02_Base_Solicitudes'!A25="","",'02_Base_Solicitudes'!R25) -> OT-UM-202609-024 | B27: =IF('02_Base_Solicitudes'!A25="","",'02_Base_Solicitudes'!A25) -> 24 | C27: =IF('02_Base_Solicitudes'!A25="","",'02_Base_Solicitudes'!C25) -> 46279 | D27: =IF('02_Base_Solicitudes'!A25="","",'02_Base_Solicitudes'!D25) -> Vicerrectoria | E27: =IF('02_Base_Solicitudes'!A25="","",'02_Base_Solicitudes'!E25) -> Jose Luis Castro Guerra | F27: =IF('02_Base_Solicitudes'!A25="","",'02_Base_Solicitudes'!G25) -> vice-rectoria@unimetro.edu.co | G27: =IF('02_Base_Solicitudes'!A25="","",'02_Base_Solicitudes'!H25) -> Tarjetas de presentación | H27: =IF('02_Base_Solicitudes'!A25="","",'02_Base_Solicitudes'!I25) -> Tarjetas de presentación | I27: =IF('02_Base_Solicitudes'!A25="","",'02_Base_Solicitudes'!J25) -> 500 | J27: =IF('02_Base_Solicitudes'!A25="","",'02_Base_Solicitudes'!M25) -> Programado | K27: =IF('02_Base_Solicitudes'!A25="","",'02_Base_Solicitudes'!K25) -> 46295 | L27: =IF($A27="","","Julio Rivera") -> Julio Rivera | M27: Diseño / Comunicaciones | N27: Sí | O27: 46279 | P27: Las tarjetas de presentación se fabricarán en propalcote 300 y plastificadas en mate. La imprenta no cuenta con equipos para crear texturas, repujado o relieve en las tarjetas. | Q27: Sí | R27: 33x23 | S27: Dos tintas | T27: Propalcote300 | U27: Corte | V27: Shinohara 52 Bicolor | W27: Sí | X27: No | Y27: 46287 | Z27: 46289 | AA27: 500 | AB27: 0 | AC27: Sí | AD27: Las tarjetas de presentación se imprimen a 2 x tintas y plastificadas en mate. Las tarjetas deben diseñarse sin trma pues los pixeles o puntos de impresión no permiten la nitidez y profundidad del color. Igualmente se debe incrementar el tamaño en el diseño para que en le proceso de refilada quede una tarjeta estandar de 9cm x 5cm | AE27: 46289 | AF27: =OTMaestraTable[[#This Row],[Solicitante]] -> Jose Luis Castro Guerra | AG27: 46289 | AH27: Cerrada | AI27: =IF(AND(C27<>"",AG27<>""),AG27-C27,"") -> 10 | AJ27: =IF(A27="","",IF(AND(AG27<>"",K27<>""),IF(AG27<=K27,"Sí","No"),"Pendiente")) -> Sí | AK27: =IF(A27="","",IF(AND($AH27="Cerrada",OR($AE27="",$AF27="",$AG27="")),"⚠ Cerrada incompleta",IF(AND($AH27<>"Cerrada",$AG27<>""),"⚠ Fecha cierre con estado abierto","OK"))) -> OK | AL27: Se entregan las500 tarjetas con un exceso. Se acepta el comentario de la secretaria de Vicerrectoria donde el diseño debe ser el estandar de una tarjeta de presentación.
A28: =IF('02_Base_Solicitudes'!A26="","",'02_Base_Solicitudes'!R26) -> OT-UM-202609-025 | B28: =IF('02_Base_Solicitudes'!A26="","",'02_Base_Solicitudes'!A26) -> 25 | C28: =IF('02_Base_Solicitudes'!A26="","",'02_Base_Solicitudes'!C26) -> 46283 | D28: =IF('02_Base_Solicitudes'!A26="","",'02_Base_Solicitudes'!D26) -> Vicerrectoria - Direccion de bienestar universitario | E28: =IF('02_Base_Solicitudes'!A26="","",'02_Base_Solicitudes'!E26) -> Katty Aguas Gamarra | F28: =IF('02_Base_Solicitudes'!A26="","",'02_Base_Solicitudes'!G26) -> desarrollohumano@unimetro.edu.co | G28: =IF('02_Base_Solicitudes'!A26="","",'02_Base_Solicitudes'!H26) -> Separadores de libros sobre salud mental | H28: =IF('02_Base_Solicitudes'!A26="","",'02_Base_Solicitudes'!I26) -> Separadores de libros | I28: =IF('02_Base_Solicitudes'!A26="","",'02_Base_Solicitudes'!J26) -> 1000 | J28: Programado | K28: =IF('02_Base_Solicitudes'!A26="","",'02_Base_Solicitudes'!K26) -> 46309 | L28: =IF($A28="","","Julio Rivera") -> Julio Rivera | M28: Diseño / Comunicaciones | N28: No | O28: 46293 | P28: Se empleará el diseño anterior | Q28: Sí | R28: 33x23 | S28: Full color | T28: Propalcote300 | U28: Corte | V28: Shinohara 52 Bicolor | W28: Sí | X28: No | Y28: 46302 | AA28: 1000 | AC28: Sí | AF28: =OTMaestraTable[[#This Row],[Solicitante]] -> Katty Aguas Gamarra | AH28: Preprensa | AI28: =IF(AND(C28<>"",AG28<>""),AG28-C28,"") | AJ28: =IF(A28="","",IF(AND(AG28<>"",K28<>""),IF(AG28<=K28,"Sí","No"),"Pendiente")) -> Pendiente | AK28: =IF(A28="","",IF(AND($AH28="Cerrada",OR($AE28="",$AF28="",$AG28="")),"⚠ Cerrada incompleta",IF(AND($AH28<>"Cerrada",$AG28<>""),"⚠ Fecha cierre con estado abierto","OK"))) -> OK
A29: =IF('02_Base_Solicitudes'!A27="","",'02_Base_Solicitudes'!R27) -> OT-UM-202609-026 | B29: =IF('02_Base_Solicitudes'!A27="","",'02_Base_Solicitudes'!A27) -> 26 | C29: =IF('02_Base_Solicitudes'!A27="","",'02_Base_Solicitudes'!C27) -> 46287 | D29: =IF('02_Base_Solicitudes'!A27="","",'02_Base_Solicitudes'!D27) -> Rectoria | E29: =IF('02_Base_Solicitudes'!A27="","",'02_Base_Solicitudes'!E27) -> Lidia Cala | F29: =IF('02_Base_Solicitudes'!A27="","",'02_Base_Solicitudes'!G27) -> rectoriaunimetro@unimetro.edu.co | G29: =IF('02_Base_Solicitudes'!A27="","",'02_Base_Solicitudes'!H27) -> Miniblocks - pieza uso interno unimetro | H29: =IF('02_Base_Solicitudes'!A27="","",'02_Base_Solicitudes'!I27) -> MiniBlocks | I29: =IF('02_Base_Solicitudes'!A27="","",'02_Base_Solicitudes'!J27) -> 1000 | J29: Programado | K29: =IF('02_Base_Solicitudes'!A27="","",'02_Base_Solicitudes'!K27) -> 46356 | L29: =IF($A29="","","Julio Rivera") -> Julio Rivera | M29: Diseño / Comunicaciones | N29: Sí | O29: 46287 | P29: Se realizaran 1000 unidades con el mismo diseño hasta ahora implementado. | Q29: Sí | R29: 42x28 | S29: Dos tintas | T29: Bond 75 g | U29: Plastificado mate | V29: Shinohara 52 Bicolor | W29: Sí | X29: No | AC29: =IF($A29="","","Pendiente") -> Pendiente | AF29: =OTMaestraTable[[#This Row],[Solicitante]] -> Lidia Cala | AH29: Preprensa | AI29: =IF(AND(C29<>"",AG29<>""),AG29-C29,"") | AJ29: =IF(A29="","",IF(AND(AG29<>"",K29<>""),IF(AG29<=K29,"Sí","No"),"Pendiente")) -> Pendiente | AK29: =IF(A29="","",IF(AND($AH29="Cerrada",OR($AE29="",$AF29="",$AG29="")),"⚠ Cerrada incompleta",IF(AND($AH29<>"Cerrada",$AG29<>""),"⚠ Fecha cierre con estado abierto","OK"))) -> OK
A30: =IF('02_Base_Solicitudes'!A28="","",'02_Base_Solicitudes'!R28) -> OT-UM-202609-027 | B30: =IF('02_Base_Solicitudes'!A28="","",'02_Base_Solicitudes'!A28) -> 27 | C30: =IF('02_Base_Solicitudes'!A28="","",'02_Base_Solicitudes'!C28) -> 46293 | D30: =IF('02_Base_Solicitudes'!A28="","",'02_Base_Solicitudes'!D28) -> Direccion de idiomas | E30: =IF('02_Base_Solicitudes'!A28="","",'02_Base_Solicitudes'!E28) -> Sara Elena Plata | F30: =IF('02_Base_Solicitudes'!A28="","",'02_Base_Solicitudes'!G28) -> direccion.idiomas@unimetro.edu.co | G30: =IF('02_Base_Solicitudes'!A28="","",'02_Base_Solicitudes'!H28) -> Volantes - Unidad Académica de Idiomas | H30: =IF('02_Base_Solicitudes'!A28="","",'02_Base_Solicitudes'!I28) -> Volantes | I30: =IF('02_Base_Solicitudes'!A28="","",'02_Base_Solicitudes'!J28) -> 1000 | J30: Urgente | K30: =IF('02_Base_Solicitudes'!A28="","",'02_Base_Solicitudes'!K28) -> 46311 | L30: =IF($A30="","","Julio Rivera") -> Julio Rivera | M30: Diseño / Comunicaciones | N30: Sí | O30: 46293 | P30: Se diiseñan en el mismo formato de los volantes de pregrado. Planchas llegan el 1 de Oct. Sin 4 volantes por 1/4 de pliego.Salen 75 pliegos para 1200 volantes estimados. | Q30: Sí | R30: 24x16 | S30: Full color | T30: Propalcote200 | U30: Corte | V30: Shinohara 52 Bicolor | W30: Sí | X30: No | Y30: 46301 | Z30: 46302 | AA30: 1000 | AB30: 0 | AC30: Sí | AD30: Se hicieron las correciones en color. Ya no es trama, ahora se diseño con parche o fondo entero, y los detalles se realizan con el color negro. Se imprimen alrededor de 1000 unidades. | AE30: 46302 | AF30: =OTMaestraTable[[#This Row],[Solicitante]] -> Sara Elena Plata | AG30: 46302 | AH30: Cerrada | AI30: =IF(AND(C30<>"",AG30<>""),AG30-C30,"") -> 9 | AJ30: =IF(A30="","",IF(AND(AG30<>"",K30<>""),IF(AG30<=K30,"Sí","No"),"Pendiente")) -> Sí | AK30: =IF(A30="","",IF(AND($AH30="Cerrada",OR($AE30="",$AF30="",$AG30="")),"⚠ Cerrada incompleta",IF(AND($AH30<>"Cerrada",$AG30<>""),"⚠ Fecha cierre con estado abierto","OK"))) -> OK | AL30: Se entregan a comunicaciones y marketing.Firma la planilla de entrega a satisfacción. Firma Camilo Robledo. Coordinador
A31: =IF('02_Base_Solicitudes'!A29="","",'02_Base_Solicitudes'!R29) -> OT-UM-202610-028 | B31: =IF('02_Base_Solicitudes'!A29="","",'02_Base_Solicitudes'!A29) -> 28 | C31: =IF('02_Base_Solicitudes'!A29="","",'02_Base_Solicitudes'!C29) -> 46300 | D31: =IF('02_Base_Solicitudes'!A29="","",'02_Base_Solicitudes'!D29) -> Vicerrectoria - Direccion de bienestar universitario | E31: =IF('02_Base_Solicitudes'!A29="","",'02_Base_Solicitudes'!E29) -> Katty Aguas Gamarra | F31: =IF('02_Base_Solicitudes'!A29="","",'02_Base_Solicitudes'!G29) -> desarrollohumano@unimetro.edu.co | G31: =IF('02_Base_Solicitudes'!A29="","",'02_Base_Solicitudes'!H29) -> Mini Agendas | H31: =IF('02_Base_Solicitudes'!A29="","",'02_Base_Solicitudes'!I29) -> Mini Agendas o Libretas | I31: =IF('02_Base_Solicitudes'!A29="","",'02_Base_Solicitudes'!J29) -> 60 | J31: =IF('02_Base_Solicitudes'!A29="","",'02_Base_Solicitudes'!M29) -> Urgente | K31: =IF('02_Base_Solicitudes'!A29="","",'02_Base_Solicitudes'!K29) -> 46314 | L31: =IF($A31="","","Julio Rivera") -> Julio Rivera | M31: Diseño / Comunicaciones | N31: Sí | O31: 46302 | P31: El diseño inicialmente fue pedido simple sin logo. Sin embargo desde la Imprenta se propuso que se hiciera un diseño simple con el mesaje que Bienestar propuciera. Es asi como se envio a fabricar la planca el 7 de Oct.El 8 de Oct ya tenemos la impresión y plastificación. Se debe entregar maximo el dia 14. 5 dias antes del evento | Q31: Sí | R31: 33x23 | S31: Full color | T31: Propalcote300 | U31: Corte | V31: Shinohara 52 Bicolor | W31: Sí | X31: No | Y31: 46303 | Z31: 46308 | AA31: 70 | AB31: 0 | AC31: Sí | AD31: Las planchas llegaron en magenta y cian, Se preparò el color rosado para seguir el estadar pedido por Bienestar. Tamaño de portada y contraportada 20 x 13 | AF31: =OTMaestraTable[[#This Row],[Solicitante]] -> Katty Aguas Gamarra | AH31: Producción | AI31: =IF(AND(C31<>"",AG31<>""),AG31-C31,"") | AJ31: =IF(A31="","",IF(AND(AG31<>"",K31<>""),IF(AG31<=K31,"Sí","No"),"Pendiente")) -> Pendiente | AK31: =IF(A31="","",IF(AND($AH31="Cerrada",OR($AE31="",$AF31="",$AG31="")),"⚠ Cerrada incompleta",IF(AND($AH31<>"Cerrada",$AG31<>""),"⚠ Fecha cierre con estado abierto","OK"))) -> OK
A32: =IF('02_Base_Solicitudes'!A30="","",'02_Base_Solicitudes'!R30) | B32: =IF('02_Base_Solicitudes'!A30="","",'02_Base_Solicitudes'!A30) | C32: =IF('02_Base_Solicitudes'!A30="","",'02_Base_Solicitudes'!C30) | D32: =IF('02_Base_Solicitudes'!A30="","",'02_Base_Solicitudes'!D30) | E32: =IF('02_Base_Solicitudes'!A30="","",'02_Base_Solicitudes'!E30) | F32: =IF('02_Base_Solicitudes'!A30="","",'02_Base_Solicitudes'!G30) | G32: =IF('02_Base_Solicitudes'!A30="","",'02_Base_Solicitudes'!H30) | H32: =IF('02_Base_Solicitudes'!A30="","",'02_Base_Solicitudes'!I30) | I32: =IF('02_Base_Solicitudes'!A30="","",'02_Base_Solicitudes'!J30) | J32: =IF('02_Base_Solicitudes'!A30="","",'02_Base_Solicitudes'!M30) | K32: =IF('02_Base_Solicitudes'!A30="","",'02_Base_Solicitudes'!K30) | L32: =IF($A32="","","Julio Rivera") | N32: =IF($A32="","","No") | W32: =IF($A32="","","Pendiente") | AC32: =IF($A32="","","Pendiente") | AF32: =OTMaestraTable[[#This Row],[Solicitante]] | AH32: =IF($A32="","","Abierta") | AI32: =IF(AND(C32<>"",AG32<>""),AG32-C32,"") | AJ32: =IF(A32="","",IF(AND(AG32<>"",K32<>""),IF(AG32<=K32,"Sí","No"),"Pendiente")) | AK32: =IF(A32="","",IF(AND($AH32="Cerrada",OR($AE32="",$AF32="",$AG32="")),"⚠ Cerrada incompleta",IF(AND($AH32<>"Cerrada",$AG32<>""),"⚠ Fecha cierre con estado abierto","OK")))
A33: =IF('02_Base_Solicitudes'!A31="","",'02_Base_Solicitudes'!R31) | B33: =IF('02_Base_Solicitudes'!A31="","",'02_Base_Solicitudes'!A31) | C33: =IF('02_Base_Solicitudes'!A31="","",'02_Base_Solicitudes'!C31) | D33: =IF('02_Base_Solicitudes'!A31="","",'02_Base_Solicitudes'!D31) | E33: =IF('02_Base_Solicitudes'!A31="","",'02_Base_Solicitudes'!E31) | F33: =IF('02_Base_Solicitudes'!A31="","",'02_Base_Solicitudes'!G31) | G33: =IF('02_Base_Solicitudes'!A31="","",'02_Base_Solicitudes'!H31) | H33: =IF('02_Base_Solicitudes'!A31="","",'02_Base_Solicitudes'!I31) | I33: =IF('02_Base_Solicitudes'!A31="","",'02_Base_Solicitudes'!J31) | J33: =IF('02_Base_Solicitudes'!A31="","",'02_Base_Solicitudes'!M31) | K33: =IF('02_Base_Solicitudes'!A31="","",'02_Base_Solicitudes'!K31) | L33: =IF($A33="","","Julio Rivera") | N33: =IF($A33="","","No") | W33: =IF($A33="","","Pendiente") | AC33: =IF($A33="","","Pendiente") | AF33: =OTMaestraTable[[#This Row],[Solicitante]] | AH33: =IF($A33="","","Abierta") | AI33: =IF(AND(C33<>"",AG33<>""),AG33-C33,"") | AJ33: =IF(A33="","",IF(AND(AG33<>"",K33<>""),IF(AG33<=K33,"Sí","No"),"Pendiente")) | AK33: =IF(A33="","",IF(AND($AH33="Cerrada",OR($AE33="",$AF33="",$AG33="")),"⚠ Cerrada incompleta",IF(AND($AH33<>"Cerrada",$AG33<>""),"⚠ Fecha cierre con estado abierto","OK")))
A34: =IF('02_Base_Solicitudes'!A32="","",'02_Base_Solicitudes'!R32) | B34: =IF('02_Base_Solicitudes'!A32="","",'02_Base_Solicitudes'!A32) | C34: =IF('02_Base_Solicitudes'!A32="","",'02_Base_Solicitudes'!C32) | D34: =IF('02_Base_Solicitudes'!A32="","",'02_Base_Solicitudes'!D32) | E34: =IF('02_Base_Solicitudes'!A32="","",'02_Base_Solicitudes'!E32) | F34: =IF('02_Base_Solicitudes'!A32="","",'02_Base_Solicitudes'!G32) | G34: =IF('02_Base_Solicitudes'!A32="","",'02_Base_Solicitudes'!H32) | H34: =IF('02_Base_Solicitudes'!A32="","",'02_Base_Solicitudes'!I32) | I34: =IF('02_Base_Solicitudes'!A32="","",'02_Base_Solicitudes'!J32) | J34: =IF('02_Base_Solicitudes'!A32="","",'02_Base_Solicitudes'!M32) | K34: =IF('02_Base_Solicitudes'!A32="","",'02_Base_Solicitudes'!K32) | L34: =IF($A34="","","Julio Rivera") | N34: =IF($A34="","","No") | W34: =IF($A34="","","Pendiente") | AC34: =IF($A34="","","Pendiente") | AF34: =OTMaestraTable[[#This Row],[Solicitante]] | AH34: =IF($A34="","","Abierta") | AI34: =IF(AND(C34<>"",AG34<>""),AG34-C34,"") | AJ34: =IF(A34="","",IF(AND(AG34<>"",K34<>""),IF(AG34<=K34,"Sí","No"),"Pendiente")) | AK34: =IF(A34="","",IF(AND($AH34="Cerrada",OR($AE34="",$AF34="",$AG34="")),"⚠ Cerrada incompleta",IF(AND($AH34<>"Cerrada",$AG34<>""),"⚠ Fecha cierre con estado abierto","OK")))
A35: =IF('02_Base_Solicitudes'!A33="","",'02_Base_Solicitudes'!R33) | B35: =IF('02_Base_Solicitudes'!A33="","",'02_Base_Solicitudes'!A33) | C35: =IF('02_Base_Solicitudes'!A33="","",'02_Base_Solicitudes'!C33) | D35: =IF('02_Base_Solicitudes'!A33="","",'02_Base_Solicitudes'!D33) | E35: =IF('02_Base_Solicitudes'!A33="","",'02_Base_Solicitudes'!E33) | F35: =IF('02_Base_Solicitudes'!A33="","",'02_Base_Solicitudes'!G33) | G35: =IF('02_Base_Solicitudes'!A33="","",'02_Base_Solicitudes'!H33) | H35: =IF('02_Base_Solicitudes'!A33="","",'02_Base_Solicitudes'!I33) | I35: =IF('02_Base_Solicitudes'!A33="","",'02_Base_Solicitudes'!J33) | J35: =IF('02_Base_Solicitudes'!A33="","",'02_Base_Solicitudes'!M33) | K35: =IF('02_Base_Solicitudes'!A33="","",'02_Base_Solicitudes'!K33) | L35: =IF($A35="","","Julio Rivera") | N35: =IF($A35="","","No") | W35: =IF($A35="","","Pendiente") | AC35: =IF($A35="","","Pendiente") | AF35: =OTMaestraTable[[#This Row],[Solicitante]] | AH35: =IF($A35="","","Abierta") | AI35: =IF(AND(C35<>"",AG35<>""),AG35-C35,"") | AJ35: =IF(A35="","",IF(AND(AG35<>"",K35<>""),IF(AG35<=K35,"Sí","No"),"Pendiente")) | AK35: =IF(A35="","",IF(AND($AH35="Cerrada",OR($AE35="",$AF35="",$AG35="")),"⚠ Cerrada incompleta",IF(AND($AH35<>"Cerrada",$AG35<>""),"⚠ Fecha cierre con estado abierto","OK")))
A36: =IF('02_Base_Solicitudes'!A34="","",'02_Base_Solicitudes'!R34) | B36: =IF('02_Base_Solicitudes'!A34="","",'02_Base_Solicitudes'!A34) | C36: =IF('02_Base_Solicitudes'!A34="","",'02_Base_Solicitudes'!C34) | D36: =IF('02_Base_Solicitudes'!A34="","",'02_Base_Solicitudes'!D34) | E36: =IF('02_Base_Solicitudes'!A34="","",'02_Base_Solicitudes'!E34) | F36: =IF('02_Base_Solicitudes'!A34="","",'02_Base_Solicitudes'!G34) | G36: =IF('02_Base_Solicitudes'!A34="","",'02_Base_Solicitudes'!H34) | H36: =IF('02_Base_Solicitudes'!A34="","",'02_Base_Solicitudes'!I34) | I36: =IF('02_Base_Solicitudes'!A34="","",'02_Base_Solicitudes'!J34) | J36: =IF('02_Base_Solicitudes'!A34="","",'02_Base_Solicitudes'!M34) | K36: =IF('02_Base_Solicitudes'!A34="","",'02_Base_Solicitudes'!K34) | L36: =IF($A36="","","Julio Rivera") | N36: =IF($A36="","","No") | W36: =IF($A36="","","Pendiente") | AC36: =IF($A36="","","Pendiente") | AF36: =OTMaestraTable[[#This Row],[Solicitante]] | AH36: =IF($A36="","","Abierta") | AI36: =IF(AND(C36<>"",AG36<>""),AG36-C36,"") | AJ36: =IF(A36="","",IF(AND(AG36<>"",K36<>""),IF(AG36<=K36,"Sí","No"),"Pendiente")) | AK36: =IF(A36="","",IF(AND($AH36="Cerrada",OR($AE36="",$AF36="",$AG36="")),"⚠ Cerrada incompleta",IF(AND($AH36<>"Cerrada",$AG36<>""),"⚠ Fecha cierre con estado abierto","OK")))
A37: =IF('02_Base_Solicitudes'!A35="","",'02_Base_Solicitudes'!R35) | B37: =IF('02_Base_Solicitudes'!A35="","",'02_Base_Solicitudes'!A35) | C37: =IF('02_Base_Solicitudes'!A35="","",'02_Base_Solicitudes'!C35) | D37: =IF('02_Base_Solicitudes'!A35="","",'02_Base_Solicitudes'!D35) | E37: =IF('02_Base_Solicitudes'!A35="","",'02_Base_Solicitudes'!E35) | F37: =IF('02_Base_Solicitudes'!A35="","",'02_Base_Solicitudes'!G35) | G37: =IF('02_Base_Solicitudes'!A35="","",'02_Base_Solicitudes'!H35) | H37: =IF('02_Base_Solicitudes'!A35="","",'02_Base_Solicitudes'!I35) | I37: =IF('02_Base_Solicitudes'!A35="","",'02_Base_Solicitudes'!J35) | J37: =IF('02_Base_Solicitudes'!A35="","",'02_Base_Solicitudes'!M35) | K37: =IF('02_Base_Solicitudes'!A35="","",'02_Base_Solicitudes'!K35) | L37: =IF($A37="","","Julio Rivera") | N37: =IF($A37="","","No") | W37: =IF($A37="","","Pendiente") | AC37: =IF($A37="","","Pendiente") | AF37: =OTMaestraTable[[#This Row],[Solicitante]] | AH37: =IF($A37="","","Abierta") | AI37: =IF(AND(C37<>"",AG37<>""),AG37-C37,"") | AJ37: =IF(A37="","",IF(AND(AG37<>"",K37<>""),IF(AG37<=K37,"Sí","No"),"Pendiente")) | AK37: =IF(A37="","",IF(AND($AH37="Cerrada",OR($AE37="",$AF37="",$AG37="")),"⚠ Cerrada incompleta",IF(AND($AH37<>"Cerrada",$AG37<>""),"⚠ Fecha cierre con estado abierto","OK")))
A38: =IF('02_Base_Solicitudes'!A36="","",'02_Base_Solicitudes'!R36) | B38: =IF('02_Base_Solicitudes'!A36="","",'02_Base_Solicitudes'!A36) | C38: =IF('02_Base_Solicitudes'!A36="","",'02_Base_Solicitudes'!C36) | D38: =IF('02_Base_Solicitudes'!A36="","",'02_Base_Solicitudes'!D36) | E38: =IF('02_Base_Solicitudes'!A36="","",'02_Base_Solicitudes'!E36) | F38: =IF('02_Base_Solicitudes'!A36="","",'02_Base_Solicitudes'!G36) | G38: =IF('02_Base_Solicitudes'!A36="","",'02_Base_Solicitudes'!H36) | H38: =IF('02_Base_Solicitudes'!A36="","",'02_Base_Solicitudes'!I36) | I38: =IF('02_Base_Solicitudes'!A36="","",'02_Base_Solicitudes'!J36) | J38: =IF('02_Base_Solicitudes'!A36="","",'02_Base_Solicitudes'!M36) | K38: =IF('02_Base_Solicitudes'!A36="","",'02_Base_Solicitudes'!K36) | L38: =IF($A38="","","Julio Rivera") | N38: =IF($A38="","","No") | W38: =IF($A38="","","Pendiente") | AC38: =IF($A38="","","Pendiente") | AF38: =OTMaestraTable[[#This Row],[Solicitante]] | AH38: =IF($A38="","","Abierta") | AI38: =IF(AND(C38<>"",AG38<>""),AG38-C38,"") | AJ38: =IF(A38="","",IF(AND(AG38<>"",K38<>""),IF(AG38<=K38,"Sí","No"),"Pendiente")) | AK38: =IF(A38="","",IF(AND($AH38="Cerrada",OR($AE38="",$AF38="",$AG38="")),"⚠ Cerrada incompleta",IF(AND($AH38<>"Cerrada",$AG38<>""),"⚠ Fecha cierre con estado abierto","OK")))
A39: =IF('02_Base_Solicitudes'!A37="","",'02_Base_Solicitudes'!R37) | B39: =IF('02_Base_Solicitudes'!A37="","",'02_Base_Solicitudes'!A37) | C39: =IF('02_Base_Solicitudes'!A37="","",'02_Base_Solicitudes'!C37) | D39: =IF('02_Base_Solicitudes'!A37="","",'02_Base_Solicitudes'!D37) | E39: =IF('02_Base_Solicitudes'!A37="","",'02_Base_Solicitudes'!E37) | F39: =IF('02_Base_Solicitudes'!A37="","",'02_Base_Solicitudes'!G37) | G39: =IF('02_Base_Solicitudes'!A37="","",'02_Base_Solicitudes'!H37) | H39: =IF('02_Base_Solicitudes'!A37="","",'02_Base_Solicitudes'!I37) | I39: =IF('02_Base_Solicitudes'!A37="","",'02_Base_Solicitudes'!J37) | J39: =IF('02_Base_Solicitudes'!A37="","",'02_Base_Solicitudes'!M37) | K39: =IF('02_Base_Solicitudes'!A37="","",'02_Base_Solicitudes'!K37) | L39: =IF($A39="","","Julio Rivera") | N39: =IF($A39="","","No") | W39: =IF($A39="","","Pendiente") | AC39: =IF($A39="","","Pendiente") | AF39: =OTMaestraTable[[#This Row],[Solicitante]] | AH39: =IF($A39="","","Abierta") | AI39: =IF(AND(C39<>"",AG39<>""),AG39-C39,"") | AJ39: =IF(A39="","",IF(AND(AG39<>"",K39<>""),IF(AG39<=K39,"Sí","No"),"Pendiente")) | AK39: =IF(A39="","",IF(AND($AH39="Cerrada",OR($AE39="",$AF39="",$AG39="")),"⚠ Cerrada incompleta",IF(AND($AH39<>"Cerrada",$AG39<>""),"⚠ Fecha cierre con estado abierto","OK")))
A40: =IF('02_Base_Solicitudes'!A38="","",'02_Base_Solicitudes'!R38) | B40: =IF('02_Base_Solicitudes'!A38="","",'02_Base_Solicitudes'!A38) | C40: =IF('02_Base_Solicitudes'!A38="","",'02_Base_Solicitudes'!C38) | D40: =IF('02_Base_Solicitudes'!A38="","",'02_Base_Solicitudes'!D38) | E40: =IF('02_Base_Solicitudes'!A38="","",'02_Base_Solicitudes'!E38) | F40: =IF('02_Base_Solicitudes'!A38="","",'02_Base_Solicitudes'!G38) | G40: =IF('02_Base_Solicitudes'!A38="","",'02_Base_Solicitudes'!H38) | H40: =IF('02_Base_Solicitudes'!A38="","",'02_Base_Solicitudes'!I38) | I40: =IF('02_Base_Solicitudes'!A38="","",'02_Base_Solicitudes'!J38) | J40: =IF('02_Base_Solicitudes'!A38="","",'02_Base_Solicitudes'!M38) | K40: =IF('02_Base_Solicitudes'!A38="","",'02_Base_Solicitudes'!K38) | L40: =IF($A40="","","Julio Rivera") | N40: =IF($A40="","","No") | W40: =IF($A40="","","Pendiente") | AC40: =IF($A40="","","Pendiente") | AF40: =OTMaestraTable[[#This Row],[Solicitante]] | AH40: =IF($A40="","","Abierta") | AI40: =IF(AND(C40<>"",AG40<>""),AG40-C40,"") | AJ40: =IF(A40="","",IF(AND(AG40<>"",K40<>""),IF(AG40<=K40,"Sí","No"),"Pendiente")) | AK40: =IF(A40="","",IF(AND($AH40="Cerrada",OR($AE40="",$AF40="",$AG40="")),"⚠ Cerrada incompleta",IF(AND($AH40<>"Cerrada",$AG40<>""),"⚠ Fecha cierre con estado abierto","OK")))
A41: =IF('02_Base_Solicitudes'!A39="","",'02_Base_Solicitudes'!R39) | B41: =IF('02_Base_Solicitudes'!A39="","",'02_Base_Solicitudes'!A39) | C41: =IF('02_Base_Solicitudes'!A39="","",'02_Base_Solicitudes'!C39) | D41: =IF('02_Base_Solicitudes'!A39="","",'02_Base_Solicitudes'!D39) | E41: =IF('02_Base_Solicitudes'!A39="","",'02_Base_Solicitudes'!E39) | F41: =IF('02_Base_Solicitudes'!A39="","",'02_Base_Solicitudes'!G39) | G41: =IF('02_Base_Solicitudes'!A39="","",'02_Base_Solicitudes'!H39) | H41: =IF('02_Base_Solicitudes'!A39="","",'02_Base_Solicitudes'!I39) | I41: =IF('02_Base_Solicitudes'!A39="","",'02_Base_Solicitudes'!J39) | J41: =IF('02_Base_Solicitudes'!A39="","",'02_Base_Solicitudes'!M39) | K41: =IF('02_Base_Solicitudes'!A39="","",'02_Base_Solicitudes'!K39) | L41: =IF($A41="","","Julio Rivera") | N41: =IF($A41="","","No") | W41: =IF($A41="","","Pendiente") | AC41: =IF($A41="","","Pendiente") | AF41: =OTMaestraTable[[#This Row],[Solicitante]] | AH41: =IF($A41="","","Abierta") | AI41: =IF(AND(C41<>"",AG41<>""),AG41-C41,"") | AJ41: =IF(A41="","",IF(AND(AG41<>"",K41<>""),IF(AG41<=K41,"Sí","No"),"Pendiente")) | AK41: =IF(A41="","",IF(AND($AH41="Cerrada",OR($AE41="",$AF41="",$AG41="")),"⚠ Cerrada incompleta",IF(AND($AH41<>"Cerrada",$AG41<>""),"⚠ Fecha cierre con estado abierto","OK")))
A42: =IF('02_Base_Solicitudes'!A40="","",'02_Base_Solicitudes'!R40) | B42: =IF('02_Base_Solicitudes'!A40="","",'02_Base_Solicitudes'!A40) | C42: =IF('02_Base_Solicitudes'!A40="","",'02_Base_Solicitudes'!C40) | D42: =IF('02_Base_Solicitudes'!A40="","",'02_Base_Solicitudes'!D40) | E42: =IF('02_Base_Solicitudes'!A40="","",'02_Base_Solicitudes'!E40) | F42: =IF('02_Base_Solicitudes'!A40="","",'02_Base_Solicitudes'!G40) | G42: =IF('02_Base_Solicitudes'!A40="","",'02_Base_Solicitudes'!H40) | H42: =IF('02_Base_Solicitudes'!A40="","",'02_Base_Solicitudes'!I40) | I42: =IF('02_Base_Solicitudes'!A40="","",'02_Base_Solicitudes'!J40) | J42: =IF('02_Base_Solicitudes'!A40="","",'02_Base_Solicitudes'!M40) | K42: =IF('02_Base_Solicitudes'!A40="","",'02_Base_Solicitudes'!K40) | L42: =IF($A42="","","Julio Rivera") | N42: =IF($A42="","","No") | W42: =IF($A42="","","Pendiente") | AC42: =IF($A42="","","Pendiente") | AF42: =OTMaestraTable[[#This Row],[Solicitante]] | AH42: =IF($A42="","","Abierta") | AI42: =IF(AND(C42<>"",AG42<>""),AG42-C42,"") | AJ42: =IF(A42="","",IF(AND(AG42<>"",K42<>""),IF(AG42<=K42,"Sí","No"),"Pendiente")) | AK42: =IF(A42="","",IF(AND($AH42="Cerrada",OR($AE42="",$AF42="",$AG42="")),"⚠ Cerrada incompleta",IF(AND($AH42<>"Cerrada",$AG42<>""),"⚠ Fecha cierre con estado abierto","OK")))
A43: =IF('02_Base_Solicitudes'!A41="","",'02_Base_Solicitudes'!R41) | B43: =IF('02_Base_Solicitudes'!A41="","",'02_Base_Solicitudes'!A41) | C43: =IF('02_Base_Solicitudes'!A41="","",'02_Base_Solicitudes'!C41) | D43: =IF('02_Base_Solicitudes'!A41="","",'02_Base_Solicitudes'!D41) | E43: =IF('02_Base_Solicitudes'!A41="","",'02_Base_Solicitudes'!E41) | F43: =IF('02_Base_Solicitudes'!A41="","",'02_Base_Solicitudes'!G41) | G43: =IF('02_Base_Solicitudes'!A41="","",'02_Base_Solicitudes'!H41) | H43: =IF('02_Base_Solicitudes'!A41="","",'02_Base_Solicitudes'!I41) | I43: =IF('02_Base_Solicitudes'!A41="","",'02_Base_Solicitudes'!J41) | J43: =IF('02_Base_Solicitudes'!A41="","",'02_Base_Solicitudes'!M41) | K43: =IF('02_Base_Solicitudes'!A41="","",'02_Base_Solicitudes'!K41) | L43: =IF($A43="","","Julio Rivera") | N43: =IF($A43="","","No") | W43: =IF($A43="","","Pendiente") | AC43: =IF($A43="","","Pendiente") | AF43: =OTMaestraTable[[#This Row],[Solicitante]] | AH43: =IF($A43="","","Abierta") | AI43: =IF(AND(C43<>"",AG43<>""),AG43-C43,"") | AJ43: =IF(A43="","",IF(AND(AG43<>"",K43<>""),IF(AG43<=K43,"Sí","No"),"Pendiente")) | AK43: =IF(A43="","",IF(AND($AH43="Cerrada",OR($AE43="",$AF43="",$AG43="")),"⚠ Cerrada incompleta",IF(AND($AH43<>"Cerrada",$AG43<>""),"⚠ Fecha cierre con estado abierto","OK")))
... A203: =IF('02_Base_Solicitudes'!A201="","",'02_Base_Solicitudes'!R201) | B203: =IF('02_Base_Solicitudes'!A201="","",'02_Base_Solicitudes'!A201) | C203: =IF('02_Base_Solicitudes'!A201="","",'02_Base_Solicitudes'!C201) | D203: =IF('02_Base_Solicitudes'!A201="","",'02_Base_Solicitudes'!D201) | E203: =IF('02_Base_Solicitudes'!A201="","",'02_Base_Solicitudes'!E201) | F203: =IF('02_Base_Solicitudes'!A201="","",'02_Base_Solicitudes'!G201) | G203: =IF('02_Base_Solicitudes'!A201="","",'02_Base_Solicitudes'!H201) | H203: =IF('02_Base_Solicitudes'!A201="","",'02_Base_Solicitudes'!I201) | I203: =IF('02_Base_Solicitudes'!A201="","",'02_Base_Solicitudes'!J201) | J203: =IF('02_Base_Solicitudes'!A201="","",'02_Base_Solicitudes'!M201) | K203: =IF('02_Base_Solicitudes'!A201="","",'02_Base_Solicitudes'!K201) | L203: =IF($A203="","","Julio Rivera") | N203: =IF($A203="","","No") | W203: =IF($A203="","","Pendiente") | AC203: =IF($A203="","","Pendiente") | AF203: =OTMaestraTable[[#This Row],[Solicitante]] | AH203: =IF($A203="","","Abierta") | AI203: =IF(AND(C203<>"",AG203<>""),AG203-C203,"") | AJ203: =IF(A203="","",IF(AND(AG203<>"",K203<>""),IF(AG203<=K203,"Sí","No"),"Pendiente")) | AK203: =IF(A203="","",IF(AND($AH203="Cerrada",OR($AE203="",$AF203="",$AG203="")),"⚠ Cerrada incompleta",IF(AND($AH203<>"Cerrada",$AG203<>""),"⚠ Fecha cierre con estado abierto","OK")))

Sheet 04_OT_Print001
A1: ORDEN DE TRABAJO - IMPRENTA UM
A2: Seleccione OT | B2: OT-UM-202605-001
A4: A. INFORMACIÓN GENERAL
A5: Número OT | B5: =B2 -> OT-UM-202605-001 | C5: Dependencia | D5: =_xlfn.XLOOKUP($B$2,OTMaestraTable[Número OT],OTMaestraTable[Dependencia],"")
A6: Fecha solicitud | B6: =_xlfn.XLOOKUP($B$2,OTMaestraTable[Número OT],OTMaestraTable[Fecha solicitud],"") | C6: Solicitante | D6: =_xlfn.XLOOKUP($B$2,OTMaestraTable[Número OT],OTMaestraTable[Solicitante],"")
A7: Nombre trabajo | B7: =_xlfn.XLOOKUP($B$2,OTMaestraTable[Número OT],OTMaestraTable[Nombre trabajo],"") | C7: Tipo trabajo | D7: =_xlfn.XLOOKUP($B$2,OTMaestraTable[Número OT],OTMaestraTable[Tipo trabajo],"")
A8: Cantidad | B8: =_xlfn.XLOOKUP($B$2,OTMaestraTable[Número OT],OTMaestraTable[Cantidad],"") | C8: Fecha requerida | D8: =_xlfn.XLOOKUP($B$2,OTMaestraTable[Número OT],OTMaestraTable[Fecha requerida],"")
A9: Prioridad | B9: =_xlfn.XLOOKUP($B$2,OTMaestraTable[Número OT],OTMaestraTable[Prioridad],"") | C9: Estado | D9: =_xlfn.XLOOKUP($B$2,OTMaestraTable[Número OT],OTMaestraTable[Estado OT],"")
A12: B. DISEÑO Y APROBACIONES
A13: Diseñador | B13: =_xlfn.XLOOKUP($B$2,OTMaestraTable[Número OT],OTMaestraTable[Diseñador],"") | C13: Cliente aprobó | D13: =_xlfn.XLOOKUP($B$2,OTMaestraTable[Número OT],OTMaestraTable[Cliente aprobó],"")
A14: Fecha aprobación | B14: =_xlfn.XLOOKUP($B$2,OTMaestraTable[Número OT],OTMaestraTable[Fecha aprobación diseño],"") | C14: Planchas Listas | D14: =_xlfn.XLOOKUP($B$2,OTMaestraTable[Número OT],OTMaestraTable[Planchas Listas],"")
A15: Observaciones | B15: =_xlfn.XLOOKUP($B$2,OTMaestraTable[Número OT],OTMaestraTable[Observaciones diseño],"")
A18: C. PREPRENSA
A19: Formato/Tamaño | B19: =_xlfn.XLOOKUP($B$2,OTMaestraTable[Número OT],OTMaestraTable[Preprensa: formato/tamaño (cm)],"") | C19: Color/Tintas | D19: =_xlfn.XLOOKUP($B$2,OTMaestraTable[Número OT],OTMaestraTable[Preprensa: color/tintas],"")
A20: Material | B20: =_xlfn.XLOOKUP($B$2,OTMaestraTable[Número OT],OTMaestraTable[Preprensa: material],"") | C20: Acabado | D20: =_xlfn.XLOOKUP($B$2,OTMaestraTable[Número OT],OTMaestraTable[Preprensa: acabado],"")
A21: Máquina sugerida | B21: =_xlfn.XLOOKUP($B$2,OTMaestraTable[Número OT],OTMaestraTable[Preprensa: máquina sugerida],"") | C21: Hay stock | D21: =_xlfn.XLOOKUP($B$2,OTMaestraTable[Número OT],OTMaestraTable[¿Hay stock?],"")
A24: D. PRODUCCIÓN / CALIDAD / CIERRE
A25: Fecha inicio prod. | B25: =_xlfn.XLOOKUP($B$2,OTMaestraTable[Número OT],OTMaestraTable[Fecha inicio producción],"") | C25: Fecha fin prod. | D25: =_xlfn.XLOOKUP($B$2,OTMaestraTable[Número OT],OTMaestraTable[Fecha fin producción],"")
A26: Cantidad producida | B26: =_xlfn.XLOOKUP($B$2,OTMaestraTable[Número OT],OTMaestraTable[Cantidad producida],"") | C26: Merma | D26: =_xlfn.XLOOKUP($B$2,OTMaestraTable[Número OT],OTMaestraTable[Entrega Parcial],"")
A27: Calidad OK | B27: =_xlfn.XLOOKUP($B$2,OTMaestraTable[Número OT],OTMaestraTable[Control calidad],"") | C27: Fecha entrega | D27: =_xlfn.XLOOKUP($B$2,OTMaestraTable[Número OT],OTMaestraTable[Fecha entrega],"")
A28: Recibido por | B28: =_xlfn.XLOOKUP($B$2,OTMaestraTable[Número OT],OTMaestraTable[Recibido por],"") | C28: SLA cumplido | D28: =_xlfn.XLOOKUP($B$2,OTMaestraTable[Número OT],OTMaestraTable[SLA cumplido],"")

Sheet 05_Catalogos
A1: Dependencias | B1: Tipo Trabajo | C1: Prioridad | D1: Estado OT | E1: Responsable OT | F1: Diseñador | G1: Máquina | H1: Material | I1: Acabado | J1: Color | K1: Sí/No | L1: Estado Solicitud | M1: Control calidad OK | N1: Proveedor Planchas | P1: Parámetro | Q1: Valor
A2: Rectoría | B2: Volante | C2: Urgente | D2: Abierta | E2: Julio Rivera | F2: Diseño / Comunicaciones | G2: Shinohara 52 Bicolor | H2: Bond 75 g | I2: Sin acabado | J2: Blanco y negro | K2: Sí | L2: Recibida | M2: Sí | N2: Sí | P2: Prefijo OT | Q2: OT-UM-
A3: Vicerrectoría | B3: Afiche | C3: Normal | D3: Diseño | E3: Operador imprenta | F3: Diseñador por asignar | G3: Ryobi 500N-NP-1 | H3: Propalcote200 | I3: Corte | J3: Una tinta | K3: No | L3: Validada | M3: No | N3: No | P3: Año | Q3: 2026
A4: Dirección Administrativa | B4: Plegable | C4: Programado | D4: Preprensa | E4: Julio Rivera | F4: Comunicaciones | G4: Ryobi 500N-NP-2 | H4: Propalcote300 | I4: Doblado | J4: Dos tintas | L4: Aprobada para OT | M4: Pendiente | P4: Link Formulario | Q4: https://forms.cloud.microsoft/r/aWUfLKWJiA
A5: Facultad Medicina | B5: Formato institucional | D5: Producción | G5: Troqueladora Saroglia Torino | H5: Propalcote320 | I5: Plastificado mate | J5: Full color | L5: En diseño | P5: Fuente | Q5: Proyecto Imprenta UM
A6: Hospital | B6: Certificado | D6: Calidad | G6: Troqueladora Chandler USA | H6: Opalina | I6: Plastificado brillante | L6: Pendiente info
A7: IPS | B7: Diploma | D7: Cerrada | G7: Troqueladora Heidelberg | H7: Cartulina | I7: Perforado | L7: Rechazada
A8: Bienestar Universitario | B8: Tarjeta | D8: Cancelada | G8: Guillotina Perfecta Polygraph | H8: Adhesivo | I8: Anillado | L8: Cancelada
A9: Comunicaciones | B9: Sticker/Etiqueta | D9: En espera Compras | G9: Plastificadora | H9: Otro | I9: Grapado
A10: Admisiones | B10: MiniBlocks | D10: Compras Planchas | G10: Taladro Vertical Drp Kerma | I10: Tinta Seguridad
A11: Biblioteca | B11: Memos | G11: Otro | I11: Otro
A12: Otra | B12: Agendas
B13: Actas de grado
B14: Tarjetas Prestamo Biblioteca
B15: Bolsillos de tarjeta de préstamo
B16: Adhesivos de Colores

Sheet 06_Dashboard
A1: Dashboard Operativo - Imprenta UM
A3: KPI | B3: Valor | D3: Estado OT | E3: Cantidad
A4: Solicitudes recibidas | B4: =COUNTIF('02_Base_Solicitudes'!A2:A201,">0") -> 28 | D4: Abierta | E4: =COUNTIFS('03_OT_Maestra'!$A$4:$A$203,"OT-UM-*",'03_OT_Maestra'!$AH$4:$AH$203,D4) -> 1
A5: Solicitudes completas | B5: =COUNTIF('02_Base_Solicitudes'!O2:P201,"Completa") -> 28 | D5: Diseño | E5: =COUNTIFS('03_OT_Maestra'!$A$4:$A$203,"OT-UM-*",'03_OT_Maestra'!$AH$4:$AH$203,D5) -> 3
A6: OT creadas | B6: =COUNTIF('03_OT_Maestra'!A4:A203,"OT-UM-*") -> 28 | D6: Preprensa | E6: =COUNTIFS('03_OT_Maestra'!$A$4:$A$203,"OT-UM-*",'03_OT_Maestra'!$AH$4:$AH$203,D6) -> 2
A7: OT cerradas | B7: =COUNTIF('03_OT_Maestra'!AH4:AH203,"Cerrada") -> 20 | D7: Producción | E7: =COUNTIFS('03_OT_Maestra'!$A$4:$A$203,"OT-UM-*",'03_OT_Maestra'!$AH$4:$AH$203,D7) -> 2
A8: OT en riesgo SLA | B8: =COUNTIF('02_Base_Solicitudes'!Q2:R201,"Riesgo SLA") -> 1 | D8: Calidad | E8: =COUNTIFS('03_OT_Maestra'!$A$4:$A$203,"OT-UM-*",'03_OT_Maestra'!$AH$4:$AH$203,D8) -> 0
A9: SLA cumplido | B9: =COUNTIF('03_OT_Maestra'!AJ4:AJ203,"Sí") -> 19 | D9: Cerrada | E9: =COUNTIFS('03_OT_Maestra'!$A$4:$A$203,"OT-UM-*",'03_OT_Maestra'!$AH$4:$AH$203,D9) -> 20
A10: Merma total | B10: =SUM('03_OT_Maestra'!AB4:AB203) -> 3300 | D10: En espera Compras | E10: =COUNTIFS('03_OT_Maestra'!$A$4:$A$203,"OT-UM-*",'03_OT_Maestra'!$AH$4:$AH$203,D10) -> 0
D11: Compras Planchas | E11: =COUNTIFS('03_OT_Maestra'!$A$4:$A$203,"OT-UM-*",'03_OT_Maestra'!$AH$4:$AH$203,D11) -> 0
